Workbook
Name _100__Premium: #REF!
Name _100__Premium: '[3]Bound Portfolio Report'!$AA$8:$AA$10000
Name _100__Premium: #REF!
Name _100__Premium: #REF!
Name _100__Premium: #REF!
Name _100__Premium: #REF!
Name _100__Premium: #REF!
Name _100_AEP: #REF!
Name _100_AEP: #REF!
Name _100_AEP: '[3]Bound Portfolio Report'!$BF$8:$BF$10000
Name _100_AEP: #REF!
Name _100_AEP: #REF!
Name _100_AEP: #REF!
Name _100_AEP: '[4]Bound Portfolio Report'!$BF$8:$BF$10000
Name _500_AEP: #REF!
Name _500_AEP: #REF!
Name _500_AEP: '[3]Bound Portfolio Report'!$BG$8:$BG$10000
Name _500_AEP: #REF!
Name _500_AEP: #REF!
Name _500_AEP: #REF!
Name _500_AEP: '[4]Bound Portfolio Report'!$BG$8:$BG$10000
Name _AREResultPropertyNames: '[3]~AnalyzeReAddIn'!$B$1:$B$30
Name Actual___of_AUM: #REF!
Name Actual___of_AUM: '[3]Bound Portfolio Report'!$BH$8:$BH$10000
Name Actual___of_AUM: #REF!
Name Actual___of_AUM: #REF!
Name Actual___of_AUM: #REF!
Name Actual___of_AUM: #REF!
Name Actual___of_AUM: #REF!
Name Aggregate_Limit__100: '[3]Bound Portfolio Report'!$Z$8:$Z$10000
Name Aggregate_Limit__100: #REF!
Name Aggregate_Limit__100: #REF!
Name Aggregate_Limit__100: #REF!
Name AIR_ARe_CipherID: [3]BoundLayerDB!$E$3:$E$1048576
Name AIR_ARe_CipherID: #REF!
Name AIR_ARe_CipherID: #REF!
Name AIR_ARe_LayerID: [3]BoundLayerDB!$D$3:$D$1048576
Name AIR_ARe_LayerID: #REF!
Name AIR_ARe_LayerID: #REF!
Name Avg_Rate_Change_Projection: #REF!
Name Avg_Rate_Change_Projection: #REF!
Name Avg_Rate_Change_Projection: #REF!
Name Bond_Price__Binding: #REF!
Name Bond_Price__Binding: #REF!
Name Bond_Price__Binding: #REF!
Name Bound_Date: '[3]Bound Portfolio Report'!$O$8:$O$10000
Name Bound_Date: #REF!
Name Bound_Date: #REF!
Name Bound_Date: #REF!
Name CipherID: #REF!
Name CipherID: #REF!
Name CipherID: #REF!
Name Co_TVAR_100: #REF!
Name Co_TVAR_100: #REF!
Name Co_TVAR_100: '[3]Bound Portfolio Report'!$BR$8:$BR$10000
Name Co_TVAR_100: #REF!
Name Co_TVAR_100: #REF!
Name Co_TVAR_100: #REF!
Name Co_TVAR_100: '[4]Bound Portfolio Report'!$BR$8:$BR$10000
Name Co_TVAR_1000: #REF!

Sheet Summary
A1: Report Name
A3: Portfolio Name
A4: Vendor
A5: Report Date
A6: PortfolioID
A7: ReportID
A8: Fronting
A9: SecurityInstrument
A10: AsOfDate
A11: Run Off
A12: IncludeExpired
A13: Total AUM
A14: Deployed AUM

Sheet Inputs
A1: Input Name | B1: Input Values | F1: Input Values
A2: PortfolioID | B2: 900000005 | F2: 4 | I2: 1
A3: ReportDate | B3: 46225 | F3: 44835 | I3: 786
A4: Vendor | B4: AIR | F4: PIMCOVIEW | I4: PIMCOVIEW
A5: Fronting | B5: all | F5: all | I5: all
A6: SecurityInstrument | B6: all | F6: all | I6: all
A7: AsOfDate | B7: 46225 | F7: 44835 | I7: =I3 -> 786
A8: RunOff | B8: 0 | F8: 0 | I8: 0
A9: IncludeExpired | B9: 1 | F9: 1 | I9: 0
A10: ExportID | B10: 760870 | F10: 674684 | I10: 808561
A11: AEPType | B11: AEPTVAR
A12: AEPCoTVARType | B12: AEPCOTVAR

Sheet ILS Report- Combined
B1: KRC ILS Fund | C1: =#REF! -> #REF!
B2: Portfolio Summary | C2: Deployed Capital | D2: Available Capital | H2: NAV | M2: Modeled Assumptions
B3: Market Value ($) | C3: ='P&L'!C1 -> 3750000 | D3: ='P&L'!C2 -> 4000000 | H3: Tail Risk Summary | J3: Deployed | K3: Available | N3: Return Ratios | O3: Deployed % NAV | P3: Available % NAV
B4: Gross Notional ($) | C4: ='P&L'!B38 -> 5250000 | D4: ='P&L'!B38 -> 5250000 | I4: USD | J4: % NAV | K4: % NAV | M4: Expected_Return Excess | N4: =VLOOKUP(M4,'P&L'!$A$25:$C$47,2,0) -> 610841 | O4: =N4/$C$3 -> 0.16289093 | P4: =N4/$D$3 -> 0.15271025
H5: Total - All Perils | I5: ='Region Peril'!AE28 -> 0 | J5: =I5/$C$3 -> 0 | K5: =I5/$D$3 -> 0 | M5: Expected_Return Net | N5: =VLOOKUP(M5,'P&L'!$A$25:$C$47,2,0) -> 557316 | O5: =N5/$C$3 -> 0.1486176 | P5: =N5/$D$3 -> 0.139329
H6: Top 5 Peril regions | M6: Standard Deviation | N6: =VLOOKUP(M6,'P&L'!$A$25:$C$47,2,0) -> 436656 | O6: =N6/$C$3 -> 0.1164416 | P6: =N6/$D$3 -> 0.109164
B7: Gross Written Premium | C7: ='P&L'!B5/'ILS Report- Combined'!C3 -> 0.20145253 | D7: ='P&L'!B5/'ILS Report- Combined'!D3 -> 0.18886175 | H7: =INDEX('Region Peril'!$X$5:$X$9,MATCH(I7,'Region Peril'!$AE$5:$AE$9,0)) -> #NUM! | I7: =SMALL('Region Peril'!$AE$5:$AE$9,1) -> #NUM! | J7: =I7/$C$3 -> #NUM! | K7: =I7/$D$3 -> #NUM! | M7: Sharpe Ratio | N7: =VLOOKUP(M7,'P&L'!$A$25:$C$47,2,0) -> 1.2763274
H8: =INDEX('Region Peril'!$X$5:$X$9,MATCH(I8,'Region Peril'!$AE$5:$AE$9,0)) -> #NUM! | I8: =SMALL('Region Peril'!$AE$5:$AE$9,2) -> #NUM! | J8: =I8/$C$3 -> #NUM! | K8: =I8/$D$3 -> #NUM! | M8: CV | N8: =VLOOKUP(M8,'P&L'!$A$25:$C$47,2,0) -> 0.78349805
B9: Gross Expected Loss | C9: =-'P&L'!$B$9/C3 -> -0.0385616 | D9: =-'P&L'!$B$9/D3 -> -0.0361515 | H9: =INDEX('Region Peril'!$X$5:$X$9,MATCH(I9,'Region Peril'!$AE$5:$AE$9,0)) -> #NUM! | I9: =SMALL('Region Peril'!$AE$5:$AE$9,3) -> #NUM! | J9: =I9/$C$3 -> #NUM! | K9: =I9/$D$3 -> #NUM! | M9: Best Reasonable Outcome | N9: =VLOOKUP(M9,'P&L'!$A$23:$C$40,2,0) -> 701922 | O9: =N9/$C$3 -> 0.1871792 | P9: =N9/$D$3 -> 0.1754805
B10: Expense | C10: =-('P&L'!$B$7+'P&L'!$B$10+'P&L'!$B$11+'P&L'!$B$12+'P&L'!$B$16+'P&L'!$B$17+'P&L'!$B$18)/C3 -> -0.016853333 | D10: =-('P&L'!$B$7+'P&L'!$B$10+'P&L'!$B$11+'P&L'!$B$12+'P&L'!$B$16+'P&L'!$B$17+'P&L'!$B$18)/D3 -> -0.0158 | H10: =INDEX('Region Peril'!$X$5:$X$9,MATCH(I10,'Region Peril'!$AE$5:$AE$9,0)) -> #NUM! | I10: =SMALL('Region Peril'!$AE$5:$AE$9,4) -> #NUM! | J10: =I10/$C$3 -> #NUM! | K10: =I10/$D$3 -> #NUM! | M10: Omega Ratio | N10: =ABS(SUMIF('EP Curve'!F1:F10002,">0")/SUMIF('EP Curve'!F1:F10002,"<0")) -> 12.266849
B11: Investment Income | C11: ='P&L'!$B$15/'ILS Report- Combined'!C3 -> 0.00258 | D11: ='P&L'!$B$15/'ILS Report- Combined'!D3 -> 0.00241875 | H11: =INDEX('Region Peril'!$X$5:$X$9,MATCH(I11,'Region Peril'!$AE$5:$AE$9,0)) -> #NUM! | I11: =SMALL('Region Peril'!$AE$5:$AE$9,5) -> #NUM! | J11: =I11/$C$3 -> #NUM! | K11: =I11/$D$3 -> #NUM! | M11: ProbabilityofLoss | N11: =VLOOKUP(M11,'P&L'!$A$25:$C$47,2,0) -> 0.0715
H12: Liquidity Provisions | J12: 0.025 | K12: 0.025 | M12: 1 in 100 yr PML | N12: =VLOOKUP(M12,'P&L'!$A$25:$C$47,2,0) -> -1785420.8 | O12: =N12/$C$3 -> -0.4761122 | P12: =N12/$D$3 -> -0.44635519
B13: Gross Total Return | C13: =SUM(C7:C11) -> 0.1486176 | D13: =SUM(D7:D11) -> 0.139329 | I13: USD | J13: % NAV | K13: % NAV | M13: 1 in 250 yr PML | N13: =VLOOKUP(M13,'P&L'!$A$25:$C$47,2,0) -> -2007508.3 | O13: =N13/$C$3 -> -0.53533555 | P13: =N13/$D$3 -> -0.50187708
M14: 1% TVaR | N14: =VLOOKUP(M14,'P&L'!$A$25:$C$47,2,0) -> -2035586.4
B15: Number of Positions | C15: =BoundPositions!$C$2 -> 0 | M15: RAROC (99%) | N15: =VLOOKUP(M15,'P&L'!$A$25:$C$47,2,0) -> 0.31214827
M16: Notional Occurrence Limits (Short) | N16: =VLOOKUP(M16,'P&L'!$A$25:$C$47,2,0) -> 5250000
M17: =3&":"&3 -> 3:3 | N17: =5&":"&5 -> 5:5 | O17: =8&":"&8 -> 8:8 | P17: =7&":"&7 -> 7:7
B18: Exposure Summary | D18: ='P&L'!B8 -> 755447 | M18: Scenario Analysis
B19: Peril | C19: Region | D19: Expected Loss (% of total AAL) | E19: TVAR Allocation (% of Deployed Capital) | F19: CoTVAR Allocation (% of WWAP) | M19: Description | N19: Industry Loss($B) | O19: P&L | P19: P&L(Event)
B20: US Hurricane | C20: Florida Hurricane | D20: =VLOOKUP($C20,'Region Peril'!$B$4:$C$80,2,FALSE)/'P&L'!$B$9 -> 0.12822723 | E20: =VLOOKUP($C20,'Region Peril'!$B$4:$F$80,5,FALSE)/$C$3 -> 0.25062758 | F20: =VLOOKUP($C20,'Region Peril'!$B$4:$G$80,6,FALSE)/'Region Peril'!$G$5 -> 0.070743483 | M20: =INDEX(HistoricalEvents!$D$4:$D$953,MATCH(O20,HistoricalEvents!$G$4:$G$953,0)) -> 0 | N20: =(INDEX(HistoricalEvents!$E$4:$E$13,MATCH(O20,HistoricalEvents!$H$4:$H$13,0)))/1000000000 -> #N/A | O20: =SMALL(HistoricalEvents!$D$4:$G$13,1) -> 1 | P20: =SMALL(HistoricalEvents!$D$4:$G$13,1) -> 1
C21: Northeast Hurricane | D21: =VLOOKUP($C21,'Region Peril'!$B$4:$C$80,2,FALSE)/'P&L'!$B$9 -> 0.099249378 | E21: =VLOOKUP($C21,'Region Peril'!$B$4:$F$80,5,FALSE)/$C$3 -> 0.311902 | F21: =VLOOKUP($C21,'Region Peril'!$B$4:$G$80,6,FALSE)/'Region Peril'!$G$5 -> 0.016072806 | M21: =INDEX(HistoricalEvents!$D$4:$D$953,MATCH(O21,HistoricalEvents!$G$4:$G$953,0)) -> 0 | N21: =(INDEX(HistoricalEvents!$E$4:$E$13,MATCH(O21,HistoricalEvents!$H$4:$H$13,0)))/1000000000 -> #N/A | O21: =SMALL(HistoricalEvents!$D$4:$G$13,2) -> 3 | P21: =SMALL(HistoricalEvents!$D$4:$G$13,2) -> 3
C22: Texas Hurricane | D22: =VLOOKUP($C22,'Region Peril'!$B$4:$C$80,2,FALSE)/'P&L'!$B$9 -> 0.1305802 | E22: =VLOOKUP($C22,'Region Peril'!$B$4:$F$80,5,FALSE)/$C$3 -> 0.2701928 | F22: =VLOOKUP($C22,'Region Peril'!$B$4:$G$80,6,FALSE)/'Region Peril'!$G$5 -> 0.01493253 | M22: =INDEX(HistoricalEvents!$D$4:$D$953,MATCH(O22,HistoricalEvents!$G$4:$G$953,0)) -> 0 | N22: =(INDEX(HistoricalEvents!$E$4:$E$13,MATCH(O22,HistoricalEvents!$H$4:$H$13,0)))/1000000000 -> #N/A | O22: =SMALL(HistoricalEvents!$D$4:$G$13,3) -> 5 | P22: =SMALL(HistoricalEvents!$D$4:$G$13,3) -> 5
C23: Louisiana Hurricane | D23: =VLOOKUP($C23,'Region Peril'!$B$4:$C$80,2,FALSE)/'P&L'!$B$9 -> 0.33989417 | E23: =VLOOKUP($C23,'Region Peril'!$B$4:$F$80,5,FALSE)/$C$3 -> 0.66365616 | F23: =VLOOKUP($C23,'Region Peril'!$B$4:$G$80,6,FALSE)/'Region Peril'!$G$5 -> 0.77208582 | M23: =INDEX(HistoricalEvents!$D$4:$D$953,MATCH(O23,HistoricalEvents!$G$4:$G$953,0)) -> 0 | N23: =(INDEX(HistoricalEvents!$E$4:$E$13,MATCH(O23,HistoricalEvents!$H$4:$H$13,0)))/1000000000 -> #N/A | O23: =SMALL(HistoricalEvents!$D$4:$G$13,4) -> 6 | P23: =SMALL(HistoricalEvents!$D$4:$G$13,4) -> 6
C24: Southeast Hurricane | D24: =VLOOKUP($C24,'Region Peril'!$B$4:$C$80,2,FALSE)/'P&L'!$B$9 -> 0.13440718 | E24: =VLOOKUP($C24,'Region Peril'!$B$4:$F$80,5,FALSE)/$C$3 -> 0.32743279 | F24: =VLOOKUP($C24,'Region Peril'!$B$4:$G$80,6,FALSE)/'Region Peril'!$G$5 -> 0.032701037 | M24: =INDEX(HistoricalEvents!$D$4:$D$953,MATCH(O24,HistoricalEvents!$G$4:$G$953,0)) -> 5.1288171e+08 | N24: =(INDEX(HistoricalEvents!$E$4:$E$13,MATCH(O24,HistoricalEvents!$H$4:$H$13,0)))/1000000000 -> #N/A | O24: =SMALL(HistoricalEvents!$D$4:$G$13,5) -> 9 | P24: =SMALL(HistoricalEvents!$D$4:$G$13,5) -> 9
C25: Gulf of Mexico WS | D25: =VLOOKUP($C25,'Region Peril'!$B$4:$C$80,2,FALSE)/'P&L'!$B$9 -> 0.37843743 | E25: =VLOOKUP($C25,'Region Peril'!$B$4:$F$80,5,FALSE)/$C$3 -> 0.66690766 | F25: =VLOOKUP($C25,'Region Peril'!$B$4:$G$80,6,FALSE)/'Region Peril'!$G$5 -> 0.82440829 | M25: =INDEX(HistoricalEvents!$D$4:$D$953,MATCH(O25,HistoricalEvents!$G$4:$G$953,0)) -> 8.9098664e+08 | N25: =(INDEX(HistoricalEvents!$E$4:$E$13,MATCH(O25,HistoricalEvents!$H$4:$H$13,0)))/1000000000 -> #N/A | O25: =SMALL(HistoricalEvents!$D$4:$G$13,6) -> 11 | P25: =SMALL(HistoricalEvents!$D$4:$G$13,6) -> 11
B26: Earthquake | C26: California Earthquake | D26: =VLOOKUP($C26,'Region Peril'!$B$4:$C$80,2,FALSE)/'P&L'!$B$9 -> 0.002027789 | E26: =VLOOKUP($C26,'Region Peril'!$B$4:$F$80,5,FALSE)/$C$3 -> 0.007819479 | F26: =VLOOKUP($C26,'Region Peril'!$B$4:$G$80,6,FALSE)/'Region Peril'!$G$5 -> 0.00091323884 | M26: =INDEX(HistoricalEvents!$D$4:$D$953,MATCH(O26,HistoricalEvents!$G$4:$G$953,0)) -> 3.570069e+08 | N26: =(INDEX(HistoricalEvents!$E$4:$E$13,MATCH(O26,HistoricalEvents!$H$4:$H$13,0)))/1000000000 -> #N/A | O26: =SMALL(HistoricalEvents!$D$4:$G$13,7) -> 17 | P26: =SMALL(HistoricalEvents!$D$4:$G$13,7) -> 17
C27: US Earthquake xCA | D27: =VLOOKUP($C27,'Region Peril'!$B$4:$C$80,2,FALSE)/'P&L'!$B$9 -> #N/A | E27: =VLOOKUP($C27,'Region Peril'!$B$4:$F$80,5,FALSE)/$C$3 -> #N/A | F27: =VLOOKUP($C27,'Region Peril'!$B$4:$G$80,6,FALSE)/'Region Peril'!$G$5 -> #N/A | M27: =INDEX(HistoricalEvents!$D$4:$D$953,MATCH(O27,HistoricalEvents!$G$4:$G$953,0)) -> 3.570069e+08 | N27: =(INDEX(HistoricalEvents!$E$4:$E$13,MATCH(O27,HistoricalEvents!$H$4:$H$13,0)))/1000000000 -> #N/A | O27: =SMALL(HistoricalEvents!$D$4:$G$13,8) -> 17 | P27: =SMALL(HistoricalEvents!$D$4:$G$13,8) -> 17
C28: Europe Earthquake | D28: =VLOOKUP($C28,'Region Peril'!$B$4:$C$80,2,FALSE)/'P&L'!$B$9 -> 0 | E28: =VLOOKUP($C28,'Region Peril'!$B$4:$F$80,5,FALSE)/$C$3 -> 0 | F28: =VLOOKUP($C28,'Region Peril'!$B$4:$G$80,6,FALSE)/'Region Peril'!$G$5 -> 0 | M28: =INDEX(HistoricalEvents!$D$4:$D$953,MATCH(O28,HistoricalEvents!$G$4:$G$953,0)) -> 1.9919565e+08 | N28: =(INDEX(HistoricalEvents!$E$4:$E$13,MATCH(O28,HistoricalEvents!$H$4:$H$13,0)))/1000000000 -> #N/A | O28: =SMALL(HistoricalEvents!$D$4:$G$13,9) -> 52 | P28: =SMALL(HistoricalEvents!$D$4:$G$13,9) -> 52
C29: Japan Earthquake | D29: =VLOOKUP($C29,'Region Peril'!$B$4:$C$80,2,FALSE)/'P&L'!$B$9 -> 0 | E29: =VLOOKUP($C29,'Region Peril'!$B$4:$F$80,5,FALSE)/$C$3 -> 0 | F29: =VLOOKUP($C29,'Region Peril'!$B$4:$G$80,6,FALSE)/'Region Peril'!$G$5 -> 0 | M29: =INDEX(HistoricalEvents!$D$4:$D$953,MATCH(O29,HistoricalEvents!$G$4:$G$953,0)) -> 3.4529243e+08 | N29: =(INDEX(HistoricalEvents!$E$4:$E$13,MATCH(O29,HistoricalEvents!$H$4:$H$13,0)))/1000000000 -> #N/A | O29: =SMALL(HistoricalEvents!$D$4:$G$13,10) -> 66 | P29: =SMALL(HistoricalEvents!$D$4:$G$13,10) -> 66
C30: Mexico Earthquake | D30: =VLOOKUP($C30,'Region Peril'!$B$4:$C$80,2,FALSE)/'P&L'!$B$9 -> 0 | E30: =VLOOKUP($C30,'Region Peril'!$B$4:$F$80,5,FALSE)/$C$3 -> 0 | F30: =VLOOKUP($C30,'Region Peril'!$B$4:$G$80,6,FALSE)/'Region Peril'!$G$5 -> 0
C31: South America Earthquake | D31: =VLOOKUP($C31,'Region Peril'!$B$4:$C$80,2,FALSE)/'P&L'!$B$9 -> 0 | E31: =VLOOKUP($C31,'Region Peril'!$B$4:$F$80,5,FALSE)/$C$3 -> 0 | F31: =VLOOKUP($C31,'Region Peril'!$B$4:$G$80,6,FALSE)/'Region Peril'!$G$5 -> 0
B32: Typhoon/WinterStorm | C32: Japan Typhoon | D32: =VLOOKUP($C32,'Region Peril'!$B$4:$C$80,2,FALSE)/'P&L'!$B$9 -> 0 | E32: =VLOOKUP($C32,'Region Peril'!$B$4:$F$80,5,FALSE)/$C$3 -> 0 | F32: =VLOOKUP($C32,'Region Peril'!$B$4:$G$80,6,FALSE)/'Region Peril'!$G$5 -> 0
C33: Europe Tropical Cyclone | D33: =VLOOKUP($C33,'Region Peril'!$B$4:$C$80,2,FALSE)/'P&L'!$B$9 -> 0 | E33: =VLOOKUP($C33,'Region Peril'!$B$4:$F$80,5,FALSE)/$C$3 -> 0 | F33: =VLOOKUP($C33,'Region Peril'!$B$4:$G$80,6,FALSE)/'Region Peril'!$G$5 -> 0
C34: Mexico Hurricane | D34: =VLOOKUP($C34,'Region Peril'!$B$4:$C$80,2,FALSE)/'P&L'!$B$9 -> 0.00027369026 | E34: =VLOOKUP($C34,'Region Peril'!$B$4:$F$80,5,FALSE)/$C$3 -> 0.0010553934 | F34: =VLOOKUP($C34,'Region Peril'!$B$4:$G$80,6,FALSE)/'Region Peril'!$G$5 -> 0
C35: US Winter Storm | D35: =VLOOKUP($C35,'Region Peril'!$B$4:$C$80,2,FALSE)/'P&L'!$B$9 -> 0.0007444827 | E35: =VLOOKUP($C35,'Region Peril'!$B$4:$F$80,5,FALSE)/$C$3 -> 0.0028708444 | F35: =VLOOKUP($C35,'Region Peril'!$B$4:$G$80,6,FALSE)/'Region Peril'!$G$5 -> 0
B36: Severe Convective Storm | C36: US Severe Storm | D36: =VLOOKUP($C36,'Region Peril'!$B$4:$C$80,2,FALSE)/'P&L'!$B$9 -> 0.0024378531 | E36: =VLOOKUP($C36,'Region Peril'!$B$4:$F$80,5,FALSE)/$C$3 -> 0.0094007514 | F36: =VLOOKUP($C36,'Region Peril'!$B$4:$G$80,6,FALSE)/'Region Peril'!$G$5 -> 0
B37: Inland Flood | C37: US Inland Flood | D37: =VLOOKUP($C37,'Region Peril'!$B$4:$C$80,2,FALSE)/'P&L'!$B$9 -> 0 | E37: =VLOOKUP($C37,'Region Peril'!$B$4:$F$80,5,FALSE)/$C$3 -> 0 | F37: =VLOOKUP($C37,'Region Peril'!$B$4:$G$80,6,FALSE)/'Region Peril'!$G$5 -> 0
B38: Wildfire | C38: US Wildfire | D38: =VLOOKUP($C38,'Region Peril'!$B$4:$C$80,2,FALSE)/'P&L'!$B$9 -> 0 | E38: =VLOOKUP($C38,'Region Peril'!$B$4:$F$80,5,FALSE)/$C$3 -> 0 | F38: =VLOOKUP($C38,'Region Peril'!$B$4:$G$80,6,FALSE)/'Region Peril'!$G$5 -> 0
B39: Terrorism | C39: Terrorism | D39: =VLOOKUP($C39,'Region Peril'!$B$4:$C$80,2,FALSE)/'P&L'!$B$9 -> 0 | E39: =VLOOKUP($C39,'Region Peril'!$B$4:$F$80,5,FALSE)/$C$3 -> 0 | F39: =VLOOKUP($C39,'Region Peril'!$B$4:$G$80,6,FALSE)/'Region Peril'!$G$5 -> 0
B40: All other WS | C40: All other WS | D40: =VLOOKUP($C40,'Region Peril'!$B$4:$C$80,2,FALSE)/'P&L'!$B$9 -> 0.0031979669 | E40: =VLOOKUP($C40,'Region Peril'!$B$4:$F$80,5,FALSE)/$C$3 -> 0.012331872 | F40: =VLOOKUP($C40,'Region Peril'!$B$4:$G$80,6,FALSE)/'Region Peril'!$G$5 -> 0
B41: All other EQ | C41: All other EQ | D41: =VLOOKUP($C41,'Region Peril'!$B$4:$C$80,2,FALSE)/'P&L'!$B$9 -> 0.00017288349 | E41: =VLOOKUP($C41,'Region Peril'!$B$4:$F$80,5,FALSE)/$C$3 -> 0.0006666664 | F41: =VLOOKUP($C41,'Region Peril'!$B$4:$G$80,6,FALSE)/'Region Peril'!$G$5 -> 0
B43: Exposure detail | C43: Expected Loss (% of Total AAL)
B44: Region/Peril | C44: Total | D44: CAT Bond | E44: Retro QS | F44: Reinsurance | G44: Retro XOL | H44: ILW Long | I44: ILW Short
A45: 1 | B45: =INDEX('Region Peril'!$B$4:$B$80, MATCH(LARGE('Region Peril'!$C$4:$C$80, $A45), 'Region Peril'!$C$4:$C$80, 0)) -> WWAP | C45: =LARGE('Region Peril'!$C$4:$C$80,$A45)/'P&L'!$B$9 -> 0.99999673 | D45: =LARGE('Region Peril'!$C$4:$C$80,$A45)/'P&L'!$B$9 -> 0.99999673 | E45: =VLOOKUP($B45,'Region Peril'!$B$4:$Q$80,MATCH('ILS Report- Combined'!E$44,'Region Peril'!$B$4:$Q$4,0),0)/'P&L'!$B$9 -> 0 | F45: =VLOOKUP($B45,'Region Peril'!$B$4:$Q$80,MATCH('ILS Report- Combined'!F$44,'Region Peril'!$B$4:$Q$4,0),0)/'P&L'!$B$9 -> 0 | G45: =VLOOKUP($B45,'Region Peril'!$B$4:$Q$80,MATCH('ILS Report- Combined'!G$44,'Region Peril'!$B$4:$Q$4,0),0)/'P&L'!$B$9 -> 0 | H45: =VLOOKUP($B45,'Region Peril'!$B$4:$Q$80,MATCH('ILS Report- Combined'!H$44,'Region Peril'!$B$4:$Q$4,0),0)/'P&L'!$B$9 -> 0 | I45: =VLOOKUP($B45,'Region Peril'!$B$4:$Q$80,MATCH('ILS Report- Combined'!I$44,'Region Peril'!$B$4:$Q$4,0),0)/'P&L'!$B$9 -> 0
A46: 2 | B46: =INDEX('Region Peril'!$B$4:$B$80, MATCH(LARGE('Region Peril'!$C$4:$C$80, $A46), 'Region Peril'!$C$4:$C$80, 0)) -> US Hurricanes | C46: =LARGE('Region Peril'!$C$4:$C$80,$A46)/'P&L'!$B$9 -> 0.98966534 | D46: =LARGE('Region Peril'!$C$4:$C$80,$A46)/'P&L'!$B$9 -> 0.98966534 | E46: =VLOOKUP($B46,'Region Peril'!$B$4:$Q$80,MATCH('ILS Report- Combined'!E$44,'Region Peril'!$B$4:$Q$4,0),0)/'P&L'!$B$9 -> 0 | F46: =VLOOKUP($B46,'Region Peril'!$B$4:$Q$80,MATCH('ILS Report- Combined'!F$44,'Region Peril'!$B$4:$Q$4,0),0)/'P&L'!$B$9 -> 0 | G46: =VLOOKUP($B46,'Region Peril'!$B$4:$Q$80,MATCH('ILS Report- Combined'!G$44,'Region Peril'!$B$4:$Q$4,0),0)/'P&L'!$B$9 -> 0 | H46: =VLOOKUP($B46,'Region Peril'!$B$4:$Q$80,MATCH('ILS Report- Combined'!H$44,'Region Peril'!$B$4:$Q$4,0),0)/'P&L'!$B$9 -> 0 | I46: =VLOOKUP($B46,'Region Peril'!$B$4:$Q$80,MATCH('ILS Report- Combined'!I$44,'Region Peril'!$B$4:$Q$4,0),0)/'P&L'!$B$9 -> 0
A47: 3 | B47: =INDEX('Region Peril'!$B$4:$B$80, MATCH(LARGE('Region Peril'!$C$4:$C$80, $A47), 'Region Peril'!$C$4:$C$80, 0)) -> Gulf of Mexico WS | C47: =LARGE('Region Peril'!$C$4:$C$80,$A47)/'P&L'!$B$9 -> 0.37843743 | D47: =LARGE('Region Peril'!$C$4:$C$80,$A47)/'P&L'!$B$9 -> 0.37843743 | E47: =VLOOKUP($B47,'Region Peril'!$B$4:$Q$80,MATCH('ILS Report- Combined'!E$44,'Region Peril'!$B$4:$Q$4,0),0)/'P&L'!$B$9 -> 0 | F47: =VLOOKUP($B47,'Region Peril'!$B$4:$Q$80,MATCH('ILS Report- Combined'!F$44,'Region Peril'!$B$4:$Q$4,0),0)/'P&L'!$B$9 -> 0 | G47: =VLOOKUP($B47,'Region Peril'!$B$4:$Q$80,MATCH('ILS Report- Combined'!G$44,'Region Peril'!$B$4:$Q$4,0),0)/'P&L'!$B$9 -> 0 | H47: =VLOOKUP($B47,'Region Peril'!$B$4:$Q$80,MATCH('ILS Report- Combined'!H$44,'Region Peril'!$B$4:$Q$4,0),0)/'P&L'!$B$9 -> 0 | I47: =VLOOKUP($B47,'Region Peril'!$B$4:$Q$80,MATCH('ILS Report- Combined'!I$44,'Region Peril'!$B$4:$Q$4,0),0)/'P&L'!$B$9 -> 0
A48: 4 | B48: =INDEX('Region Peril'!$B$4:$B$80, MATCH(LARGE('Region Peril'!$C$4:$C$80, $A48), 'Region Peril'!$C$4:$C$80, 0)) -> Louisiana Hurricane | C48: =LARGE('Region Peril'!$C$4:$C$80,$A48)/'P&L'!$B$9 -> 0.33989417 | D48: =LARGE('Region Peril'!$C$4:$C$80,$A48)/'P&L'!$B$9 -> 0.33989417 | E48: =VLOOKUP($B48,'Region Peril'!$B$4:$Q$80,MATCH('ILS Report- Combined'!E$44,'Region Peril'!$B$4:$Q$4,0),0)/'P&L'!$B$9 -> 0 | F48: =VLOOKUP($B48,'Region Peril'!$B$4:$Q$80,MATCH('ILS Report- Combined'!F$44,'Region Peril'!$B$4:$Q$4,0),0)/'P&L'!$B$9 -> 0 | G48: =VLOOKUP($B48,'Region Peril'!$B$4:$Q$80,MATCH('ILS Report- Combined'!G$44,'Region Peril'!$B$4:$Q$4,0),0)/'P&L'!$B$9 -> 0 | H48: =VLOOKUP($B48,'Region Peril'!$B$4:$Q$80,MATCH('ILS Report- Combined'!H$44,'Region Peril'!$B$4:$Q$4,0),0)/'P&L'!$B$9 -> 0 | I48: =VLOOKUP($B48,'Region Peril'!$B$4:$Q$80,MATCH('ILS Report- Combined'!I$44,'Region Peril'!$B$4:$Q$4,0),0)/'P&L'!$B$9 -> 0
A49: 5 | B49: =INDEX('Region Peril'!$B$4:$B$80, MATCH(LARGE('Region Peril'!$C$4:$C$80, $A49), 'Region Peril'!$C$4:$C$80, 0)) -> Southeast Hurricane | C49: =LARGE('Region Peril'!$C$4:$C$80,$A49)/'P&L'!$B$9 -> 0.13440718 | D49: =LARGE('Region Peril'!$C$4:$C$80,$A49)/'P&L'!$B$9 -> 0.13440718 | E49: =VLOOKUP($B49,'Region Peril'!$B$4:$Q$80,MATCH('ILS Report- Combined'!E$44,'Region Peril'!$B$4:$Q$4,0),0)/'P&L'!$B$9 -> 0 | F49: =VLOOKUP($B49,'Region Peril'!$B$4:$Q$80,MATCH('ILS Report- Combined'!F$44,'Region Peril'!$B$4:$Q$4,0),0)/'P&L'!$B$9 -> 0 | G49: =VLOOKUP($B49,'Region Peril'!$B$4:$Q$80,MATCH('ILS Report- Combined'!G$44,'Region Peril'!$B$4:$Q$4,0),0)/'P&L'!$B$9 -> 0 | H49: =VLOOKUP($B49,'Region Peril'!$B$4:$Q$80,MATCH('ILS Report- Combined'!H$44,'Region Peril'!$B$4:$Q$4,0),0)/'P&L'!$B$9 -> 0 | I49: =VLOOKUP($B49,'Region Peril'!$B$4:$Q$80,MATCH('ILS Report- Combined'!I$44,'Region Peril'!$B$4:$Q$4,0),0)/'P&L'!$B$9 -> 0
A50: 6 | B50: =INDEX('Region Peril'!$B$4:$B$80, MATCH(LARGE('Region Peril'!$C$4:$C$80, $A50), 'Region Peril'!$C$4:$C$80, 0)) -> Texas Hurricane | C50: =LARGE('Region Peril'!$C$4:$C$80,$A50)/'P&L'!$B$9 -> 0.1305802 | D50: =LARGE('Region Peril'!$C$4:$C$80,$A50)/'P&L'!$B$9 -> 0.1305802 | E50: =VLOOKUP($B50,'Region Peril'!$B$4:$Q$80,MATCH('ILS Report- Combined'!E$44,'Region Peril'!$B$4:$Q$4,0),0)/'P&L'!$B$9 -> 0 | F50: =VLOOKUP($B50,'Region Peril'!$B$4:$Q$80,MATCH('ILS Report- Combined'!F$44,'Region Peril'!$B$4:$Q$4,0),0)/'P&L'!$B$9 -> 0 | G50: =VLOOKUP($B50,'Region Peril'!$B$4:$Q$80,MATCH('ILS Report- Combined'!G$44,'Region Peril'!$B$4:$Q$4,0),0)/'P&L'!$B$9 -> 0 | H50: =VLOOKUP($B50,'Region Peril'!$B$4:$Q$80,MATCH('ILS Report- Combined'!H$44,'Region Peril'!$B$4:$Q$4,0),0)/'P&L'!$B$9 -> 0 | I50: =VLOOKUP($B50,'Region Peril'!$B$4:$Q$80,MATCH('ILS Report- Combined'!I$44,'Region Peril'!$B$4:$Q$4,0),0)/'P&L'!$B$9 -> 0
A51: 7 | B51: =INDEX('Region Peril'!$B$4:$B$80, MATCH(LARGE('Region Peril'!$C$4:$C$80, $A51), 'Region Peril'!$C$4:$C$80, 0)) -> Florida Hurricane | C51: =LARGE('Region Peril'!$C$4:$C$80,$A51)/'P&L'!$B$9 -> 0.12822723 | D51: =LARGE('Region Peril'!$C$4:$C$80,$A51)/'P&L'!$B$9 -> 0.12822723 | E51: =VLOOKUP($B51,'Region Peril'!$B$4:$Q$80,MATCH('ILS Report- Combined'!E$44,'Region Peril'!$B$4:$Q$4,0),0)/'P&L'!$B$9 -> 0 | F51: =VLOOKUP($B51,'Region Peril'!$B$4:$Q$80,MATCH('ILS Report- Combined'!F$44,'Region Peril'!$B$4:$Q$4,0),0)/'P&L'!$B$9 -> 0 | G51: =VLOOKUP($B51,'Region Peril'!$B$4:$Q$80,MATCH('ILS Report- Combined'!G$44,'Region Peril'!$B$4:$Q$4,0),0)/'P&L'!$B$9 -> 0 | H51: =VLOOKUP($B51,'Region Peril'!$B$4:$Q$80,MATCH('ILS Report- Combined'!H$44,'Region Peril'!$B$4:$Q$4,0),0)/'P&L'!$B$9 -> 0 | I51: =VLOOKUP($B51,'Region Peril'!$B$4:$Q$80,MATCH('ILS Report- Combined'!I$44,'Region Peril'!$B$4:$Q$4,0),0)/'P&L'!$B$9 -> 0
A52: 8 | B52: =INDEX('Region Peril'!$B$4:$B$80, MATCH(LARGE('Region Peril'!$C$4:$C$80, $A52), 'Region Peril'!$C$4:$C$80, 0)) -> Northeast Hurricane | C52: =LARGE('Region Peril'!$C$4:$C$80,$A52)/'P&L'!$B$9 -> 0.099249378 | D52: =LARGE('Region Peril'!$C$4:$C$80,$A52)/'P&L'!$B$9 -> 0.099249378 | E52: =VLOOKUP($B52,'Region Peril'!$B$4:$Q$80,MATCH('ILS Report- Combined'!E$44,'Region Peril'!$B$4:$Q$4,0),0)/'P&L'!$B$9 -> 0 | F52: =VLOOKUP($B52,'Region Peril'!$B$4:$Q$80,MATCH('ILS Report- Combined'!F$44,'Region Peril'!$B$4:$Q$4,0),0)/'P&L'!$B$9 -> 0 | G52: =VLOOKUP($B52,'Region Peril'!$B$4:$Q$80,MATCH('ILS Report- Combined'!G$44,'Region Peril'!$B$4:$Q$4,0),0)/'P&L'!$B$9 -> 0 | H52: =VLOOKUP($B52,'Region Peril'!$B$4:$Q$80,MATCH('ILS Report- Combined'!H$44,'Region Peril'!$B$4:$Q$4,0),0)/'P&L'!$B$9 -> 0 | I52: =VLOOKUP($B52,'Region Peril'!$B$4:$Q$80,MATCH('ILS Report- Combined'!I$44,'Region Peril'!$B$4:$Q$4,0),0)/'P&L'!$B$9 -> 0
A53: 9 | B53: =INDEX('Region Peril'!$B$4:$B$80, MATCH(LARGE('Region Peril'!$C$4:$C$80, $A53), 'Region Peril'!$C$4:$C$80, 0)) -> All other WS | C53: =LARGE('Region Peril'!$C$4:$C$80,$A53)/'P&L'!$B$9 -> 0.0031979669 | D53: =LARGE('Region Peril'!$C$4:$C$80,$A53)/'P&L'!$B$9 -> 0.0031979669 | E53: =VLOOKUP($B53,'Region Peril'!$B$4:$Q$80,MATCH('ILS Report- Combined'!E$44,'Region Peril'!$B$4:$Q$4,0),0)/'P&L'!$B$9 -> 0 | F53: =VLOOKUP($B53,'Region Peril'!$B$4:$Q$80,MATCH('ILS Report- Combined'!F$44,'Region Peril'!$B$4:$Q$4,0),0)/'P&L'!$B$9 -> 0 | G53: =VLOOKUP($B53,'Region Peril'!$B$4:$Q$80,MATCH('ILS Report- Combined'!G$44,'Region Peril'!$B$4:$Q$4,0),0)/'P&L'!$B$9 -> 0 | H53: =VLOOKUP($B53,'Region Peril'!$B$4:$Q$80,MATCH('ILS Report- Combined'!H$44,'Region Peril'!$B$4:$Q$4,0),0)/'P&L'!$B$9 -> 0 | I53: =VLOOKUP($B53,'Region Peril'!$B$4:$Q$80,MATCH('ILS Report- Combined'!I$44,'Region Peril'!$B$4:$Q$4,0),0)/'P&L'!$B$9 -> 0
A54: 10 | B54: =INDEX('Region Peril'!$B$4:$B$80, MATCH(LARGE('Region Peril'!$C$4:$C$80, $A54), 'Region Peril'!$C$4:$C$80, 0)) -> US Severe Storm | C54: =LARGE('Region Peril'!$C$4:$C$80,$A54)/'P&L'!$B$9 -> 0.0024378531 | D54: =LARGE('Region Peril'!$C$4:$C$80,$A54)/'P&L'!$B$9 -> 0.0024378531 | E54: =VLOOKUP($B54,'Region Peril'!$B$4:$Q$80,MATCH('ILS Report- Combined'!E$44,'Region Peril'!$B$4:$Q$4,0),0)/'P&L'!$B$9 -> 0 | F54: =VLOOKUP($B54,'Region Peril'!$B$4:$Q$80,MATCH('ILS Report- Combined'!F$44,'Region Peril'!$B$4:$Q$4,0),0)/'P&L'!$B$9 -> 0 | G54: =VLOOKUP($B54,'Region Peril'!$B$4:$Q$80,MATCH('ILS Report- Combined'!G$44,'Region Peril'!$B$4:$Q$4,0),0)/'P&L'!$B$9 -> 0 | H54: =VLOOKUP($B54,'Region Peril'!$B$4:$Q$80,MATCH('ILS Report- Combined'!H$44,'Region Peril'!$B$4:$Q$4,0),0)/'P&L'!$B$9 -> 0 | I54: =VLOOKUP($B54,'Region Peril'!$B$4:$Q$80,MATCH('ILS Report- Combined'!I$44,'Region Peril'!$B$4:$Q$4,0),0)/'P&L'!$B$9 -> 0
B57: =2&":"&8 -> 2:8 | C57: ="A:A" -> A:A | D57: =2&":"&2 -> 2:2
B58: Investment Type | C58: Expected Loss (%) | D58: Capital allocation (%)
B59: Short
B60: Cat Bond | C60: =_xlfn.IFNA(INDEX(INDIRECT("'Guidelines Summary'!"&$B$57),MATCH($B60,INDIRECT("'Guidelines Summary'!"&$C$57),0)-1,MATCH("EL (%)",INDIRECT("'Guidelines Summary'!"&$D$57),0)),0) -> 0.99999673 | D60: =_xlfn.IFNA(INDEX(INDIRECT("'Guidelines Summary'!"&$B$57),MATCH($B60,INDIRECT("'Guidelines Summary'!"&$C$57),0)-1,MATCH("AUM (%)",INDIRECT("'Guidelines Summary'!"&$D$57),0)),0) -> 1.463873
B61: Treasury | C61: =_xlfn.IFNA(INDEX(INDIRECT("'Guidelines Summary'!"&$B$57),MATCH($B61,INDIRECT("'Guidelines Summary'!"&$C$57),0)-1,MATCH("EL (%)",INDIRECT("'Guidelines Summary'!"&$D$57),0)),0) -> 0 | D61: =_xlfn.IFNA(INDEX(INDIRECT("'Guidelines Summary'!"&$B$57),MATCH($B61,INDIRECT("'Guidelines Summary'!"&$C$57),0)-1,MATCH("AUM (%)",INDIRECT("'Guidelines Summary'!"&$D$57),0)),0) -> 0

Sheet P&L
A1: P&L Report | B1: Deployed AUM | C1: =VLOOKUP(B1,$A$26:$B$42,2,FALSE) -> 3750000
B2: Total AUM | C2: =VLOOKUP(B2,$A$26:$B$42,2,FALSE) -> 4000000
A3: Expected P&L | B3: Expected | C3: 0.1 | D3: 0.5 | E3: 0.8 | F3: 0.9 | G3: 0.96 | H3: 0.98 | I3: 0.99 | J3: 0.996 | K3: 0.998 | L3: 0.999
C4: 1.111 yr | D4: 2 yr | E4: 5 yr | F4: 10 yr | G4: 25 yr | H4: 50 yr | I4: 100 yr | J4: 250 yr | K4: 500 yr | L4: 1000 yr
A5: Gross Written Premium | B5: 755447 | C5: 755447 | D5: 755447 | E5: 755447 | F5: 755447 | G5: 755447 | H5: 755447 | I5: 755447 | J5: 755447 | K5: 755447 | L5: 755447
A6: Reinstatement Premium | B6: 0 | C6: 0 | D6: 0 | E6: 0 | F6: 0 | G6: 0 | H6: 0 | I6: 0 | J6: 0 | K6: 0 | L6: 0
A7: Leverage Expense | B7: 0 | C7: 0 | D7: 0 | E7: 0 | F7: 0 | G7: 0 | H7: 0 | I7: 0 | J7: 0 | K7: 0 | L7: 0
A8: Net Written Premium | B8: 755447 | C8: 755447 | D8: 755447 | E8: 755447 | F8: 755447 | G8: 755447 | H8: 755447 | I8: 755447 | J8: 755447 | K8: 755447 | L8: 755447
A9: Gross Loss Amount | B9: 144606 | C9: 0 | D9: 0 | E9: 0 | F9: 499999.55 | G9: 1202416.8 | H9: 1809700.5 | I9: 2487342.8 | J9: 2709430.3 | K9: 2791852.9 | L9: 3272442.7
A10: Acquisition Expenses | B10: 0 | C10: 0 | D10: 0 | E10: 0 | F10: 0 | G10: 0 | H10: 0 | I10: 0 | J10: 0 | K10: 0 | L10: 0
A11: Federal Excise Tax | B11: 0 | C11: 0 | D11: 0 | E11: 0 | F11: 0 | G11: 0 | H11: 0 | I11: 0 | J11: 0 | K11: 0 | L11: 0
A12: Fronting Fee | B12: 0 | C12: 0 | D12: 0 | E12: 0 | F12: 0 | G12: 0 | H12: 0 | I12: 0 | J12: 0 | K12: 0 | L12: 0
A13: Net Underwriting Income | B13: 610841 | C13: 755447 | D13: 755447 | E13: 755447 | F13: 255447.45 | G13: -446969.79 | H13: -1054253.5 | I13: -1731895.8 | J13: -1953983.3 | K13: -2036405.9 | L13: -2516995.7
A14: Excess Return Gross | B14: 0.15271025 | C14: 0.18886175 | D14: 0.18886175 | E14: 0.18886175 | F14: 0.063861862 | G14: -0.11174245 | H14: -0.26356338 | I14: -0.43297394 | J14: -0.48849583 | K14: -0.50910148 | L14: -0.62924893
A15: Investment Income | B15: 9675 | C15: 9675 | D15: 9675 | E15: 9675 | F15: 9675 | G15: 9675 | H15: 9675 | I15: 9675 | J15: 9675 | K15: 9675 | L15: 9675
A16: Op/Org Expenses | B16: 15200 | C16: 15200 | D16: 15200 | E16: 15200 | F16: 15200 | G16: 15200 | H16: 15200 | I16: 15200 | J16: 15200 | K16: 15200 | L16: 15200
... A20: Total Net Return | B20: 0.139329 | C20: 0.1754805 | D20: 0.1754805 | E20: 0.1754805 | F20: 0.050480612 | G20: -0.1251237 | H20: -0.27694463 | I20: -0.44635519 | J20: -0.50187708 | K20: -0.52248273 | L20: -0.64263018
A23: Portfolio Metrics
A25: Metric | B25: USD | C25: %NAV
A26: Expected_Return Excess | B26: 610841 | C26: 0.15271025
A27: Expected_Return Net | B27: 557316 | C27: 0.139329
A28: Standard Deviation | B28: 436656 | C28: 0.109164
A29: Sharpe Ratio | B29: 1.2763274 | C29: 1.2763274
A30: CV | B30: 0.78349805
A31: Best Reasonable Outcome | B31: 701922 | C31: 0.1754805
A32: ProbabilityOfLoss | B32: 0.0715
A33: 1 in 100 yr PML | B33: -1785420.8 | C33: -0.44635519
A34: 1 in 250 yr PML | B34: -2007508.3 | C34: -0.50187708
A35: 1% TVAR | B35: -2035586.4 | C35: -0.5088966
A36: RAROC (99%) | B36: 0.31214827
A37: Notional Occurrence Limits (Short) | B37: 5250000
A38: Notional Aggregate Limits (Short) | B38: 5250000
A39: Leverage | C39: 1.3125
A40: ROL | C40: 0.14389467
A41: Deployed AUM | B41: 3750000
A42: Total AUM | B42: 4000000
A43: Deployed AUM
A44: Total AUM

Sheet EP Curve
A3: AggLoss | B3: Rank | C3: Probability | D3: UW P&L | E3: Total P&L | F3: Excess Return(% Total) | G3: Total Return(% Total) | H3: Excess Return(% Deployed) | I3: Total Return(% Deployed)
A4: 4499998 | B4: 1 | C4: 0.0001 | D4: -3744551 | E4: -3798076 | F4: -0.93613775 | G4: -0.949519 | H4: -0.99854693 | I4: -1.0128203
A5: 4499998 | B5: 2 | C5: 0.0002 | D5: -3744551 | E5: -3798076 | F5: -0.93613775 | G5: -0.949519 | H5: -0.99854693 | I5: -1.0128203
A6: 3825126.4 | B6: 3 | C6: 0.0003 | D6: -3069679.4 | E6: -3123204.4 | F6: -0.76741985 | G6: -0.7808011 | H6: -0.81858118 | I6: -0.83285451
A7: 3749998.3 | B7: 4 | C7: 0.0004 | D7: -2994551.3 | E7: -3048076.3 | F7: -0.74863783 | G7: -0.76201908 | H7: -0.79854702 | I7: -0.81282036
A8: 3649685.8 | B8: 5 | C8: 0.0005 | D8: -2894238.8 | E8: -2947763.8 | F8: -0.7235597 | G8: -0.73694095 | H8: -0.77179701 | I8: -0.78607035
A9: 3499998.3 | B9: 6 | C9: 0.0006 | D9: -2744551.3 | E9: -2798076.3 | F9: -0.68613784 | G9: -0.69951909 | H9: -0.73188036 | I9: -0.74615369
A10: 3499998.3 | B10: 7 | C10: 0.0007 | D10: -2744551.3 | E10: -2798076.3 | F10: -0.68613784 | G10: -0.69951909 | H10: -0.73188036 | I10: -0.74615369
A11: 3436532.7 | B11: 8 | C11: 0.0008 | D11: -2681085.7 | E11: -2734610.7 | F11: -0.67027143 | G11: -0.68365268 | H11: -0.71495619 | I11: -0.72922953
A12: 3322639.2 | B12: 9 | C12: 0.0009 | D12: -2567192.2 | E12: -2620717.2 | F12: -0.64179806 | G12: -0.65517931 | H12: -0.68458459 | I12: -0.69885793
A13: 3272442.7 | B13: 10 | C13: 0.001 | D13: -2516995.7 | E13: -2570520.7 | F13: -0.62924893 | G13: -0.64263018 | H13: -0.67119886 | I13: -0.68547219
A14: 3263752.4 | B14: 11 | C14: 0.0011 | D14: -2508305.4 | E14: -2561830.4 | F14: -0.62707635 | G14: -0.6404576 | H14: -0.66888144 | I14: -0.68315478
A15: 3249999.1 | B15: 12 | C15: 0.0012 | D15: -2494552.1 | E15: -2548077.1 | F15: -0.62363804 | G15: -0.63701929 | H15: -0.6652139 | I15: -0.67948724
... A10003: 0 | B10003: 10000 | C10003: 1 | D10003: 755447 | E10003: 701922 | F10003: 0.18886175 | G10003: 0.1754805 | H10003: 0.20145253 | I10003: 0.1871792

Sheet HistoricalEvents
D3: IndustryLoss | E3: EventID | F3: EventName | G3: EventYear | H3: EventType | I3: CB-Bayou Re Ltd. Series 2024-1 Class B Reset 2025 | J3: CB-Bayou Re Ltd. Series 2024-1 Class A Reset 2025 | K3: CB-Bayou Re Ltd. Series 2025-1 Class A | L3: CB-Gateway Re Ltd. Series 2023-1 Class B Reset 2025 | M3: CB-Purple Re Ltd. Series 2024-1 Class A Reset 2025 | N3: CB-Blue Ridge Re Ltd. Series 2023-1 Class A Reset 2025 | O3: CB-Purple Re Ltd. Series 2023-2 Class A Reset 2025 | P3: CB-Charles River Re Ltd. Series 2024-1 Class A Reset 2025 | Q3: CB-3264 Re Ltd. Series 2024-1 Class B Reset 2025 | R3: CB-Citrus Re Ltd. Series 2023-1 Class B Reset 2025 | S3: CB-Bayou Re Ltd. Series 2023-1 Class B Reset 2025 | T3: CB-Baldwin Re Ltd. Series 2023-1 Class A Reset 2025 | U3: CB-Gateway Re Ltd. Series 2023-1 Class A Reset 2025 | V3: Portfolio | W3: CB-Bayou Re Ltd. Series 2023-1 Class A Reset 2025 | X3: CB-Gateway Re Ltd. Series 2025-1 Class A | Y3: CB-Montoya Re Ltd. Series 2025-1 Class B Reset 2025 | Z3: CB-Acorn Re Ltd. Series 2023-1 Class A | AA3: CB-Logistics Re Ltd. Series 2024-1 Class A | AB3: CB-Winston Re Ltd. Series 2024-1 Class A Reset 2025 | AC3: CB-Veraison Re Ltd. Series 2023-1 Class A Reset 2025 | AD3: CB-Winston Re Ltd. Series 2025-1 Class A | AE3: CB-Res Re 2025 Ltd. Series 2025-II Class 2 | AF3: CB-Charles River Re Ltd. Series 2024-1 Class A Reset 2025 | AG3: CB-Citrus Re Ltd. Series 2023-1 Class B Reset 2025 | AH3: CB-Tomoni Re Pte. Ltd. Series 2022-1 Class B-1 Reset 2025 | AI3: CB-Baldwin Re Ltd. Series 2023-1 Class A Reset 2025 | AJ3: Portfolio | AK3: CB-Torrey Pines Re Ltd. Series 2023-1 Class A Reset 2025 | AL3: CB-Bayou Re Ltd. Series 2023-1 Class A Reset 2025 | AM3: CB-Commonwealth Re Ltd. Series 2023-1 Class A Reset 2025 | AN3: CB-Gateway Re Ltd. Series 2025-1 Class C2 | AO3: CB-Black Kite Re Ltd. Series 2025-1 Class A | AP3: CB-Fish Pond Re Ltd. Series 2024-1 Class A Reset 2025 | AQ3: CB-Montoya Re Ltd. Series 2025-1 Class B Reset 2025 | AR3: CB-Nakama Re Pte. Ltd. Series 2024-1 Class 1 Reset 2025 | AS3: CB-Veraison Re Ltd. Series 2025-1 Class A | AT3: CB-Fuchsia 2 Series 2024-1 Class A Reset 2025 | AU3: CB-Lightning Re Ltd. Series 2023-1 Class A Reset 2025 | AV3: CB-FloodSmart Re Ltd. Series 2024-1 Class A Reset 2025_wLMF | AW3: CB-Aragonite Re Ltd. Series 2024-1 Class A Reset 2025 | AX3: CB-Everglades Re II Ltd. Series 2024-1 Class A Reset 2025 | AY3: CB-Maschpark Re Ltd. Series 2024-1 Class A | AZ3: CB-Winston Re Ltd. Series 2024-1 Class B Reset 2025 | BA3: CB-Titania Re Ltd. Series 2023-1 Class A Reset 2025 | BB3: CB-Veraison Re Ltd. Series 2025-1 Class A | BC3: CB-Fuchsia 2 Series 2024-1 Class A Reset 2025 | BD3: CB-Lightning Re Ltd. Series 2023-1 Class A Reset 2025 | BE3: CB-Four Lakes Re Ltd. Series 2023-1 Class B Reset 2025 | BF3: CB-Aragonite Re Ltd. Series 2024-1 Class A Reset 2025 | BG3: CB-Everglades Re II Ltd. Series 2024-1 Class A Reset 2025 | BH3: CB-Maschpark Re Ltd. Series 2024-1 Class A | BI3: CB-Winston Re Ltd. Series 2024-1 Class B Reset 2025 | BJ3: CB-Titania Re Ltd. Series 2023-1 Class A Reset 2025
D4: 5.1288171e+08 | E4: 55951561 | F4: 2012 Waldo Canyon | G4: 9 | H4: 5 | I4: 0 | J4: 0 | K4: 0 | L4: 0 | M4: 0 | N4: 0 | O4: 0 | P4: 0 | Q4: 0 | R4: 0 | S4: 0 | T4: 0 | U4: 0 | V4: 0 | W4: 0 | X4: 0 | Y4: 0 | Z4: 0 | AA4: 0 | AB4: 0 | AC4: 0 | AD4: 0 | AE4: 0 | AF4: 0 | AG4: 0 | AH4: 0 | AI4: 0 | AJ4: 0 | AK4: 0 | AL4: 0 | AM4: 0 | AN4: 0 | AO4: 0 | AP4: 0 | AQ4: 0 | AR4: 0 | AS4: 0 | AT4: 0 | AU4: 0 | AV4: 0 | AW4: 0 | AX4: 0 | AY4: 0 | AZ4: 0 | BA4: 0 | BB4: 0 | BC4: 0 | BD4: 0 | BE4: 0 | BF4: 0 | BG4: 0 | BH4: 0 | BI4: 0 | BJ4: 0
E5: 60098992 | F5: 2016 Yarloop Bushfire | G5: 3 | H5: 6 | I5: 0 | J5: 0 | K5: 0 | L5: 0 | M5: 0 | N5: 0 | O5: 0 | P5: 0 | Q5: 0 | R5: 0 | S5: 0 | T5: 0 | U5: 0 | V5: 0 | W5: 0 | X5: 0 | Y5: 0 | Z5: 0 | AA5: 0 | AB5: 0 | AC5: 0 | AD5: 0 | AE5: 0 | AF5: 0 | AG5: 0 | AH5: 0 | AI5: 0 | AJ5: 0 | AK5: 0 | AL5: 0 | AM5: 0 | AN5: 0 | AO5: 0 | AP5: 0 | AQ5: 0 | AR5: 0 | AS5: 0 | AT5: 0 | AU5: 0 | AV5: 0 | AW5: 0 | AX5: 0 | AY5: 0 | AZ5: 0 | BA5: 0 | BB5: 0 | BC5: 0 | BD5: 0 | BE5: 0 | BF5: 0 | BG5: 0 | BH5: 0 | BI5: 0 | BJ5: 0
E6: 60615059 | F6: 2019 Bunyip Bushfire | G6: 6 | H6: 6 | I6: 0 | J6: 0 | K6: 0 | L6: 0 | M6: 0 | N6: 0 | O6: 0 | P6: 0 | Q6: 0 | R6: 0 | S6: 0 | T6: 0 | U6: 0 | V6: 0 | W6: 0 | X6: 0 | Y6: 0 | Z6: 0 | AA6: 0 | AB6: 0 | AC6: 0 | AD6: 0 | AE6: 0 | AF6: 0 | AG6: 0 | AH6: 0 | AI6: 0 | AJ6: 0 | AK6: 0 | AL6: 0 | AM6: 0 | AN6: 0 | AO6: 0 | AP6: 0 | AQ6: 0 | AR6: 0 | AS6: 0 | AT6: 0 | AU6: 0 | AV6: 0 | AW6: 0 | AX6: 0 | AY6: 0 | AZ6: 0 | BA6: 0 | BB6: 0 | BC6: 0 | BD6: 0 | BE6: 0 | BF6: 0 | BG6: 0 | BH6: 0 | BI6: 0 | BJ6: 0
E7: 60678765 | F7: 1983 Ash Wednesday Bushfire | G7: 1 | H7: 6 | I7: 0 | J7: 0 | K7: 0 | L7: 0 | M7: 0 | N7: 0 | O7: 0 | P7: 0 | Q7: 0 | R7: 0 | S7: 0 | T7: 0 | U7: 0 | V7: 0 | W7: 0 | X7: 0 | Y7: 0 | Z7: 0 | AA7: 0 | AB7: 0 | AC7: 0 | AD7: 0 | AE7: 0 | AF7: 0 | AG7: 0 | AH7: 0 | AI7: 0 | AJ7: 0 | AK7: 0 | AL7: 0 | AM7: 0 | AN7: 0 | AO7: 0 | AP7: 0 | AQ7: 0 | AR7: 0 | AS7: 0 | AT7: 0 | AU7: 0 | AV7: 0 | AW7: 0 | AX7: 0 | AY7: 0 | AZ7: 0 | BA7: 0 | BB7: 0 | BC7: 0 | BD7: 0 | BE7: 0 | BF7: 0 | BG7: 0 | BH7: 0 | BI7: 0 | BJ7: 0
E8: 61179696 | F8: 2018 Tathra Bushfire | G8: 5 | H8: 6 | I8: 0 | J8: 0 | K8: 0 | L8: 0 | M8: 0 | N8: 0 | O8: 0 | P8: 0 | Q8: 0 | R8: 0 | S8: 0 | T8: 0 | U8: 0 | V8: 0 | W8: 0 | X8: 0 | Y8: 0 | Z8: 0 | AA8: 0 | AB8: 0 | AC8: 0 | AD8: 0 | AE8: 0 | AF8: 0 | AG8: 0 | AH8: 0 | AI8: 0 | AJ8: 0 | AK8: 0 | AL8: 0 | AM8: 0 | AN8: 0 | AO8: 0 | AP8: 0 | AQ8: 0 | AR8: 0 | AS8: 0 | AT8: 0 | AU8: 0 | AV8: 0 | AW8: 0 | AX8: 0 | AY8: 0 | AZ8: 0 | BA8: 0 | BB8: 0 | BC8: 0 | BD8: 0 | BE8: 0 | BF8: 0 | BG8: 0 | BH8: 0 | BI8: 0 | BJ8: 0
D9: 8.9098664e+08 | E9: 80439281 | F9: 2011 Tropical Storm Lee | G9: 11 | H9: 8 | I9: 0 | J9: 0 | K9: 0 | L9: 0 | M9: 0 | N9: 0 | O9: 0 | P9: 0 | Q9: 0 | R9: 0 | S9: 0 | T9: 0 | U9: 0 | V9: 0 | W9: 0 | X9: 0 | Y9: 0 | Z9: 0 | AA9: 0 | AB9: 0 | AC9: 0 | AD9: 0 | AE9: 0 | AF9: 0 | AG9: 0 | AH9: 0 | AI9: 0 | AJ9: 0 | AK9: 0 | AL9: 0 | AM9: 0 | AN9: 0 | AO9: 0 | AP9: 0 | AQ9: 0 | AR9: 0 | AS9: 0 | AT9: 0 | AU9: 0 | AV9: 0 | AW9: 0 | AX9: 0 | AY9: 0 | AZ9: 0 | BA9: 0 | BB9: 0 | BC9: 0 | BD9: 0 | BE9: 0 | BF9: 0 | BG9: 0 | BH9: 0 | BI9: 0 | BJ9: 0
D10: 3.4529243e+08 | E10: 110000544 | F10: 1991 Glendale-Arcadia-Sierra Madre CA | G10: 66 | H10: 11 | I10: 0 | J10: 0 | K10: 0 | L10: 0 | M10: 0 | N10: 0 | O10: 0 | P10: 0 | Q10: 0 | R10: 0 | S10: 0 | T10: 0 | U10: 0 | V10: 0 | W10: 0 | X10: 0 | Y10: 0 | Z10: 0 | AA10: 0 | AB10: 0 | AC10: 0 | AD10: 0 | AE10: 0 | AF10: 0 | AG10: 0 | AH10: 0 | AI10: 0 | AJ10: 0 | AK10: 0 | AL10: 0 | AM10: 0 | AN10: 0 | AO10: 0 | AP10: 0 | AQ10: 0 | AR10: 0 | AS10: 0 | AT10: 0 | AU10: 0 | AV10: 0 | AW10: 0 | AX10: 0 | AY10: 0 | AZ10: 0 | BA10: 0 | BB10: 0 | BC10: 0 | BD10: 0 | BE10: 0 | BF10: 0 | BG10: 0 | BH10: 0 | BI10: 0 | BJ10: 0
D11: 3.570069e+08 | E11: 110009851 | F11: 1873 Oregon Coast-Scenario 1 | G11: 17 | H11: 11 | I11: 0 | J11: 0 | K11: 0 | L11: 0 | M11: 0 | N11: 0 | O11: 0 | P11: 0 | Q11: 0 | R11: 0 | S11: 0 | T11: 0 | U11: 0 | V11: 0 | W11: 0 | X11: 0 | Y11: 0 | Z11: 0 | AA11: 0 | AB11: 0 | AC11: 0 | AD11: 0 | AE11: 0 | AF11: 0 | AG11: 0 | AH11: 0 | AI11: 0 | AJ11: 0 | AK11: 0 | AL11: 0 | AM11: 0 | AN11: 0 | AO11: 0 | AP11: 0 | AQ11: 0 | AR11: 0 | AS11: 0 | AT11: 0 | AU11: 0 | AV11: 0 | AW11: 0 | AX11: 0 | AY11: 0 | AZ11: 0 | BA11: 0 | BB11: 0 | BC11: 0 | BD11: 0 | BE11: 0 | BF11: 0 | BG11: 0 | BH11: 0 | BI11: 0 | BJ11: 0
D12: 3.2844716e+08 | E12: 110009851 | F12: 1873 Oregon Coast-Scenario 1 | G12: 17 | H12: 11 | I12: 0 | J12: 0 | K12: 0 | L12: 0 | M12: 0 | N12: 0 | O12: 0 | P12: 0 | Q12: 0 | R12: 0 | S12: 0 | T12: 0 | U12: 0 | V12: 0 | W12: 0 | X12: 0 | Y12: 0 | Z12: 0 | AA12: 0 | AB12: 0 | AC12: 0 | AD12: 0 | AE12: 0 | AF12: 0 | AG12: 0 | AH12: 0 | AI12: 0 | AJ12: 0 | AK12: 0 | AL12: 0 | AM12: 0 | AN12: 0 | AO12: 0 | AP12: 0 | AQ12: 0 | AR12: 0 | AS12: 0 | AT12: 0 | AU12: 0 | AV12: 0 | AW12: 0 | AX12: 0 | AY12: 0 | AZ12: 0 | BA12: 0 | BB12: 0 | BC12: 0 | BD12: 0 | BE12: 0 | BF12: 0 | BG12: 0 | BH12: 0 | BI12: 0 | BJ12: 0
D13: 1.9919565e+08 | E13: 110011943 | F13: 1975 Oroville Reservoir CA | G13: 52 | H13: 11 | I13: 0 | J13: 0 | K13: 0 | L13: 0 | M13: 0 | N13: 0 | O13: 0 | P13: 0 | Q13: 0 | R13: 0 | S13: 0 | T13: 0 | U13: 0 | V13: 0 | W13: 0 | X13: 0 | Y13: 0 | Z13: 0 | AA13: 0 | AB13: 0 | AC13: 0 | AD13: 0 | AE13: 0 | AF13: 0 | AG13: 0 | AH13: 0 | AI13: 0 | AJ13: 0 | AK13: 0 | AL13: 0 | AM13: 0 | AN13: 0 | AO13: 0 | AP13: 0 | AQ13: 0 | AR13: 0 | AS13: 0 | AT13: 0 | AU13: 0 | AV13: 0 | AW13: 0 | AX13: 0 | AY13: 0 | AZ13: 0 | BA13: 0 | BB13: 0 | BC13: 0 | BD13: 0 | BE13: 0 | BF13: 0 | BG13: 0 | BH13: 0 | BI13: 0 | BJ13: 0
D14: 23802576 | E14: 110019370 | F14: 1927 Lompoc CA | G14: 29 | H14: 11 | I14: 0 | J14: 0 | K14: 0 | L14: 0 | M14: 0 | N14: 0 | O14: 0 | P14: 0 | Q14: 0 | R14: 0 | S14: 0 | T14: 0 | U14: 0 | V14: 0 | W14: 0 | X14: 0 | Y14: 0 | Z14: 0 | AA14: 0 | AB14: 0 | AC14: 0 | AD14: 0 | AE14: 0 | AF14: 0 | AG14: 0 | AH14: 0 | AI14: 0 | AJ14: 0 | AK14: 0 | AL14: 0 | AM14: 0 | AN14: 0 | AO14: 0 | AP14: 0 | AQ14: 0 | AR14: 0 | AS14: 0 | AT14: 0 | AU14: 0 | AV14: 0 | AW14: 0 | AX14: 0 | AY14: 0 | AZ14: 0 | BA14: 0 | BB14: 0 | BC14: 0 | BD14: 0 | BE14: 0 | BF14: 0 | BG14: 0 | BH14: 0 | BI14: 0 | BJ14: 0
D15: 887583.48 | E15: 110024122 | F15: 1899 Yakutat Bay AK | G15: 20 | H15: 11 | I15: 0 | J15: 0 | K15: 0 | L15: 0 | M15: 0 | N15: 0 | O15: 0 | P15: 0 | Q15: 0 | R15: 0 | S15: 0 | T15: 0 | U15: 0 | V15: 0 | W15: 0 | X15: 0 | Y15: 0 | Z15: 0 | AA15: 0 | AB15: 0 | AC15: 0 | AD15: 0 | AE15: 0 | AF15: 0 | AG15: 0 | AH15: 0 | AI15: 0 | AJ15: 0 | AK15: 0 | AL15: 0 | AM15: 0 | AN15: 0 | AO15: 0 | AP15: 0 | AQ15: 0 | AR15: 0 | AS15: 0 | AT15: 0 | AU15: 0 | AV15: 0 | AW15: 0 | AX15: 0 | AY15: 0 | AZ15: 0 | BA15: 0 | BB15: 0 | BC15: 0 | BD15: 0 | BE15: 0 | BF15: 0 | BG15: 0 | BH15: 0 | BI15: 0 | BJ15: 0
D16: 41473500 | E16: 110058772 | F16: 1949 Offshore of Haida Gwaii/Queen Charlotte Islands BC | G16: 38 | H16: 11 | I16: 0 | J16: 0 | K16: 0 | L16: 0 | M16: 0 | N16: 0 | O16: 0 | P16: 0 | Q16: 0 | R16: 0 | S16: 0 | T16: 0 | U16: 0 | V16: 0 | W16: 0 | X16: 0 | Y16: 0 | Z16: 0 | AA16: 0 | AB16: 0 | AC16: 0 | AD16: 0 | AE16: 0 | AF16: 0 | AG16: 0 | AH16: 0 | AI16: 0 | AJ16: 0 | AK16: 0 | AL16: 0 | AM16: 0 | AN16: 0 | AO16: 0 | AP16: 0 | AQ16: 0 | AR16: 0 | AS16: 0 | AT16: 0 | AU16: 0 | AV16: 0 | AW16: 0 | AX16: 0 | AY16: 0 | AZ16: 0 | BA16: 0 | BB16: 0 | BC16: 0 | BD16: 0 | BE16: 0 | BF16: 0 | BG16: 0 | BH16: 0 | BI16: 0 | BJ16: 0
D17: 2834863.4 | E17: 110062060 | F17: 1986 Paicines-San Banito CA | G17: 61 | H17: 11 | I17: 0 | J17: 0 | K17: 0 | L17: 0 | M17: 0 | N17: 0 | O17: 0 | P17: 0 | Q17: 0 | R17: 0 | S17: 0 | T17: 0 | U17: 0 | V17: 0 | W17: 0 | X17: 0 | Y17: 0 | Z17: 0 | AA17: 0 | AB17: 0 | AC17: 0 | AD17: 0 | AE17: 0 | AF17: 0 | AG17: 0 | AH17: 0 | AI17: 0 | AJ17: 0 | AK17: 0 | AL17: 0 | AM17: 0 | AN17: 0 | AO17: 0 | AP17: 0 | AQ17: 0 | AR17: 0 | AS17: 0 | AT17: 0 | AU17: 0 | AV17: 0 | AW17: 0 | AX17: 0 | AY17: 0 | AZ17: 0 | BA17: 0 | BB17: 0 | BC17: 0 | BD17: 0 | BE17: 0 | BF17: 0 | BG17: 0 | BH17: 0 | BI17: 0 | BJ17: 0
D18: 26585281 | E18: 110062287 | F18: 1904 Passamaquoddy Bay NB | G18: 21 | H18: 11 | I18: 0 | J18: 0 | K18: 0 | L18: 0 | M18: 0 | N18: 0 | O18: 0 | P18: 0 | Q18: 0 | R18: 0 | S18: 0 | T18: 0 | U18: 0 | V18: 0 | W18: 0 | X18: 0 | Y18: 0 | Z18: 0 | AA18: 0 | AB18: 0 | AC18: 0 | AD18: 0 | AE18: 0 | AF18: 0 | AG18: 0 | AH18: 0 | AI18: 0 | AJ18: 0 | AK18: 0 | AL18: 0 | AM18: 0 | AN18: 0 | AO18: 0 | AP18: 0 | AQ18: 0 | AR18: 0 | AS18: 0 | AT18: 0 | AU18: 0 | AV18: 0 | AW18: 0 | AX18: 0 | AY18: 0 | AZ18: 0 | BA18: 0 | BB18: 0 | BC18: 0 | BD18: 0 | BE18: 0 | BF18: 0 | BG18: 0 | BH18: 0 | BI18: 0 | BJ18: 0
D19: 18038605256 | E19: 110069846 | F19: 1812 Wrightwood CA | G19: 8 | H19: 11 | I19: 0 | J19: 0 | K19: 0 | L19: 0 | M19: 0 | N19: 0 | O19: 0 | P19: 0 | Q19: 0 | R19: 0 | S19: 0 | T19: 0 | U19: 0 | V19: 0 | W19: 0 | X19: 0 | Y19: 0 | Z19: 0 | AA19: 0 | AB19: 0 | AC19: 0 | AD19: 0 | AE19: 0 | AF19: 0 | AG19: 0 | AH19: 0 | AI19: 0 | AJ19: 0 | AK19: 0 | AL19: 0 | AM19: 0 | AN19: 0 | AO19: 0 | AP19: 0 | AQ19: 0 | AR19: 0 | AS19: 0 | AT19: 0 | AU19: 0 | AV19: 0 | AW19: 0 | AX19: 0 | AY19: 0 | AZ19: 0 | BA19: 0 | BB19: 0 | BC19: 0 | BD19: 0 | BE19: 0 | BF19: 0 | BG19: 0 | BH19: 0 | BI19: 0 | BJ19: 0
D20: 2.78213e+08 | E20: 110071633 | F20: 1992 Landers-Yucca Valley CA | G20: 67 | H20: 11 | I20: 0 | J20: 0 | K20: 0 | L20: 0 | M20: 0 | N20: 0 | O20: 0 | P20: 0 | Q20: 0 | R20: 0 | S20: 0 | T20: 0 | U20: 0 | V20: 0 | W20: 0 | X20: 0 | Y20: 0 | Z20: 0 | AA20: 0 | AB20: 0 | AC20: 0 | AD20: 0 | AE20: 0 | AF20: 0 | AG20: 0 | AH20: 0 | AI20: 0 | AJ20: 0 | AK20: 0 | AL20: 0 | AM20: 0 | AN20: 0 | AO20: 0 | AP20: 0 | AQ20: 0 | AR20: 0 | AS20: 0 | AT20: 0 | AU20: 0 | AV20: 0 | AW20: 0 | AX20: 0 | AY20: 0 | AZ20: 0 | BA20: 0 | BB20: 0 | BC20: 0 | BD20: 0 | BE20: 0 | BF20: 0 | BG20: 0 | BH20: 0 | BI20: 0 | BJ20: 0
... D26: 3.6804797e+08 | E26: 190237570 | F26: 2020 Fort McMurray Ice Jam Flood | G26: 6 | H26: 19 | I26: 0 | J26: 0 | K26: 0 | L26: 0 | M26: 0 | N26: 0 | O26: 0 | P26: 0 | Q26: 0 | R26: 0 | S26: 0 | T26: 0 | U26: 0 | V26: 0 | W26: 0 | X26: 0 | Y26: 0 | Z26: 0 | AA26: 0 | AB26: 0 | AC26: 0 | AD26: 0 | AE26: 0 | AF26: 0 | AG26: 0 | AH26: 0 | AI26: 0 | AJ26: 0 | AK26: 0 | AL26: 0 | AM26: 0 | AN26: 0 | AO26: 0 | AP26: 0 | AQ26: 0 | AR26: 0 | AS26: 0 | AT26: 0 | AU26: 0 | AV26: 0 | AW26: 0 | AX26: 0 | AY26: 0 | AZ26: 0 | BA26: 0 | BB26: 0 | BC26: 0 | BD26: 0 | BE26: 0 | BF26: 0 | BG26: 0 | BH26: 0 | BI26: 0 | BJ26: 0
E27: 221642484 | F27: MidwestOutbreak_PCS18_5 | G27: 15 | H27: 22 | I27: 0 | J27: 0 | K27: 0 | L27: 0 | M27: 0 | N27: 0 | O27: 0 | P27: 0 | Q27: 0 | R27: 0 | S27: 0 | T27: 0 | U27: 0 | V27: 0 | W27: 0 | X27: 0 | Y27: 0 | Z27: 0 | AA27: 0 | AB27: 0 | AC27: 0 | AD27: 0 | AE27: 0 | AF27: 0 | AG27: 0 | AH27: 0 | AI27: 0 | AJ27: 0 | AK27: 0 | AL27: 0 | AM27: 0 | AN27: 0 | AO27: 0 | AP27: 0 | AQ27: 0 | AR27: 0 | AS27: 0 | AT27: 0 | AU27: 0 | AV27: 0 | AW27: 0 | AX27: 0 | AY27: 0 | AZ27: 0 | BA27: 0 | BB27: 0 | BC27: 0 | BD27: 0 | BE27: 0 | BF27: 0 | BG27: 0 | BH27: 0 | BI27: 0 | BJ27: 0
D28: 1.5300437e+09 | E28: 270003198 | F28: 1999 Lenny | G28: 44 | H28: 27 | I28: 0 | J28: 0 | K28: 0 | L28: 0 | M28: 0 | N28: 0 | O28: 0 | P28: 0 | Q28: 0 | R28: 0 | S28: 0 | T28: 0 | U28: 0 | V28: 0 | W28: 0 | X28: 0 | Y28: 0 | Z28: 0 | AA28: 0 | AB28: 0 | AC28: 0 | AD28: 0 | AE28: 0 | AF28: 0 | AG28: 0 | AH28: 0 | AI28: 0 | AJ28: 0 | AK28: 0 | AL28: 0 | AM28: 0 | AN28: 0 | AO28: 0 | AP28: 0 | AQ28: 0 | AR28: 0 | AS28: 0 | AT28: 0 | AU28: 0 | AV28: 0 | AW28: 0 | AX28: 0 | AY28: 0 | AZ28: 0 | BA28: 0 | BB28: 0 | BC28: 0 | BD28: 0 | BE28: 0 | BF28: 0 | BG28: 0 | BH28: 0 | BI28: 0 | BJ28: 0
D29: 6.6468185e+09 | E29: 270016896 | F29: 2011 Irene | G29: 53 | H29: 27 | I29: 0 | J29: 0 | K29: 0 | L29: 0 | M29: 0 | N29: 0 | O29: 0 | P29: 0 | Q29: 0 | R29: 0 | S29: 0 | T29: 0 | U29: 0 | V29: 0 | W29: 0 | X29: 0 | Y29: 0 | Z29: 0 | AA29: 0 | AB29: 0 | AC29: 0 | AD29: 0 | AE29: 0 | AF29: 0 | AG29: 0 | AH29: 0 | AI29: 0 | AJ29: 0 | AK29: 0 | AL29: 0 | AM29: 0 | AN29: 0 | AO29: 0 | AP29: 0 | AQ29: 0 | AR29: 0 | AS29: 0 | AT29: 0 | AU29: 0 | AV29: 0 | AW29: 0 | AX29: 0 | AY29: 0 | AZ29: 0 | BA29: 0 | BB29: 0 | BC29: 0 | BD29: 0 | BE29: 0 | BF29: 0 | BG29: 0 | BH29: 0 | BI29: 0 | BJ29: 0
D30: 2.9934117e+09 | E30: 270028025 | F30: 2020 Hurricane Sally | G30: 59 | H30: 27 | I30: 0 | J30: 0 | K30: 0 | L30: 0 | M30: 0 | N30: 0 | O30: 0 | P30: 0 | Q30: 0 | R30: 0 | S30: 0 | T30: 0 | U30: 0 | V30: 0 | W30: 0 | X30: 0 | Y30: 0 | Z30: 0 | AA30: 0 | AB30: 0 | AC30: 0 | AD30: 0 | AE30: 0 | AF30: 0 | AG30: 0 | AH30: 0 | AI30: 0 | AJ30: 0 | AK30: 0 | AL30: 0 | AM30: 0 | AN30: 0 | AO30: 0 | AP30: 0 | AQ30: 0 | AR30: 0 | AS30: 0 | AT30: 0 | AU30: 0 | AV30: 0 | AW30: 0 | AX30: 0 | AY30: 0 | AZ30: 0 | BA30: 0 | BB30: 0 | BC30: 0 | BD30: 0 | BE30: 0 | BF30: 0 | BG30: 0 | BH30: 0 | BI30: 0 | BJ30: 0
D31: 3.1161323e+08 | E31: 270029073 | F31: 2016 Hermine | G31: 56 | H31: 27 | I31: 0 | J31: 0 | K31: 0 | L31: 0 | M31: 0 | N31: 0 | O31: 0 | P31: 0 | Q31: 0 | R31: 0 | S31: 0 | T31: 0 | U31: 0 | V31: 0 | W31: 0 | X31: 0 | Y31: 0 | Z31: 0 | AA31: 0 | AB31: 0 | AC31: 0 | AD31: 0 | AE31: 0 | AF31: 0 | AG31: 0 | AH31: 0 | AI31: 0 | AJ31: 0 | AK31: 0 | AL31: 0 | AM31: 0 | AN31: 0 | AO31: 0 | AP31: 0 | AQ31: 0 | AR31: 0 | AS31: 0 | AT31: 0 | AU31: 0 | AV31: 0 | AW31: 0 | AX31: 0 | AY31: 0 | AZ31: 0 | BA31: 0 | BB31: 0 | BC31: 0 | BD31: 0 | BE31: 0 | BF31: 0 | BG31: 0 | BH31: 0 | BI31: 0 | BJ31: 0
D32: 8.9256974e+10 | E32: 270077773 | F32: 1992 Andrew | G32: 37 | H32: 27 | I32: 0 | J32: 0 | K32: 0 | L32: 0 | M32: 0 | N32: 0 | O32: 0 | P32: 0 | Q32: 60198.824 | R32: 0 | S32: 0 | T32: 0 | U32: 0 | V32: 60198.824 | W32: 0 | X32: 0 | Y32: 0 | Z32: 0 | AA32: 0 | AB32: 0 | AC32: 0 | AD32: 0 | AE32: 0 | AF32: 0 | AG32: 0 | AH32: 0 | AI32: 0 | AJ32: 250002 | AK32: 0 | AL32: 0 | AM32: 0 | AN32: 0 | AO32: 0 | AP32: 0 | AQ32: 0 | AR32: 0 | AS32: 0 | AT32: 0 | AU32: 0 | AV32: 250002 | AW32: 0 | AX32: 0 | AY32: 0 | AZ32: 0 | BA32: 0 | BB32: 0 | BC32: 0 | BD32: 0 | BE32: 0 | BF32: 0 | BG32: 0 | BH32: 0 | BI32: 0 | BJ32: 0
D33: 3.2673448e+10 | E33: 270132852 | F33: 2012 Sandy | G33: 54 | H33: 27 | I33: 0 | J33: 0 | K33: 0 | L33: 0 | M33: 0 | N33: 0 | O33: 0 | P33: 69604.262 | Q33: 0 | R33: 0 | S33: 0 | T33: 0 | U33: 0 | V33: 69604.262 | W33: 0 | X33: 0 | Y33: 0 | Z33: 0 | AA33: 0 | AB33: 0 | AC33: 0 | AD33: 0 | AE33: 126181.26 | AF33: 250000 | AG33: 249999.65 | AH33: 0 | AI33: 250000 | AJ33: 1912503.1 | AK33: 0 | AL33: 0 | AM33: 250000.5 | AN33: 0 | AO33: 0 | AP33: 0 | AQ33: 0 | AR33: 0 | AS33: 0 | AT33: 0 | AU33: 0 | AV33: 0 | AW33: 0 | AX33: 0 | AY33: 0 | AZ33: 0 | BA33: 0 | BB33: 0 | BC33: 0 | BD33: 0 | BE33: 0 | BF33: 0 | BG33: 0 | BH33: 0 | BI33: 0 | BJ33: 0
D34: 5.7938128e+09 | E34: 270140848 | F34: 1935 Event 6 Florida | G34: 11 | H34: 27 | I34: 0 | J34: 0 | K34: 0 | L34: 0 | M34: 0 | N34: 0 | O34: 0 | P34: 0 | Q34: 0 | R34: 0 | S34: 0 | T34: 0 | U34: 0 | V34: 0 | W34: 0 | X34: 0 | Y34: 0 | Z34: 0 | AA34: 0 | AB34: 0 | AC34: 0 | AD34: 0 | AE34: 0 | AF34: 0 | AG34: 0 | AH34: 0 | AI34: 0 | AJ34: 0 | AK34: 0 | AL34: 0 | AM34: 0 | AN34: 0 | AO34: 0 | AP34: 0 | AQ34: 0 | AR34: 0 | AS34: 0 | AT34: 0 | AU34: 0 | AV34: 0 | AW34: 0 | AX34: 0 | AY34: 0 | AZ34: 0 | BA34: 0 | BB34: 0 | BC34: 0 | BD34: 0 | BE34: 0 | BF34: 0 | BG34: 0 | BH34: 0 | BI34: 0 | BJ34: 0
D35: 3.4583652e+10 | E35: 270144918 | F35: 2005 Wilma (US loss) | G35: 50 | H35: 27 | I35: 0 | J35: 0 | K35: 0 | L35: 0 | M35: 0 | N35: 0 | O35: 0 | P35: 0 | Q35: 0 | R35: 0 | S35: 0 | T35: 0 | U35: 0 | V35: 0 | W35: 0 | X35: 0 | Y35: 0 | Z35: 0 | AA35: 0 | AB35: 0 | AC35: 0 | AD35: 0 | AE35: 0 | AF35: 0 | AG35: 0 | AH35: 0 | AI35: 0 | AJ35: 0 | AK35: 0 | AL35: 0 | AM35: 0 | AN35: 0 | AO35: 0 | AP35: 0 | AQ35: 0 | AR35: 0 | AS35: 0 | AT35: 0 | AU35: 0 | AV35: 0 | AW35: 0 | AX35: 0 | AY35: 0 | AZ35: 0 | BA35: 0 | BB35: 0 | BC35: 0 | BD35: 0 | BE35: 0 | BF35: 0 | BG35: 0 | BH35: 0 | BI35: 0 | BJ35: 0
D36: 3.8486484e+10 | E36: 270150496 | F36: 1944 Event 11 Florida | G36: 15 | H36: 27 | I36: 0 | J36: 0 | K36: 0 | L36: 0 | M36: 0 | N36: 0 | O36: 0 | P36: 0 | Q36: 0 | R36: 0 | S36: 0 | T36: 0 | U36: 0 | V36: 0 | W36: 0 | X36: 0 | Y36: 0 | Z36: 0 | AA36: 0 | AB36: 0 | AC36: 0 | AD36: 0 | AE36: 0 | AF36: 0 | AG36: 0 | AH36: 0 | AI36: 0 | AJ36: 0 | AK36: 0 | AL36: 0 | AM36: 0 | AN36: 0 | AO36: 0 | AP36: 0 | AQ36: 0 | AR36: 0 | AS36: 0 | AT36: 0 | AU36: 0 | AV36: 0 | AW36: 0 | AX36: 0 | AY36: 0 | AZ36: 0 | BA36: 0 | BB36: 0 | BC36: 0 | BD36: 0 | BE36: 0 | BF36: 0 | BG36: 0 | BH36: 0 | BI36: 0 | BJ36: 0
D37: 1.7325172e+10 | E37: 270184270 | F37: 2017 Maria | G37: 57 | H37: 27 | I37: 0 | J37: 0 | K37: 0 | L37: 0 | M37: 0 | N37: 0 | O37: 0 | P37: 0 | Q37: 0 | R37: 0 | S37: 0 | T37: 0 | U37: 0 | V37: 0 | W37: 0 | X37: 0 | Y37: 0 | Z37: 0 | AA37: 0 | AB37: 0 | AC37: 0 | AD37: 0 | AE37: 0 | AF37: 0 | AG37: 0 | AH37: 0 | AI37: 0 | AJ37: 0 | AK37: 0 | AL37: 0 | AM37: 0 | AN37: 0 | AO37: 0 | AP37: 0 | AQ37: 0 | AR37: 0 | AS37: 0 | AT37: 0 | AU37: 0 | AV37: 0 | AW37: 0 | AX37: 0 | AY37: 0 | AZ37: 0 | BA37: 0 | BB37: 0 | BC37: 0 | BD37: 0 | BE37: 0 | BF37: 0 | BG37: 0 | BH37: 0 | BI37: 0 | BJ37: 0
D38: 1.3974705e+10 | E38: 270201984 | F38: 1979 Frederic | G38: 30 | H38: 27 | I38: 0 | J38: 0 | K38: 0 | L38: 0 | M38: 0 | N38: 0 | O38: 0 | P38: 0 | Q38: 0 | R38: 0 | S38: 0 | T38: 0 | U38: 0 | V38: 0 | W38: 0 | X38: 0 | Y38: 0 | Z38: 0 | AA38: 0 | AB38: 0 | AC38: 0 | AD38: 0 | AE38: 0 | AF38: 0 | AG38: 0 | AH38: 0 | AI38: 0 | AJ38: 0 | AK38: 0 | AL38: 0 | AM38: 0 | AN38: 0 | AO38: 0 | AP38: 0 | AQ38: 0 | AR38: 0 | AS38: 0 | AT38: 0 | AU38: 0 | AV38: 0 | AW38: 0 | AX38: 0 | AY38: 0 | AZ38: 0 | BA38: 0 | BB38: 0 | BC38: 0 | BD38: 0 | BE38: 0 | BF38: 0 | BG38: 0 | BH38: 0 | BI38: 0 | BJ38: 0
D39: 3.4594641e+08 | E39: 270228712 | F39: 2003 Claudette | G39: 48 | H39: 27 | I39: 0 | J39: 0 | K39: 0 | L39: 0 | M39: 0 | N39: 0 | O39: 0 | P39: 0 | Q39: 0 | R39: 0 | S39: 0 | T39: 0 | U39: 0 | V39: 0 | W39: 0 | X39: 0 | Y39: 0 | Z39: 0 | AA39: 0 | AB39: 0 | AC39: 0 | AD39: 0 | AE39: 0 | AF39: 0 | AG39: 0 | AH39: 0 | AI39: 0 | AJ39: 0 | AK39: 0 | AL39: 0 | AM39: 0 | AN39: 0 | AO39: 0 | AP39: 0 | AQ39: 0 | AR39: 0 | AS39: 0 | AT39: 0 | AU39: 0 | AV39: 0 | AW39: 0 | AX39: 0 | AY39: 0 | AZ39: 0 | BA39: 0 | BB39: 0 | BC39: 0 | BD39: 0 | BE39: 0 | BF39: 0 | BG39: 0 | BH39: 0 | BI39: 0 | BJ39: 0
... D103: 6.6853748e+08 | E103: 56576525 | F103: 2020 Almeda Drive | G103: 14 | H103: 5 | I103: 0 | J103: 0 | K103: 0 | L103: 0 | M103: 0 | N103: 0 | O103: 0 | P103: 0 | Q103: 0 | R103: 0 | S103: 0 | T103: 0 | U103: 0 | V103: 0 | W103: 0 | X103: 0 | Y103: 0 | Z103: 0 | AA103: 0 | AB103: 0 | AC103: 0 | AD103: 0 | AE103: 0 | AF103: 0 | AG103: 0 | AH103: 0 | AI103: 0 | AJ103: 0 | AK103: 0 | AL103: 0 | AM103: 0 | AN103: 0 | AO103: 0 | AP103: 0 | AQ103: 0 | AR103: 0 | AS103: 0 | AT103: 0 | AU103: 0 | AV103: 0 | AW103: 0 | AX103: 0 | AY103: 0 | AZ103: 0 | BA103: 0 | BB103: 0 | BC103: 0 | BD103: 0 | BE103: 0 | BF103: 0 | BG103: 0 | BH103: 0 | BI103: 0 | BJ103: 0
E104: 60814971 | F104: 2017 Sir Ivan and Carwoola Bushfire | G104: 4 | H104: 6 | I104: 0 | J104: 0 | K104: 0 | L104: 0 | M104: 0 | N104: 0 | O104: 0 | P104: 0 | Q104: 0 | R104: 0 | S104: 0 | T104: 0 | U104: 0 | V104: 0 | W104: 0 | X104: 0 | Y104: 0 | Z104: 0 | AA104: 0 | AB104: 0 | AC104: 0 | AD104: 0 | AE104: 0 | AF104: 0 | AG104: 0 | AH104: 0 | AI104: 0 | AJ104: 0 | AK104: 0 | AL104: 0 | AM104: 0 | AN104: 0 | AO104: 0 | AP104: 0 | AQ104: 0 | AR104: 0 | AS104: 0 | AT104: 0 | AU104: 0 | AV104: 0 | AW104: 0 | AX104: 0 | AY104: 0 | AZ104: 0 | BA104: 0 | BB104: 0 | BC104: 0 | BD104: 0 | BE104: 0 | BF104: 0 | BG104: 0 | BH104: 0 | BI104: 0 | BJ104: 0
D105: 4.2342111e+09 | E105: 80006364 | F105: 2001 Tropical Storm Alisson | G105: 6 | H105: 8 | I105: 0 | J105: 0 | K105: 0 | L105: 0 | M105: 0 | N105: 0 | O105: 0 | P105: 0 | Q105: 0 | R105: 0 | S105: 0 | T105: 0 | U105: 0 | V105: 0 | W105: 0 | X105: 0 | Y105: 0 | Z105: 0 | AA105: 0 | AB105: 0 | AC105: 0 | AD105: 0 | AE105: 0 | AF105: 0 | AG105: 0 | AH105: 0 | AI105: 0 | AJ105: 0 | AK105: 0 | AL105: 0 | AM105: 0 | AN105: 0 | AO105: 0 | AP105: 0 | AQ105: 0 | AR105: 0 | AS105: 0 | AT105: 0 | AU105: 0 | AV105: 0 | AW105: 0 | AX105: 0 | AY105: 0 | AZ105: 0 | BA105: 0 | BB105: 0 | BC105: 0 | BD105: 0 | BE105: 0 | BF105: 0 | BG105: 0 | BH105: 0 | BI105: 0 | BJ105: 0
D106: 1.5345066e+09 | E106: 80127142 | F106: 1995 California Flood | G106: 2 | H106: 8 | I106: 0 | J106: 0 | K106: 0 | L106: 0 | M106: 0 | N106: 0 | O106: 0 | P106: 0 | Q106: 0 | R106: 0 | S106: 0 | T106: 0 | U106: 0 | V106: 0 | W106: 0 | X106: 0 | Y106: 0 | Z106: 0 | AA106: 0 | AB106: 0 | AC106: 0 | AD106: 0 | AE106: 0 | AF106: 0 | AG106: 0 | AH106: 0 | AI106: 0 | AJ106: 0 | AK106: 0 | AL106: 0 | AM106: 0 | AN106: 0 | AO106: 0 | AP106: 0 | AQ106: 0 | AR106: 0 | AS106: 0 | AT106: 0 | AU106: 0 | AV106: 0 | AW106: 0 | AX106: 0 | AY106: 0 | AZ106: 0 | BA106: 0 | BB106: 0 | BC106: 0 | BD106: 0 | BE106: 0 | BF106: 0 | BG106: 0 | BH106: 0 | BI106: 0 | BJ106: 0
D107: 177423.09 | E107: 110003338 | F107: 1958 Lituya Bay AK | G107: 43 | H107: 11 | I107: 0 | J107: 0 | K107: 0 | L107: 0 | M107: 0 | N107: 0 | O107: 0 | P107: 0 | Q107: 0 | R107: 0 | S107: 0 | T107: 0 | U107: 0 | V107: 0 | W107: 0 | X107: 0 | Y107: 0 | Z107: 0 | AA107: 0 | AB107: 0 | AC107: 0 | AD107: 0 | AE107: 0 | AF107: 0 | AG107: 0 | AH107: 0 | AI107: 0 | AJ107: 0 | AK107: 0 | AL107: 0 | AM107: 0 | AN107: 0 | AO107: 0 | AP107: 0 | AQ107: 0 | AR107: 0 | AS107: 0 | AT107: 0 | AU107: 0 | AV107: 0 | AW107: 0 | AX107: 0 | AY107: 0 | AZ107: 0 | BA107: 0 | BB107: 0 | BC107: 0 | BD107: 0 | BE107: 0 | BF107: 0 | BG107: 0 | BH107: 0 | BI107: 0 | BJ107: 0
D108: 9.0357654e+10 | E108: 110011195 | F108: 1812 New Madrid Seismic Zone-Scenario 4-3 Segments Rupture | G108: 8 | H108: 11 | I108: 0 | J108: 0 | K108: 0 | L108: 0 | M108: 0 | N108: 0 | O108: 0 | P108: 0 | Q108: 0 | R108: 0 | S108: 0 | T108: 0 | U108: 0 | V108: 0 | W108: 0 | X108: 0 | Y108: 0 | Z108: 0 | AA108: 0 | AB108: 0 | AC108: 0 | AD108: 0 | AE108: 0 | AF108: 0 | AG108: 0 | AH108: 0 | AI108: 0 | AJ108: 0 | AK108: 0 | AL108: 0 | AM108: 0 | AN108: 0 | AO108: 0 | AP108: 0 | AQ108: 0 | AR108: 0 | AS108: 0 | AT108: 0 | AU108: 0 | AV108: 0 | AW108: 0 | AX108: 0 | AY108: 0 | AZ108: 0 | BA108: 0 | BB108: 0 | BC108: 0 | BD108: 0 | BE108: 0 | BF108: 0 | BG108: 0 | BH108: 0 | BI108: 0 | BJ108: 0
D109: 45931856 | E109: 110015411 | F109: 1992 Petrolia-Cape Mendocino CA | G109: 67 | H109: 11 | I109: 0 | J109: 0 | K109: 0 | L109: 0 | M109: 0 | N109: 0 | O109: 0 | P109: 0 | Q109: 0 | R109: 0 | S109: 0 | T109: 0 | U109: 0 | V109: 0 | W109: 0 | X109: 0 | Y109: 0 | Z109: 0 | AA109: 0 | AB109: 0 | AC109: 0 | AD109: 0 | AE109: 0 | AF109: 0 | AG109: 0 | AH109: 0 | AI109: 0 | AJ109: 0 | AK109: 0 | AL109: 0 | AM109: 0 | AN109: 0 | AO109: 0 | AP109: 0 | AQ109: 0 | AR109: 0 | AS109: 0 | AT109: 0 | AU109: 0 | AV109: 0 | AW109: 0 | AX109: 0 | AY109: 0 | AZ109: 0 | BA109: 0 | BB109: 0 | BC109: 0 | BD109: 0 | BE109: 0 | BF109: 0 | BG109: 0 | BH109: 0 | BI109: 0 | BJ109: 0
D110: 4.3303971e+08 | E110: 110017483 | F110: 1860 Charlevoix-Kamouraska region QC | G110: 12 | H110: 11 | I110: 0 | J110: 0 | K110: 0 | L110: 0 | M110: 0 | N110: 0 | O110: 0 | P110: 0 | Q110: 0 | R110: 0 | S110: 0 | T110: 0 | U110: 0 | V110: 0 | W110: 0 | X110: 0 | Y110: 0 | Z110: 0 | AA110: 0 | AB110: 0 | AC110: 0 | AD110: 0 | AE110: 0 | AF110: 0 | AG110: 0 | AH110: 0 | AI110: 0 | AJ110: 0 | AK110: 0 | AL110: 0 | AM110: 0 | AN110: 0 | AO110: 0 | AP110: 0 | AQ110: 0 | AR110: 0 | AS110: 0 | AT110: 0 | AU110: 0 | AV110: 0 | AW110: 0 | AX110: 0 | AY110: 0 | AZ110: 0 | BA110: 0 | BB110: 0 | BC110: 0 | BD110: 0 | BE110: 0 | BF110: 20528.103 | BG110: 0 | BH110: 0 | BI110: 0 | BJ110: 0
D111: 5.3283648e+08 | E111: 110017483 | F111: 1860 Charlevoix-Kamouraska region QC | G111: 12 | H111: 11 | I111: 0 | J111: 0 | K111: 0 | L111: 0 | M111: 0 | N111: 0 | O111: 0 | P111: 0 | Q111: 0 | R111: 0 | S111: 0 | T111: 0 | U111: 0 | V111: 0 | W111: 0 | X111: 0 | Y111: 0 | Z111: 0 | AA111: 0 | AB111: 0 | AC111: 0 | AD111: 0 | AE111: 0 | AF111: 0 | AG111: 0 | AH111: 0 | AI111: 0 | AJ111: 0 | AK111: 0 | AL111: 0 | AM111: 0 | AN111: 0 | AO111: 0 | AP111: 0 | AQ111: 0 | AR111: 0 | AS111: 0 | AT111: 0 | AU111: 0 | AV111: 0 | AW111: 0 | AX111: 0 | AY111: 0 | AZ111: 0 | BA111: 0 | BB111: 0 | BC111: 0 | BD111: 0 | BE111: 0 | BF111: 0 | BG111: 0 | BH111: 0 | BI111: 0 | BJ111: 0
D112: 54664805 | E112: 110024673 | F112: 1954 Eureka-Arcata CA | G112: 40 | H112: 11 | I112: 0 | J112: 0 | K112: 0 | L112: 0 | M112: 0 | N112: 0 | O112: 0 | P112: 0 | Q112: 0 | R112: 0 | S112: 0 | T112: 0 | U112: 0 | V112: 0 | W112: 0 | X112: 0 | Y112: 0 | Z112: 0 | AA112: 0 | AB112: 0 | AC112: 0 | AD112: 0 | AE112: 0 | AF112: 0 | AG112: 0 | AH112: 0 | AI112: 0 | AJ112: 0 | AK112: 0 | AL112: 0 | AM112: 0 | AN112: 0 | AO112: 0 | AP112: 0 | AQ112: 0 | AR112: 0 | AS112: 0 | AT112: 0 | AU112: 0 | AV112: 0 | AW112: 0 | AX112: 0 | AY112: 0 | AZ112: 0 | BA112: 0 | BB112: 0 | BC112: 0 | BD112: 0 | BE112: 0 | BF112: 0 | BG112: 0 | BH112: 0 | BI112: 0 | BJ112: 0
D113: 1.4781516e+10 | E113: 110029231 | F113: 1732 Montreal Region QC-Scenario 2 | G113: 3 | H113: 11 | I113: 0 | J113: 0 | K113: 0 | L113: 0 | M113: 0 | N113: 0 | O113: 0 | P113: 0 | Q113: 0 | R113: 0 | S113: 0 | T113: 0 | U113: 0 | V113: 0 | W113: 0 | X113: 0 | Y113: 0 | Z113: 0 | AA113: 0 | AB113: 0 | AC113: 0 | AD113: 0 | AE113: 0 | AF113: 0 | AG113: 0 | AH113: 0 | AI113: 0 | AJ113: 0 | AK113: 0 | AL113: 0 | AM113: 0 | AN113: 0 | AO113: 0 | AP113: 0 | AQ113: 0 | AR113: 0 | AS113: 0 | AT113: 0 | AU113: 0 | AV113: 0 | AW113: 0 | AX113: 0 | AY113: 0 | AZ113: 0 | BA113: 0 | BB113: 0 | BC113: 0 | BD113: 0 | BE113: 0 | BF113: 0 | BG113: 0 | BH113: 0 | BI113: 0 | BJ113: 0
D114: 1.7525633e+10 | E114: 110029231 | F114: 1732 Montreal Region QC-Scenario 2 | G114: 3 | H114: 11 | I114: 0 | J114: 0 | K114: 0 | L114: 0 | M114: 0 | N114: 0 | O114: 0 | P114: 0 | Q114: 0 | R114: 0 | S114: 0 | T114: 0 | U114: 0 | V114: 0 | W114: 0 | X114: 0 | Y114: 0 | Z114: 0 | AA114: 0 | AB114: 0 | AC114: 0 | AD114: 0 | AE114: 0 | AF114: 0 | AG114: 0 | AH114: 0 | AI114: 0 | AJ114: 0 | AK114: 0 | AL114: 0 | AM114: 0 | AN114: 0 | AO114: 0 | AP114: 0 | AQ114: 0 | AR114: 0 | AS114: 0 | AT114: 0 | AU114: 0 | AV114: 0 | AW114: 0 | AX114: 0 | AY114: 0 | AZ114: 0 | BA114: 0 | BB114: 0 | BC114: 0 | BD114: 0 | BE114: 0 | BF114: 0 | BG114: 0 | BH114: 0 | BI114: 0 | BJ114: 0
D115: 2.799016e+08 | E115: 110033613 | F115: 1980 Maysville KY | G115: 55 | H115: 11 | I115: 0 | J115: 0 | K115: 0 | L115: 0 | M115: 0 | N115: 0 | O115: 0 | P115: 0 | Q115: 0 | R115: 0 | S115: 0 | T115: 0 | U115: 0 | V115: 0 | W115: 0 | X115: 0 | Y115: 0 | Z115: 0 | AA115: 0 | AB115: 0 | AC115: 0 | AD115: 0 | AE115: 0 | AF115: 0 | AG115: 0 | AH115: 0 | AI115: 0 | AJ115: 0 | AK115: 0 | AL115: 0 | AM115: 0 | AN115: 0 | AO115: 0 | AP115: 0 | AQ115: 0 | AR115: 0 | AS115: 0 | AT115: 0 | AU115: 0 | AV115: 0 | AW115: 0 | AX115: 0 | AY115: 0 | AZ115: 0 | BA115: 0 | BB115: 0 | BC115: 0 | BD115: 0 | BE115: 0 | BF115: 0 | BG115: 0 | BH115: 0 | BI115: 0 | BJ115: 0
D116: 12881131 | E116: 110035565 | F116: 2011 Virginia | G116: 78 | H116: 11 | I116: 0 | J116: 0 | K116: 0 | L116: 0 | M116: 0 | N116: 0 | O116: 0 | P116: 0 | Q116: 0 | R116: 0 | S116: 0 | T116: 0 | U116: 0 | V116: 0 | W116: 0 | X116: 0 | Y116: 0 | Z116: 0 | AA116: 0 | AB116: 0 | AC116: 0 | AD116: 0 | AE116: 0 | AF116: 0 | AG116: 0 | AH116: 0 | AI116: 0 | AJ116: 0 | AK116: 0 | AL116: 0 | AM116: 0 | AN116: 0 | AO116: 0 | AP116: 0 | AQ116: 0 | AR116: 0 | AS116: 0 | AT116: 0 | AU116: 0 | AV116: 0 | AW116: 0 | AX116: 0 | AY116: 0 | AZ116: 0 | BA116: 0 | BB116: 0 | BC116: 0 | BD116: 0 | BE116: 0 | BF116: 0 | BG116: 0 | BH116: 0 | BI116: 0 | BJ116: 0
... D125: 2.3554129e+09 | E125: 190228427 | F125: 2013 Southern Alberta | G125: 4 | H125: 19 | I125: 0 | J125: 0 | K125: 0 | L125: 0 | M125: 0 | N125: 0 | O125: 0 | P125: 0 | Q125: 0 | R125: 0 | S125: 0 | T125: 0 | U125: 0 | V125: 0 | W125: 0 | X125: 0 | Y125: 0 | Z125: 0 | AA125: 0 | AB125: 0 | AC125: 0 | AD125: 0 | AE125: 0 | AF125: 0 | AG125: 0 | AH125: 0 | AI125: 0 | AJ125: 0 | AK125: 0 | AL125: 0 | AM125: 0 | AN125: 0 | AO125: 0 | AP125: 0 | AQ125: 0 | AR125: 0 | AS125: 0 | AT125: 0 | AU125: 0 | AV125: 0 | AW125: 0 | AX125: 0 | AY125: 0 | AZ125: 0 | BA125: 0 | BB125: 0 | BC125: 0 | BD125: 0 | BE125: 0 | BF125: 0 | BG125: 0 | BH125: 0 | BI125: 0 | BJ125: 0
E126: 220374119 | F126: May2010Part1_PCS13_5 | G126: 5 | H126: 22 | I126: 0 | J126: 0 | K126: 0 | L126: 0 | M126: 0 | N126: 0 | O126: 0 | P126: 0 | Q126: 0 | R126: 0 | S126: 0 | T126: 0 | U126: 0 | V126: 0 | W126: 0 | X126: 0 | Y126: 0 | Z126: 0 | AA126: 0 | AB126: 0 | AC126: 0 | AD126: 0 | AE126: 0 | AF126: 0 | AG126: 0 | AH126: 0 | AI126: 0 | AJ126: 0 | AK126: 0 | AL126: 0 | AM126: 0 | AN126: 0 | AO126: 0 | AP126: 0 | AQ126: 0 | AR126: 0 | AS126: 0 | AT126: 0 | AU126: 0 | AV126: 0 | AW126: 0 | AX126: 0 | AY126: 0 | AZ126: 0 | BA126: 0 | BB126: 0 | BC126: 0 | BD126: 0 | BE126: 0 | BF126: 0 | BG126: 0 | BH126: 0 | BI126: 0 | BJ126: 0
E127: 220402862 | F127: June2012Derecho_PCS83_4 | G127: 34 | H127: 22 | I127: 0 | J127: 0 | K127: 0 | L127: 0 | M127: 0 | N127: 0 | O127: 0 | P127: 0 | Q127: 0 | R127: 0 | S127: 0 | T127: 0 | U127: 0 | V127: 0 | W127: 0 | X127: 0 | Y127: 0 | Z127: 0 | AA127: 0 | AB127: 0 | AC127: 0 | AD127: 0 | AE127: 0 | AF127: 0 | AG127: 0 | AH127: 0 | AI127: 0 | AJ127: 0 | AK127: 0 | AL127: 0 | AM127: 0 | AN127: 0 | AO127: 0 | AP127: 0 | AQ127: 0 | AR127: 0 | AS127: 0 | AT127: 0 | AU127: 0 | AV127: 0 | AW127: 0 | AX127: 0 | AY127: 0 | AZ127: 0 | BA127: 0 | BB127: 0 | BC127: 0 | BD127: 0 | BE127: 0 | BF127: 0 | BG127: 0 | BH127: 0 | BI127: 0 | BJ127: 0
E128: 222139806 | F128: TuscaloosaOutbreak_PCS46_5 | G128: 25 | H128: 22 | I128: 0 | J128: 0 | K128: 0 | L128: 0 | M128: 0 | N128: 0 | O128: 0 | P128: 0 | Q128: 0 | R128: 0 | S128: 0 | T128: 0 | U128: 0 | V128: 0 | W128: 0 | X128: 0 | Y128: 0 | Z128: 0 | AA128: 0 | AB128: 0 | AC128: 0 | AD128: 0 | AE128: 0 | AF128: 0 | AG128: 0 | AH128: 0 | AI128: 0 | AJ128: 0 | AK128: 0 | AL128: 0 | AM128: 0 | AN128: 0 | AO128: 0 | AP128: 0 | AQ128: 0 | AR128: 0 | AS128: 0 | AT128: 0 | AU128: 0 | AV128: 0 | AW128: 0 | AX128: 0 | AY128: 0 | AZ128: 0 | BA128: 0 | BB128: 0 | BC128: 0 | BD128: 0 | BE128: 0 | BF128: 0 | BG128: 0 | BH128: 0 | BI128: 0 | BJ128: 0
D129: 5.3368949e+08 | E129: 230011531 | F129: 1982 Iwa | G129: 1 | H129: 23 | I129: 0 | J129: 0 | K129: 0 | L129: 0 | M129: 0 | N129: 0 | O129: 0 | P129: 0 | Q129: 0 | R129: 0 | S129: 0 | T129: 0 | U129: 0 | V129: 0 | W129: 0 | X129: 0 | Y129: 0 | Z129: 0 | AA129: 0 | AB129: 0 | AC129: 0 | AD129: 0 | AE129: 0 | AF129: 0 | AG129: 0 | AH129: 0 | AI129: 0 | AJ129: 0 | AK129: 0 | AL129: 0 | AM129: 0 | AN129: 0 | AO129: 0 | AP129: 0 | AQ129: 0 | AR129: 0 | AS129: 0 | AT129: 0 | AU129: 0 | AV129: 0 | AW129: 0 | AX129: 0 | AY129: 0 | AZ129: 0 | BA129: 0 | BB129: 0 | BC129: 0 | BD129: 0 | BE129: 0 | BF129: 0 | BG129: 0 | BH129: 0 | BI129: 0 | BJ129: 0
D130: 8.5193677e+08 | E130: 270002599 | F130: 2008 Dolly | G130: 52 | H130: 27 | I130: 0 | J130: 0 | K130: 0 | L130: 0 | M130: 0 | N130: 0 | O130: 0 | P130: 0 | Q130: 0 | R130: 0 | S130: 0 | T130: 0 | U130: 0 | V130: 0 | W130: 0 | X130: 0 | Y130: 0 | Z130: 0 | AA130: 0 | AB130: 0 | AC130: 0 | AD130: 0 | AE130: 0 | AF130: 0 | AG130: 0 | AH130: 0 | AI130: 0 | AJ130: 0 | AK130: 0 | AL130: 0 | AM130: 0 | AN130: 0 | AO130: 0 | AP130: 0 | AQ130: 0 | AR130: 0 | AS130: 0 | AT130: 0 | AU130: 0 | AV130: 0 | AW130: 0 | AX130: 0 | AY130: 0 | AZ130: 0 | BA130: 0 | BB130: 0 | BC130: 0 | BD130: 0 | BE130: 0 | BF130: 0 | BG130: 0 | BH130: 0 | BI130: 0 | BJ130: 0
D131: 1.547181e+10 | E131: 270021407 | F131: 2005 Rita | G131: 50 | H131: 27 | I131: 0 | J131: 0 | K131: 0 | L131: 0 | M131: 0 | N131: 0 | O131: 0 | P131: 0 | Q131: 0 | R131: 0 | S131: 0 | T131: 0 | U131: 0 | V131: 0 | W131: 0 | X131: 0 | Y131: 0 | Z131: 0 | AA131: 0 | AB131: 0 | AC131: 0 | AD131: 0 | AE131: 0 | AF131: 0 | AG131: 0 | AH131: 0 | AI131: 0 | AJ131: 256790.95 | AK131: 0 | AL131: 0 | AM131: 0 | AN131: 0 | AO131: 0 | AP131: 0 | AQ131: 0 | AR131: 0 | AS131: 0 | AT131: 0 | AU131: 0 | AV131: 0 | AW131: 0 | AX131: 0 | AY131: 0 | AZ131: 0 | BA131: 0 | BB131: 0 | BC131: 0 | BD131: 13044.115 | BE131: 0 | BF131: 0 | BG131: 0 | BH131: 0 | BI131: 0 | BJ131: 0
D132: 8.3627578e+08 | E132: 270024303 | F132: 1955 Janet | G132: 22 | H132: 27 | I132: 0 | J132: 0 | K132: 0 | L132: 0 | M132: 0 | N132: 0 | O132: 0 | P132: 0 | Q132: 0 | R132: 0 | S132: 0 | T132: 0 | U132: 0 | V132: 0 | W132: 0 | X132: 0 | Y132: 0 | Z132: 0 | AA132: 0 | AB132: 0 | AC132: 0 | AD132: 0 | AE132: 0 | AF132: 0 | AG132: 0 | AH132: 0 | AI132: 0 | AJ132: 0 | AK132: 0 | AL132: 0 | AM132: 0 | AN132: 0 | AO132: 0 | AP132: 0 | AQ132: 0 | AR132: 0 | AS132: 0 | AT132: 0 | AU132: 0 | AV132: 0 | AW132: 0 | AX132: 0 | AY132: 0 | AZ132: 0 | BA132: 0 | BB132: 0 | BC132: 0 | BD132: 0 | BE132: 0 | BF132: 0 | BG132: 0 | BH132: 0 | BI132: 0 | BJ132: 0
D133: 2.473e+10 | E133: 270069685 | F133: 2004 Ivan | G133: 49 | H133: 27 | I133: 0 | J133: 0 | K133: 0 | L133: 0 | M133: 0 | N133: 0 | O133: 0 | P133: 0 | Q133: 0 | R133: 0 | S133: 0 | T133: 0 | U133: 0 | V133: 0 | W133: 0 | X133: 0 | Y133: 0 | Z133: 0 | AA133: 0 | AB133: 0 | AC133: 0 | AD133: 0 | AE133: 0 | AF133: 0 | AG133: 0 | AH133: 0 | AI133: 0 | AJ133: 0 | AK133: 0 | AL133: 0 | AM133: 0 | AN133: 0 | AO133: 0 | AP133: 0 | AQ133: 0 | AR133: 0 | AS133: 0 | AT133: 0 | AU133: 0 | AV133: 0 | AW133: 0 | AX133: 0 | AY133: 0 | AZ133: 0 | BA133: 0 | BB133: 0 | BC133: 0 | BD133: 0 | BE133: 0 | BF133: 0 | BG133: 0 | BH133: 0 | BI133: 0 | BJ133: 0
D134: 9.8946154e+09 | E134: 270127772 | F134: 1985 Elena | G134: 32 | H134: 27 | I134: 0 | J134: 0 | K134: 0 | L134: 0 | M134: 0 | N134: 0 | O134: 0 | P134: 0 | Q134: 0 | R134: 0 | S134: 0 | T134: 0 | U134: 0 | V134: 0 | W134: 0 | X134: 0 | Y134: 0 | Z134: 0 | AA134: 0 | AB134: 0 | AC134: 0 | AD134: 0 | AE134: 0 | AF134: 0 | AG134: 0 | AH134: 0 | AI134: 0 | AJ134: 0 | AK134: 0 | AL134: 0 | AM134: 0 | AN134: 0 | AO134: 0 | AP134: 0 | AQ134: 0 | AR134: 0 | AS134: 0 | AT134: 0 | AU134: 0 | AV134: 0 | AW134: 0 | AX134: 0 | AY134: 0 | AZ134: 0 | BA134: 0 | BB134: 0 | BC134: 0 | BD134: 0 | BE134: 0 | BF134: 0 | BG134: 0 | BH134: 0 | BI134: 0 | BJ134: 0
D135: 1.8398822e+10 | E135: 270133692 | F135: 1954 Carol | G135: 21 | H135: 27 | I135: 0 | J135: 0 | K135: 0 | L135: 0 | M135: 0 | N135: 0 | O135: 0 | P135: 0 | Q135: 0 | R135: 0 | S135: 0 | T135: 514734.14 | U135: 0 | V135: 514734.14 | W135: 0 | X135: 0 | Y135: 0 | Z135: 0 | AA135: 0 | AB135: 0 | AC135: 0 | AD135: 0 | AE135: 0 | AF135: 0 | AG135: 0 | AH135: 0 | AI135: 0 | AJ135: 0 | AK135: 0 | AL135: 0 | AM135: 0 | AN135: 0 | AO135: 0 | AP135: 0 | AQ135: 0 | AR135: 0 | AS135: 0 | AT135: 0 | AU135: 0 | AV135: 0 | AW135: 0 | AX135: 0 | AY135: 0 | AZ135: 0 | BA135: 0 | BB135: 0 | BC135: 0 | BD135: 0 | BE135: 0 | BF135: 0 | BG135: 0 | BH135: 0 | BI135: 0 | BJ135: 0
D136: 347541103 | E136: 270139154 | F136: 2003 Ignatio | G136: 48 | H136: 27 | I136: 0 | J136: 0 | K136: 0 | L136: 0 | M136: 0 | N136: 0 | O136: 0 | P136: 0 | Q136: 0 | R136: 0 | S136: 0 | T136: 0 | U136: 0 | V136: 0 | W136: 0 | X136: 0 | Y136: 0 | Z136: 0 | AA136: 0 | AB136: 0 | AC136: 0 | AD136: 0 | AE136: 0 | AF136: 0 | AG136: 0 | AH136: 0 | AI136: 0 | AJ136: 0 | AK136: 0 | AL136: 0 | AM136: 0 | AN136: 0 | AO136: 0 | AP136: 0 | AQ136: 0 | AR136: 0 | AS136: 0 | AT136: 0 | AU136: 0 | AV136: 0 | AW136: 0 | AX136: 0 | AY136: 0 | AZ136: 0 | BA136: 0 | BB136: 0 | BC136: 0 | BD136: 0 | BE136: 0 | BF136: 0 | BG136: 0 | BH136: 0 | BI136: 0 | BJ136: 0
D137: 4.2229892e+09 | E137: 270174471 | F137: 2016 Matthew | G137: 56 | H137: 27 | I137: 0 | J137: 0 | K137: 0 | L137: 0 | M137: 0 | N137: 0 | O137: 0 | P137: 0 | Q137: 0 | R137: 0 | S137: 0 | T137: 0 | U137: 0 | V137: 0 | W137: 0 | X137: 0 | Y137: 0 | Z137: 0 | AA137: 0 | AB137: 0 | AC137: 0 | AD137: 0 | AE137: 0 | AF137: 0 | AG137: 0 | AH137: 0 | AI137: 0 | AJ137: 0 | AK137: 0 | AL137: 0 | AM137: 0 | AN137: 0 | AO137: 0 | AP137: 0 | AQ137: 0 | AR137: 0 | AS137: 0 | AT137: 0 | AU137: 0 | AV137: 0 | AW137: 0 | AX137: 0 | AY137: 0 | AZ137: 0 | BA137: 0 | BB137: 0 | BC137: 0 | BD137: 0 | BE137: 0 | BF137: 0 | BG137: 0 | BH137: 0 | BI137: 0 | BJ137: 0
D138: 2.29414e+10 | E138: 270174842 | F138: 2004 Charley | G138: 49 | H138: 27 | I138: 0 | J138: 0 | K138: 0 | L138: 0 | M138: 0 | N138: 0 | O138: 0 | P138: 0 | Q138: 0 | R138: 0 | S138: 0 | T138: 0 | U138: 0 | V138: 0 | W138: 0 | X138: 0 | Y138: 0 | Z138: 0 | AA138: 0 | AB138: 0 | AC138: 0 | AD138: 0 | AE138: 0 | AF138: 0 | AG138: 0 | AH138: 0 | AI138: 0 | AJ138: 0 | AK138: 0 | AL138: 0 | AM138: 0 | AN138: 0 | AO138: 0 | AP138: 0 | AQ138: 0 | AR138: 0 | AS138: 0 | AT138: 0 | AU138: 0 | AV138: 0 | AW138: 0 | AX138: 0 | AY138: 0 | AZ138: 0 | BA138: 0 | BB138: 0 | BC138: 0 | BD138: 0 | BE138: 0 | BF138: 0 | BG138: 0 | BH138: 0 | BI138: 0 | BJ138: 0
D139: 1.7959834e+11 | E139: 270195425 | F139: 1928 Okeechobee | G139: 9 | H139: 27 | I139: 0 | J139: 0 | K139: 0 | L139: 0 | M139: 0 | N139: 0 | O139: 0 | P139: 0 | Q139: 0 | R139: 0 | S139: 0 | T139: 0 | U139: 0 | V139: 0 | W139: 0 | X139: 0 | Y139: 0 | Z139: 0 | AA139: 0 | AB139: 0 | AC139: 0 | AD139: 0 | AE139: 0 | AF139: 0 | AG139: 0 | AH139: 0 | AI139: 0 | AJ139: 0 | AK139: 0 | AL139: 0 | AM139: 0 | AN139: 0 | AO139: 0 | AP139: 0 | AQ139: 0 | AR139: 0 | AS139: 0 | AT139: 0 | AU139: 0 | AV139: 0 | AW139: 0 | AX139: 0 | AY139: 0 | AZ139: 0 | BA139: 0 | BB139: 0 | BC139: 0 | BD139: 0 | BE139: 0 | BF139: 0 | BG139: 0 | BH139: 0 | BI139: 0 | BJ139: 0
D140: 1.9784649e+11 | E140: 270205454 | F140: 1926 Great Miami | G140: 8 | H140: 27 | I140: 0 | J140: 0 | K140: 0 | L140: 0 | M140: 0 | N140: 0 | O140: 0 | P140: 0 | Q140: 0 | R140: 0 | S140: 0 | T140: 0 | U140: 0 | V140: 249999.9 | W140: 0 | X140: 0 | Y140: 249999.9 | Z140: 0 | AA140: 0 | AB140: 0 | AC140: 0 | AD140: 0 | AE140: 0 | AF140: 0 | AG140: 0 | AH140: 0 | AI140: 0 | AJ140: 0 | AK140: 0 | AL140: 0 | AM140: 0 | AN140: 0 | AO140: 0 | AP140: 0 | AQ140: 0 | AR140: 0 | AS140: 0 | AT140: 0 | AU140: 0 | AV140: 0 | AW140: 0 | AX140: 0 | AY140: 0 | AZ140: 0 | BA140: 0 | BB140: 0 | BC140: 0 | BD140: 0 | BE140: 0 | BF140: 0 | BG140: 0 | BH140: 0 | BI140: 0 | BJ140: 0
... D183: 3.2416539e+08 | E183: 600171810 | F183: 1979 Hope | G183: 12 | H183: 60 | I183: 0 | J183: 0 | K183: 0 | L183: 0 | M183: 0 | N183: 0 | O183: 0 | P183: 0 | Q183: 0 | R183: 0 | S183: 0 | T183: 0 | U183: 0 | V183: 0 | W183: 0 | X183: 0 | Y183: 0 | Z183: 0 | AA183: 0 | AB183: 0 | AC183: 0 | AD183: 0 | AE183: 0 | AF183: 0 | AG183: 0 | AH183: 0 | AI183: 0 | AJ183: 0 | AK183: 0 | AL183: 0 | AM183: 0 | AN183: 0 | AO183: 0 | AP183: 0 | AQ183: 0 | AR183: 0 | AS183: 0 | AT183: 0 | AU183: 0 | AV183: 0 | AW183: 0 | AX183: 0 | AY183: 0 | AZ183: 0 | BA183: 0 | BB183: 0 | BC183: 0 | BD183: 0 | BE183: 0 | BF183: 0 | BG183: 0 | BH183: 0 | BI183: 0 | BJ183: 0
E184: 600212797 | F184: 2002 Rusa | G184: 28 | H184: 60 | I184: 0 | J184: 0 | K184: 0 | L184: 0 | M184: 0 | N184: 0 | O184: 0 | P184: 0 | Q184: 0 | R184: 0 | S184: 0 | T184: 0 | U184: 0 | V184: 0 | W184: 0 | X184: 0 | Y184: 0 | Z184: 0 | AA184: 0 | AB184: 0 | AC184: 0 | AD184: 0 | AE184: 0 | AF184: 0 | AG184: 0 | AH184: 0 | AI184: 0 | AJ184: 0 | AK184: 0 | AL184: 0 | AM184: 0 | AN184: 0 | AO184: 0 | AP184: 0 | AQ184: 0 | AR184: 0 | AS184: 0 | AT184: 0 | AU184: 0 | AV184: 0 | AW184: 0 | AX184: 0 | AY184: 0 | AZ184: 0 | BA184: 0 | BB184: 0 | BC184: 0 | BD184: 0 | BE184: 0 | BF184: 0 | BG184: 0 | BH184: 0 | BI184: 0 | BJ184: 0
D185: 8.5805096e+08 | E185: 600214308 | F185: 2009 Ketsana | G185: 48 | H185: 60 | I185: 0 | J185: 0 | K185: 0 | L185: 0 | M185: 0 | N185: 0 | O185: 0 | P185: 0 | Q185: 0 | R185: 0 | S185: 0 | T185: 0 | U185: 0 | V185: 0 | W185: 0 | X185: 0 | Y185: 0 | Z185: 0 | AA185: 0 | AB185: 0 | AC185: 0 | AD185: 0 | AE185: 0 | AF185: 0 | AG185: 0 | AH185: 0 | AI185: 0 | AJ185: 0 | AK185: 0 | AL185: 0 | AM185: 0 | AN185: 0 | AO185: 0 | AP185: 0 | AQ185: 0 | AR185: 0 | AS185: 0 | AT185: 0 | AU185: 0 | AV185: 0 | AW185: 0 | AX185: 0 | AY185: 0 | AZ185: 0 | BA185: 0 | BB185: 0 | BC185: 0 | BD185: 0 | BE185: 0 | BF185: 0 | BG185: 0 | BH185: 0 | BI185: 0 | BJ185: 0
E186: 600239216 | F186: 1959 Sarah | G186: 4 | H186: 60 | I186: 0 | J186: 0 | K186: 0 | L186: 0 | M186: 0 | N186: 0 | O186: 0 | P186: 0 | Q186: 0 | R186: 0 | S186: 0 | T186: 0 | U186: 0 | V186: 0 | W186: 0 | X186: 0 | Y186: 0 | Z186: 0 | AA186: 0 | AB186: 0 | AC186: 0 | AD186: 0 | AE186: 0 | AF186: 0 | AG186: 0 | AH186: 0 | AI186: 0 | AJ186: 0 | AK186: 0 | AL186: 0 | AM186: 0 | AN186: 0 | AO186: 0 | AP186: 0 | AQ186: 0 | AR186: 0 | AS186: 0 | AT186: 0 | AU186: 0 | AV186: 0 | AW186: 0 | AX186: 0 | AY186: 0 | AZ186: 0 | BA186: 0 | BB186: 0 | BC186: 0 | BD186: 0 | BE186: 0 | BF186: 0 | BG186: 0 | BH186: 0 | BI186: 0 | BJ186: 0
E187: 600249406 | F187: 1987 Thelma | G187: 15 | H187: 60 | I187: 0 | J187: 0 | K187: 0 | L187: 0 | M187: 0 | N187: 0 | O187: 0 | P187: 0 | Q187: 0 | R187: 0 | S187: 0 | T187: 0 | U187: 0 | V187: 0 | W187: 0 | X187: 0 | Y187: 0 | Z187: 0 | AA187: 0 | AB187: 0 | AC187: 0 | AD187: 0 | AE187: 0 | AF187: 0 | AG187: 0 | AH187: 0 | AI187: 0 | AJ187: 0 | AK187: 0 | AL187: 0 | AM187: 0 | AN187: 0 | AO187: 0 | AP187: 0 | AQ187: 0 | AR187: 0 | AS187: 0 | AT187: 0 | AU187: 0 | AV187: 0 | AW187: 0 | AX187: 0 | AY187: 0 | AZ187: 0 | BA187: 0 | BB187: 0 | BC187: 0 | BD187: 0 | BE187: 0 | BF187: 0 | BG187: 0 | BH187: 0 | BI187: 0 | BJ187: 0
D188: 3635282.7 | E188: 700161135 | F188: 2008 El Calvario Colombia | G188: 65 | H188: 70 | I188: 0 | J188: 0 | K188: 0 | L188: 0 | M188: 0 | N188: 0 | O188: 0 | P188: 0 | Q188: 0 | R188: 0 | S188: 0 | T188: 0 | U188: 0 | V188: 0 | W188: 0 | X188: 0 | Y188: 0 | Z188: 0 | AA188: 0 | AB188: 0 | AC188: 0 | AD188: 0 | AE188: 0 | AF188: 0 | AG188: 0 | AH188: 0 | AI188: 0 | AJ188: 0 | AK188: 0 | AL188: 0 | AM188: 0 | AN188: 0 | AO188: 0 | AP188: 0 | AQ188: 0 | AR188: 0 | AS188: 0 | AT188: 0 | AU188: 0 | AV188: 0 | AW188: 0 | AX188: 0 | AY188: 0 | AZ188: 0 | BA188: 0 | BB188: 0 | BC188: 0 | BD188: 0 | BE188: 0 | BF188: 0 | BG188: 0 | BH188: 0 | BI188: 0 | BJ188: 0
D189: 1.4175994e+09 | E189: 700410696 | F189: 1999 Armenia Colombia | G189: 59 | H189: 70 | I189: 0 | J189: 0 | K189: 0 | L189: 0 | M189: 0 | N189: 0 | O189: 0 | P189: 0 | Q189: 0 | R189: 0 | S189: 0 | T189: 0 | U189: 0 | V189: 0 | W189: 0 | X189: 0 | Y189: 0 | Z189: 0 | AA189: 0 | AB189: 0 | AC189: 0 | AD189: 0 | AE189: 0 | AF189: 0 | AG189: 0 | AH189: 0 | AI189: 0 | AJ189: 0 | AK189: 0 | AL189: 0 | AM189: 0 | AN189: 0 | AO189: 0 | AP189: 0 | AQ189: 0 | AR189: 0 | AS189: 0 | AT189: 0 | AU189: 0 | AV189: 0 | AW189: 0 | AX189: 0 | AY189: 0 | AZ189: 0 | BA189: 0 | BB189: 0 | BC189: 0 | BD189: 0 | BE189: 0 | BF189: 0 | BG189: 0 | BH189: 0 | BI189: 0 | BJ189: 0
D190: 16881356 | E190: 700652017 | F190: 1928 Chachapoyas Peru | G190: 21 | H190: 70 | I190: 0 | J190: 0 | K190: 0 | L190: 0 | M190: 0 | N190: 0 | O190: 0 | P190: 0 | Q190: 0 | R190: 0 | S190: 0 | T190: 0 | U190: 0 | V190: 0 | W190: 0 | X190: 0 | Y190: 0 | Z190: 0 | AA190: 0 | AB190: 0 | AC190: 0 | AD190: 0 | AE190: 0 | AF190: 0 | AG190: 0 | AH190: 0 | AI190: 0 | AJ190: 0 | AK190: 0 | AL190: 0 | AM190: 0 | AN190: 0 | AO190: 0 | AP190: 0 | AQ190: 0 | AR190: 0 | AS190: 0 | AT190: 0 | AU190: 0 | AV190: 0 | AW190: 0 | AX190: 0 | AY190: 0 | AZ190: 0 | BA190: 0 | BB190: 0 | BC190: 0 | BD190: 0 | BE190: 0 | BF190: 0 | BG190: 0 | BH190: 0 | BI190: 0 | BJ190: 0
D191: 54500170 | E191: 700875777 | F191: 1970 Piura Peru | G191: 37 | H191: 70 | I191: 0 | J191: 0 | K191: 0 | L191: 0 | M191: 0 | N191: 0 | O191: 0 | P191: 0 | Q191: 0 | R191: 0 | S191: 0 | T191: 0 | U191: 0 | V191: 0 | W191: 0 | X191: 0 | Y191: 0 | Z191: 0 | AA191: 0 | AB191: 0 | AC191: 0 | AD191: 0 | AE191: 0 | AF191: 0 | AG191: 0 | AH191: 0 | AI191: 0 | AJ191: 0 | AK191: 0 | AL191: 0 | AM191: 0 | AN191: 0 | AO191: 0 | AP191: 0 | AQ191: 0 | AR191: 0 | AS191: 0 | AT191: 0 | AU191: 0 | AV191: 0 | AW191: 0 | AX191: 0 | AY191: 0 | AZ191: 0 | BA191: 0 | BB191: 0 | BC191: 0 | BD191: 0 | BE191: 0 | BF191: 0 | BG191: 0 | BH191: 0 | BI191: 0 | BJ191: 0
D192: 88473237 | E192: 700977309 | F192: 1990 Moyobamba | G192: 51 | H192: 70 | I192: 0 | J192: 0 | K192: 0 | L192: 0 | M192: 0 | N192: 0 | O192: 0 | P192: 0 | Q192: 0 | R192: 0 | S192: 0 | T192: 0 | U192: 0 | V192: 0 | W192: 0 | X192: 0 | Y192: 0 | Z192: 0 | AA192: 0 | AB192: 0 | AC192: 0 | AD192: 0 | AE192: 0 | AF192: 0 | AG192: 0 | AH192: 0 | AI192: 0 | AJ192: 0 | AK192: 0 | AL192: 0 | AM192: 0 | AN192: 0 | AO192: 0 | AP192: 0 | AQ192: 0 | AR192: 0 | AS192: 0 | AT192: 0 | AU192: 0 | AV192: 0 | AW192: 0 | AX192: 0 | AY192: 0 | AZ192: 0 | BA192: 0 | BB192: 0 | BC192: 0 | BD192: 0 | BE192: 0 | BF192: 0 | BG192: 0 | BH192: 500000 | BI192: 0 | BJ192: 0
D193: 1641.18 | E193: 700998265 | F193: 1950 Santander Colombia | G193: 29 | H193: 70 | I193: 0 | J193: 0 | K193: 0 | L193: 0 | M193: 0 | N193: 0 | O193: 0 | P193: 0 | Q193: 0 | R193: 0 | S193: 0 | T193: 0 | U193: 0 | V193: 0 | W193: 0 | X193: 0 | Y193: 0 | Z193: 0 | AA193: 0 | AB193: 0 | AC193: 0 | AD193: 0 | AE193: 0 | AF193: 0 | AG193: 0 | AH193: 0 | AI193: 0 | AJ193: 0 | AK193: 0 | AL193: 0 | AM193: 0 | AN193: 0 | AO193: 0 | AP193: 0 | AQ193: 0 | AR193: 0 | AS193: 0 | AT193: 0 | AU193: 0 | AV193: 0 | AW193: 0 | AX193: 0 | AY193: 0 | AZ193: 0 | BA193: 0 | BB193: 0 | BC193: 0 | BD193: 0 | BE193: 0 | BF193: 0 | BG193: 0 | BH193: 0 | BI193: 0 | BJ193: 0
D194: 5.4351058e+09 | E194: 701054194 | F194: 1604 Arica Chile | G194: 2 | H194: 70 | I194: 0 | J194: 0 | K194: 0 | L194: 0 | M194: 0 | N194: 0 | O194: 0 | P194: 0 | Q194: 0 | R194: 0 | S194: 0 | T194: 0 | U194: 0 | V194: 0 | W194: 0 | X194: 0 | Y194: 0 | Z194: 0 | AA194: 0 | AB194: 0 | AC194: 0 | AD194: 0 | AE194: 0 | AF194: 0 | AG194: 0 | AH194: 0 | AI194: 0 | AJ194: 0 | AK194: 0 | AL194: 0 | AM194: 0 | AN194: 0 | AO194: 0 | AP194: 0 | AQ194: 0 | AR194: 0 | AS194: 0 | AT194: 0 | AU194: 0 | AV194: 0 | AW194: 0 | AX194: 0 | AY194: 0 | AZ194: 0 | BA194: 0 | BB194: 0 | BC194: 0 | BD194: 0 | BE194: 0 | BF194: 0 | BG194: 0 | BH194: 0 | BI194: 0 | BJ194: 0
D195: 3.1719576e+08 | E195: 701079115 | F195: 1983 Popoyan Colombia | G195: 46 | H195: 70 | I195: 0 | J195: 0 | K195: 0 | L195: 0 | M195: 0 | N195: 0 | O195: 0 | P195: 0 | Q195: 0 | R195: 0 | S195: 0 | T195: 0 | U195: 0 | V195: 0 | W195: 0 | X195: 0 | Y195: 0 | Z195: 0 | AA195: 0 | AB195: 0 | AC195: 0 | AD195: 0 | AE195: 0 | AF195: 0 | AG195: 0 | AH195: 0 | AI195: 0 | AJ195: 0 | AK195: 0 | AL195: 0 | AM195: 0 | AN195: 0 | AO195: 0 | AP195: 0 | AQ195: 0 | AR195: 0 | AS195: 0 | AT195: 0 | AU195: 0 | AV195: 0 | AW195: 0 | AX195: 0 | AY195: 0 | AZ195: 0 | BA195: 0 | BB195: 0 | BC195: 0 | BD195: 0 | BE195: 0 | BF195: 0 | BG195: 0 | BH195: 0 | BI195: 0 | BJ195: 0
D196: 1.5633978e+09 | E196: 701251329 | F196: 1917 Bogota Colombia | G196: 18 | H196: 70 | I196: 0 | J196: 0 | K196: 0 | L196: 0 | M196: 0 | N196: 0 | O196: 0 | P196: 0 | Q196: 0 | R196: 0 | S196: 0 | T196: 0 | U196: 0 | V196: 0 | W196: 0 | X196: 0 | Y196: 0 | Z196: 0 | AA196: 0 | AB196: 0 | AC196: 0 | AD196: 0 | AE196: 0 | AF196: 0 | AG196: 0 | AH196: 0 | AI196: 0 | AJ196: 0 | AK196: 0 | AL196: 0 | AM196: 0 | AN196: 0 | AO196: 0 | AP196: 0 | AQ196: 0 | AR196: 0 | AS196: 0 | AT196: 0 | AU196: 0 | AV196: 0 | AW196: 0 | AX196: 0 | AY196: 0 | AZ196: 0 | BA196: 0 | BB196: 0 | BC196: 0 | BD196: 0 | BE196: 0 | BF196: 0 | BG196: 0 | BH196: 0 | BI196: 0 | BJ196: 0
E197: 920003955 | F197: June 21 - July 2, 2007 UK Summer Floods Event | G197: 2 | H197: 92 | I197: 0 | J197: 0 | K197: 0 | L197: 0 | M197: 0 | N197: 0 | O197: 0 | P197: 0 | Q197: 0 | R197: 0 | S197: 0 | T197: 0 | U197: 0 | V197: 0 | W197: 0 | X197: 0 | Y197: 0 | Z197: 0 | AA197: 0 | AB197: 0 | AC197: 0 | AD197: 0 | AE197: 0 | AF197: 0 | AG197: 0 | AH197: 0 | AI197: 0 | AJ197: 0 | AK197: 0 | AL197: 0 | AM197: 0 | AN197: 0 | AO197: 0 | AP197: 0 | AQ197: 0 | AR197: 0 | AS197: 0 | AT197: 0 | AU197: 0 | AV197: 0 | AW197: 0 | AX197: 0 | AY197: 0 | AZ197: 0 | BA197: 0 | BB197: 0 | BC197: 0 | BD197: 0 | BE197: 0 | BF197: 0 | BG197: 0 | BH197: 0 | BI197: 0 | BJ197: 0
E198: 920022604 | F198: 2011 IE October Floods | G198: 5 | H198: 92 | I198: 0 | J198: 0 | K198: 0 | L198: 0 | M198: 0 | N198: 0 | O198: 0 | P198: 0 | Q198: 0 | R198: 0 | S198: 0 | T198: 0 | U198: 0 | V198: 0 | W198: 0 | X198: 0 | Y198: 0 | Z198: 0 | AA198: 0 | AB198: 0 | AC198: 0 | AD198: 0 | AE198: 0 | AF198: 0 | AG198: 0 | AH198: 0 | AI198: 0 | AJ198: 0 | AK198: 0 | AL198: 0 | AM198: 0 | AN198: 0 | AO198: 0 | AP198: 0 | AQ198: 0 | AR198: 0 | AS198: 0 | AT198: 0 | AU198: 0 | AV198: 0 | AW198: 0 | AX198: 0 | AY198: 0 | AZ198: 0 | BA198: 0 | BB198: 0 | BC198: 0 | BD198: 0 | BE198: 0 | BF198: 0 | BG198: 0 | BH198: 0 | BI198: 0 | BJ198: 0
E199: 920037484 | F199: December 22 - January 15, 2015 UK Winter Floods Storms Eva-Frank | G199: 8 | H199: 92 | I199: 0 | J199: 0 | K199: 0 | L199: 0 | M199: 0 | N199: 0 | O199: 0 | P199: 0 | Q199: 0 | R199: 0 | S199: 0 | T199: 0 | U199: 0 | V199: 0 | W199: 0 | X199: 0 | Y199: 0 | Z199: 0 | AA199: 0 | AB199: 0 | AC199: 0 | AD199: 0 | AE199: 0 | AF199: 0 | AG199: 0 | AH199: 0 | AI199: 0 | AJ199: 0 | AK199: 0 | AL199: 0 | AM199: 0 | AN199: 0 | AO199: 0 | AP199: 0 | AQ199: 0 | AR199: 0 | AS199: 0 | AT199: 0 | AU199: 0 | AV199: 0 | AW199: 0 | AX199: 0 | AY199: 0 | AZ199: 0 | BA199: 0 | BB199: 0 | BC199: 0 | BD199: 0 | BE199: 0 | BF199: 0 | BG199: 0 | BH199: 0 | BI199: 0 | BJ199: 0
D200: 902242.7 | E200: 960043404 | F200: 2009 Sicilia Flood | G200: 5 | H200: 96 | I200: 0 | J200: 0 | K200: 0 | L200: 0 | M200: 0 | N200: 0 | O200: 0 | P200: 0 | Q200: 0 | R200: 0 | S200: 0 | T200: 0 | U200: 0 | V200: 0 | W200: 0 | X200: 0 | Y200: 0 | Z200: 0 | AA200: 0 | AB200: 0 | AC200: 0 | AD200: 0 | AE200: 0 | AF200: 0 | AG200: 0 | AH200: 0 | AI200: 0 | AJ200: 0 | AK200: 0 | AL200: 0 | AM200: 0 | AN200: 0 | AO200: 0 | AP200: 0 | AQ200: 0 | AR200: 0 | AS200: 0 | AT200: 0 | AU200: 0 | AV200: 0 | AW200: 0 | AX200: 0 | AY200: 0 | AZ200: 0 | BA200: 0 | BB200: 0 | BC200: 0 | BD200: 0 | BE200: 0 | BF200: 0 | BG200: 0 | BH200: 0 | BI200: 0 | BJ200: 0
D201: 2.9142521e+08 | E201: 50356251 | F201: 2017 Mendocino Lake Complex | G201: 12 | H201: 5 | I201: 0 | J201: 0 | K201: 0 | L201: 0 | M201: 0 | N201: 0 | O201: 0 | P201: 0 | Q201: 0 | R201: 0 | S201: 0 | T201: 0 | U201: 0 | V201: 0 | W201: 0 | X201: 0 | Y201: 0 | Z201: 0 | AA201: 0 | AB201: 0 | AC201: 0 | AD201: 0 | AE201: 0 | AF201: 0 | AG201: 0 | AH201: 0 | AI201: 0 | AJ201: 0 | AK201: 0 | AL201: 0 | AM201: 0 | AN201: 0 | AO201: 0 | AP201: 0 | AQ201: 0 | AR201: 0 | AS201: 0 | AT201: 0 | AU201: 0 | AV201: 0 | AW201: 0 | AX201: 0 | AY201: 0 | AZ201: 0 | BA201: 0 | BB201: 0 | BC201: 0 | BD201: 0 | BE201: 0 | BF201: 0 | BG201: 0 | BH201: 0 | BI201: 0 | BJ201: 0
D202: 4.0577446e+08 | E202: 52730410 | F202: 2013 Black Forest | G202: 10 | H202: 5 | I202: 0 | J202: 0 | K202: 0 | L202: 0 | M202: 0 | N202: 0 | O202: 0 | P202: 0 | Q202: 0 | R202: 0 | S202: 0 | T202: 0 | U202: 0 | V202: 0 | W202: 0 | X202: 0 | Y202: 0 | Z202: 0 | AA202: 0 | AB202: 0 | AC202: 0 | AD202: 0 | AE202: 0 | AF202: 0 | AG202: 0 | AH202: 0 | AI202: 0 | AJ202: 0 | AK202: 0 | AL202: 0 | AM202: 0 | AN202: 0 | AO202: 0 | AP202: 0 | AQ202: 0 | AR202: 0 | AS202: 0 | AT202: 0 | AU202: 0 | AV202: 0 | AW202: 0 | AX202: 0 | AY202: 0 | AZ202: 0 | BA202: 0 | BB202: 0 | BC202: 0 | BD202: 0 | BE202: 0 | BF202: 0 | BG202: 0 | BH202: 0 | BI202: 0 | BJ202: 0
D203: 2.2774946e+09 | E203: 53016051 | F203: 2020 Glass | G203: 14 | H203: 5 | I203: 0 | J203: 0 | K203: 0 | L203: 0 | M203: 0 | N203: 0 | O203: 0 | P203: 0 | Q203: 0 | R203: 0 | S203: 0 | T203: 0 | U203: 0 | V203: 0 | W203: 0 | X203: 0 | Y203: 0 | Z203: 0 | AA203: 0 | AB203: 0 | AC203: 0 | AD203: 0 | AE203: 0 | AF203: 0 | AG203: 0 | AH203: 0 | AI203: 0 | AJ203: 0 | AK203: 0 | AL203: 0 | AM203: 0 | AN203: 0 | AO203: 0 | AP203: 0 | AQ203: 0 | AR203: 0 | AS203: 0 | AT203: 0 | AU203: 0 | AV203: 0 | AW203: 0 | AX203: 0 | AY203: 0 | AZ203: 0 | BA203: 0 | BB203: 0 | BC203: 0 | BD203: 0 | BE203: 0 | BF203: 0 | BG203: 0 | BH203: 0 | BI203: 0 | BJ203: 0
D204: 3.3151452e+08 | E204: 53332729 | F204: 2022 Hermits Peak | G204: 16 | H204: 5 | I204: 0 | J204: 0 | K204: 0 | L204: 0 | M204: 0 | N204: 0 | O204: 0 | P204: 0 | Q204: 0 | R204: 0 | S204: 0 | T204: 0 | U204: 0 | V204: 0 | W204: 0 | X204: 0 | Y204: 0 | Z204: 0 | AA204: 0 | AB204: 0 | AC204: 0 | AD204: 0 | AE204: 0 | AF204: 0 | AG204: 0 | AH204: 0 | AI204: 0 | AJ204: 0 | AK204: 0 | AL204: 0 | AM204: 0 | AN204: 0 | AO204: 0 | AP204: 0 | AQ204: 0 | AR204: 0 | AS204: 0 | AT204: 0 | AU204: 0 | AV204: 0 | AW204: 0 | AX204: 0 | AY204: 0 | AZ204: 0 | BA204: 0 | BB204: 0 | BC204: 0 | BD204: 0 | BE204: 0 | BF204: 0 | BG204: 0 | BH204: 0 | BI204: 0 | BJ204: 0
D205: 3.0350465e+09 | E205: 80135593 | F205: 1993 The Great Flood | G205: 1 | H205: 8 | I205: 0 | J205: 0 | K205: 0 | L205: 0 | M205: 0 | N205: 0 | O205: 0 | P205: 0 | Q205: 0 | R205: 0 | S205: 0 | T205: 0 | U205: 0 | V205: 0 | W205: 0 | X205: 0 | Y205: 0 | Z205: 0 | AA205: 0 | AB205: 0 | AC205: 0 | AD205: 0 | AE205: 0 | AF205: 0 | AG205: 0 | AH205: 0 | AI205: 0 | AJ205: 0 | AK205: 0 | AL205: 0 | AM205: 0 | AN205: 0 | AO205: 0 | AP205: 0 | AQ205: 0 | AR205: 0 | AS205: 0 | AT205: 0 | AU205: 0 | AV205: 0 | AW205: 0 | AX205: 0 | AY205: 0 | AZ205: 0 | BA205: 0 | BB205: 0 | BC205: 0 | BD205: 0 | BE205: 0 | BF205: 0 | BG205: 0 | BH205: 0 | BI205: 0 | BJ205: 0
D206: 5.2151251e+08 | E206: 80241864 | F206: 2011 Mississippi Flood | G206: 11 | H206: 8 | I206: 0 | J206: 0 | K206: 0 | L206: 0 | M206: 0 | N206: 0 | O206: 0 | P206: 0 | Q206: 0 | R206: 0 | S206: 0 | T206: 0 | U206: 0 | V206: 0 | W206: 0 | X206: 0 | Y206: 0 | Z206: 0 | AA206: 0 | AB206: 0 | AC206: 0 | AD206: 0 | AE206: 0 | AF206: 0 | AG206: 0 | AH206: 0 | AI206: 0 | AJ206: 0 | AK206: 0 | AL206: 0 | AM206: 0 | AN206: 0 | AO206: 0 | AP206: 0 | AQ206: 0 | AR206: 0 | AS206: 0 | AT206: 0 | AU206: 0 | AV206: 0 | AW206: 0 | AX206: 0 | AY206: 0 | AZ206: 0 | BA206: 0 | BB206: 0 | BC206: 0 | BD206: 0 | BE206: 0 | BF206: 0 | BG206: 0 | BH206: 0 | BI206: 0 | BJ206: 0
D207: 1.3904768e+09 | E207: 80310399 | F207: 1995 Gulf Coast Flood | G207: 2 | H207: 8 | I207: 0 | J207: 0 | K207: 0 | L207: 0 | M207: 0 | N207: 0 | O207: 0 | P207: 0 | Q207: 0 | R207: 0 | S207: 0 | T207: 0 | U207: 0 | V207: 0 | W207: 0 | X207: 0 | Y207: 0 | Z207: 0 | AA207: 0 | AB207: 0 | AC207: 0 | AD207: 0 | AE207: 0 | AF207: 0 | AG207: 0 | AH207: 0 | AI207: 0 | AJ207: 0 | AK207: 0 | AL207: 0 | AM207: 0 | AN207: 0 | AO207: 0 | AP207: 0 | AQ207: 0 | AR207: 0 | AS207: 0 | AT207: 0 | AU207: 0 | AV207: 0 | AW207: 0 | AX207: 0 | AY207: 0 | AZ207: 0 | BA207: 0 | BB207: 0 | BC207: 0 | BD207: 0 | BE207: 0 | BF207: 0 | BG207: 0 | BH207: 0 | BI207: 0 | BJ207: 0
D208: 7163929.8 | E208: 110005362 | F208: 1980 Humboldt County CA | G208: 55 | H208: 11 | I208: 0 | J208: 0 | K208: 0 | L208: 0 | M208: 0 | N208: 0 | O208: 0 | P208: 0 | Q208: 0 | R208: 0 | S208: 0 | T208: 0 | U208: 0 | V208: 0 | W208: 0 | X208: 0 | Y208: 0 | Z208: 0 | AA208: 0 | AB208: 0 | AC208: 0 | AD208: 0 | AE208: 0 | AF208: 0 | AG208: 0 | AH208: 0 | AI208: 0 | AJ208: 0 | AK208: 0 | AL208: 0 | AM208: 0 | AN208: 0 | AO208: 0 | AP208: 0 | AQ208: 0 | AR208: 0 | AS208: 0 | AT208: 0 | AU208: 0 | AV208: 0 | AW208: 0 | AX208: 0 | AY208: 0 | AZ208: 0 | BA208: 0 | BB208: 0 | BC208: 0 | BD208: 0 | BE208: 0 | BF208: 0 | BG208: 0 | BH208: 0 | BI208: 0 | BJ208: 0
D209: 3.570069e+08 | E209: 110009851 | F209: 1873 Oregon Coast-Scenario 2 | G209: 17 | H209: 11 | I209: 0 | J209: 0 | K209: 0 | L209: 0 | M209: 0 | N209: 0 | O209: 0 | P209: 0 | Q209: 0 | R209: 0 | S209: 0 | T209: 0 | U209: 0 | V209: 0 | W209: 0 | X209: 0 | Y209: 0 | Z209: 0 | AA209: 0 | AB209: 0 | AC209: 0 | AD209: 0 | AE209: 0 | AF209: 0 | AG209: 0 | AH209: 0 | AI209: 0 | AJ209: 0 | AK209: 0 | AL209: 0 | AM209: 0 | AN209: 0 | AO209: 0 | AP209: 0 | AQ209: 0 | AR209: 0 | AS209: 0 | AT209: 0 | AU209: 0 | AV209: 0 | AW209: 0 | AX209: 0 | AY209: 0 | AZ209: 0 | BA209: 0 | BB209: 0 | BC209: 0 | BD209: 0 | BE209: 0 | BF209: 0 | BG209: 0 | BH209: 0 | BI209: 0 | BJ209: 0
D210: 3.2844716e+08 | E210: 110009851 | F210: 1873 Oregon Coast-Scenario 2 | G210: 17 | H210: 11 | I210: 0 | J210: 0 | K210: 0 | L210: 0 | M210: 0 | N210: 0 | O210: 0 | P210: 0 | Q210: 0 | R210: 0 | S210: 0 | T210: 0 | U210: 0 | V210: 0 | W210: 0 | X210: 0 | Y210: 0 | Z210: 0 | AA210: 0 | AB210: 0 | AC210: 0 | AD210: 0 | AE210: 0 | AF210: 0 | AG210: 0 | AH210: 0 | AI210: 0 | AJ210: 0 | AK210: 0 | AL210: 0 | AM210: 0 | AN210: 0 | AO210: 0 | AP210: 0 | AQ210: 0 | AR210: 0 | AS210: 0 | AT210: 0 | AU210: 0 | AV210: 0 | AW210: 0 | AX210: 0 | AY210: 0 | AZ210: 0 | BA210: 0 | BB210: 0 | BC210: 0 | BD210: 0 | BE210: 0 | BF210: 0 | BG210: 0 | BH210: 0 | BI210: 0 | BJ210: 0
D211: 284539.09 | E211: 110023012 | F211: 2011 Vancouver Island BC | G211: 78 | H211: 11 | I211: 0 | J211: 0 | K211: 0 | L211: 0 | M211: 0 | N211: 0 | O211: 0 | P211: 0 | Q211: 0 | R211: 0 | S211: 0 | T211: 0 | U211: 0 | V211: 0 | W211: 0 | X211: 0 | Y211: 0 | Z211: 0 | AA211: 0 | AB211: 0 | AC211: 0 | AD211: 0 | AE211: 0 | AF211: 0 | AG211: 0 | AH211: 0 | AI211: 0 | AJ211: 0 | AK211: 0 | AL211: 0 | AM211: 0 | AN211: 0 | AO211: 0 | AP211: 0 | AQ211: 0 | AR211: 0 | AS211: 0 | AT211: 0 | AU211: 0 | AV211: 0 | AW211: 0 | AX211: 0 | AY211: 0 | AZ211: 0 | BA211: 0 | BB211: 0 | BC211: 0 | BD211: 0 | BE211: 0 | BF211: 0 | BG211: 0 | BH211: 0 | BI211: 0 | BJ211: 0
... D222: 2.9064566e+08 | E222: 180044467 | F222: 2004 Nigata Flood | G222: 2 | H222: 18 | I222: 0 | J222: 0 | K222: 0 | L222: 0 | M222: 0 | N222: 0 | O222: 0 | P222: 0 | Q222: 0 | R222: 0 | S222: 0 | T222: 0 | U222: 0 | V222: 0 | W222: 0 | X222: 0 | Y222: 0 | Z222: 0 | AA222: 0 | AB222: 0 | AC222: 0 | AD222: 0 | AE222: 0 | AF222: 0 | AG222: 0 | AH222: 0 | AI222: 0 | AJ222: 0 | AK222: 0 | AL222: 0 | AM222: 0 | AN222: 0 | AO222: 0 | AP222: 0 | AQ222: 0 | AR222: 0 | AS222: 0 | AT222: 0 | AU222: 0 | AV222: 0 | AW222: 0 | AX222: 0 | AY222: 0 | AZ222: 0 | BA222: 0 | BB222: 0 | BC222: 0 | BD222: 0 | BE222: 0 | BF222: 0 | BG222: 0 | BH222: 0 | BI222: 0 | BJ222: 0
E223: 220935132 | F223: ArizonaHail_PCS31_1 | G223: 16 | H223: 22 | I223: 0 | J223: 0 | K223: 0 | L223: 0 | M223: 0 | N223: 0 | O223: 0 | P223: 0 | Q223: 0 | R223: 0 | S223: 0 | T223: 0 | U223: 0 | V223: 0 | W223: 0 | X223: 0 | Y223: 0 | Z223: 0 | AA223: 0 | AB223: 0 | AC223: 0 | AD223: 0 | AE223: 0 | AF223: 0 | AG223: 0 | AH223: 0 | AI223: 0 | AJ223: 0 | AK223: 0 | AL223: 0 | AM223: 0 | AN223: 0 | AO223: 0 | AP223: 0 | AQ223: 0 | AR223: 0 | AS223: 0 | AT223: 0 | AU223: 0 | AV223: 0 | AW223: 0 | AX223: 0 | AY223: 0 | AZ223: 0 | BA223: 0 | BB223: 0 | BC223: 0 | BD223: 0 | BE223: 0 | BF223: 0 | BG223: 0 | BH223: 0 | BI223: 0 | BJ223: 0
D224: 1.676036e+10 | E224: 270015205 | F224: 2018 Michael | G224: 58 | H224: 27 | I224: 0 | J224: 0 | K224: 0 | L224: 0 | M224: 0 | N224: 0 | O224: 0 | P224: 0 | Q224: 0 | R224: 0 | S224: 0 | T224: 0 | U224: 0 | V224: 0 | W224: 0 | X224: 0 | Y224: 0 | Z224: 0 | AA224: 250000.1 | AB224: 0 | AC224: 0 | AD224: 0 | AE224: 0 | AF224: 0 | AG224: 0 | AH224: 0 | AI224: 0 | AJ224: 1668804.2 | AK224: 250000.5 | AL224: 0 | AM224: 0 | AN224: 0 | AO224: 0 | AP224: 0 | AQ224: 0 | AR224: 0 | AS224: 212248.63 | AT224: 0 | AU224: 0 | AV224: 0 | AW224: 250000 | AX224: 0 | AY224: 0 | AZ224: 0 | BA224: 0 | BB224: 0 | BC224: 0 | BD224: 0 | BE224: 0 | BF224: 0 | BG224: 0 | BH224: 0 | BI224: 0 | BJ224: 0
D225: 1.927074e+10 | E225: 270043453 | F225: 1919 Event 2 Texas | G225: 6 | H225: 27 | I225: 0 | J225: 0 | K225: 0 | L225: 0 | M225: 0 | N225: 0 | O225: 0 | P225: 0 | Q225: 0 | R225: 0 | S225: 0 | T225: 0 | U225: 0 | V225: 0 | W225: 0 | X225: 0 | Y225: 0 | Z225: 0 | AA225: 0 | AB225: 0 | AC225: 0 | AD225: 0 | AE225: 0 | AF225: 0 | AG225: 0 | AH225: 0 | AI225: 0 | AJ225: 0 | AK225: 0 | AL225: 0 | AM225: 0 | AN225: 0 | AO225: 0 | AP225: 0 | AQ225: 0 | AR225: 0 | AS225: 0 | AT225: 0 | AU225: 0 | AV225: 0 | AW225: 0 | AX225: 0 | AY225: 0 | AZ225: 0 | BA225: 0 | BB225: 0 | BC225: 0 | BD225: 0 | BE225: 0 | BF225: 0 | BG225: 0 | BH225: 0 | BI225: 0 | BJ225: 0
D226: 2.6316677e+10 | E226: 270089264 | F226: 2017 Harvey | G226: 57 | H226: 27 | I226: 0 | J226: 0 | K226: 0 | L226: 0 | M226: 0 | N226: 0 | O226: 0 | P226: 0 | Q226: 13015.845 | R226: 0 | S226: 0 | T226: 0 | U226: 0 | V226: 13015.845 | W226: 0 | X226: 0 | Y226: 0 | Z226: 0 | AA226: 0 | AB226: 0 | AC226: 0 | AD226: 0 | AE226: 0 | AF226: 0 | AG226: 0 | AH226: 0 | AI226: 0 | AJ226: 0 | AK226: 0 | AL226: 0 | AM226: 0 | AN226: 0 | AO226: 0 | AP226: 0 | AQ226: 0 | AR226: 0 | AS226: 0 | AT226: 0 | AU226: 0 | AV226: 0 | AW226: 0 | AX226: 0 | AY226: 0 | AZ226: 0 | BA226: 0 | BB226: 0 | BC226: 0 | BD226: 0 | BE226: 0 | BF226: 0 | BG226: 0 | BH226: 0 | BI226: 0 | BJ226: 0
D227: 1.4976381e+09 | E227: 270089345 | F227: 1926 Event 10 Florida | G227: 8 | H227: 27 | I227: 0 | J227: 0 | K227: 0 | L227: 0 | M227: 0 | N227: 0 | O227: 0 | P227: 0 | Q227: 0 | R227: 0 | S227: 0 | T227: 0 | U227: 0 | V227: 0 | W227: 0 | X227: 0 | Y227: 0 | Z227: 0 | AA227: 0 | AB227: 0 | AC227: 0 | AD227: 0 | AE227: 0 | AF227: 0 | AG227: 0 | AH227: 0 | AI227: 0 | AJ227: 0 | AK227: 0 | AL227: 0 | AM227: 0 | AN227: 0 | AO227: 0 | AP227: 0 | AQ227: 0 | AR227: 0 | AS227: 0 | AT227: 0 | AU227: 0 | AV227: 0 | AW227: 0 | AX227: 0 | AY227: 0 | AZ227: 0 | BA227: 0 | BB227: 0 | BC227: 0 | BD227: 0 | BE227: 0 | BF227: 0 | BG227: 0 | BH227: 0 | BI227: 0 | BJ227: 0
D228: 1.5281851e+10 | E228: 270112220 | F228: 2004 Frances | G228: 49 | H228: 27 | I228: 0 | J228: 0 | K228: 0 | L228: 0 | M228: 0 | N228: 0 | O228: 0 | P228: 0 | Q228: 0 | R228: 0 | S228: 0 | T228: 0 | U228: 0 | V228: 0 | W228: 0 | X228: 0 | Y228: 0 | Z228: 0 | AA228: 0 | AB228: 0 | AC228: 0 | AD228: 0 | AE228: 0 | AF228: 0 | AG228: 0 | AH228: 0 | AI228: 0 | AJ228: 0 | AK228: 0 | AL228: 0 | AM228: 0 | AN228: 0 | AO228: 0 | AP228: 0 | AQ228: 0 | AR228: 0 | AS228: 0 | AT228: 0 | AU228: 0 | AV228: 0 | AW228: 0 | AX228: 0 | AY228: 0 | AZ228: 0 | BA228: 0 | BB228: 0 | BC228: 0 | BD228: 0 | BE228: 0 | BF228: 0 | BG228: 0 | BH228: 0 | BI228: 0 | BJ228: 0
D229: 7.2388632e+08 | E229: 270119073 | F229: 2005 Cindy | G229: 50 | H229: 27 | I229: 0 | J229: 0 | K229: 0 | L229: 0 | M229: 0 | N229: 0 | O229: 0 | P229: 0 | Q229: 0 | R229: 0 | S229: 0 | T229: 0 | U229: 0 | V229: 0 | W229: 0 | X229: 0 | Y229: 0 | Z229: 0 | AA229: 0 | AB229: 0 | AC229: 0 | AD229: 0 | AE229: 0 | AF229: 0 | AG229: 0 | AH229: 0 | AI229: 0 | AJ229: 250000 | AK229: 0 | AL229: 0 | AM229: 0 | AN229: 0 | AO229: 0 | AP229: 0 | AQ229: 0 | AR229: 0 | AS229: 0 | AT229: 0 | AU229: 0 | AV229: 0 | AW229: 0 | AX229: 0 | AY229: 0 | AZ229: 0 | BA229: 0 | BB229: 0 | BC229: 0 | BD229: 0 | BE229: 0 | BF229: 0 | BG229: 0 | BH229: 0 | BI229: 0 | BJ229: 0
D230: 8.1105375e+08 | E230: 270155308 | F230: 1996 Hortense | G230: 41 | H230: 27 | I230: 0 | J230: 0 | K230: 0 | L230: 0 | M230: 0 | N230: 0 | O230: 0 | P230: 0 | Q230: 0 | R230: 0 | S230: 0 | T230: 0 | U230: 0 | V230: 0 | W230: 0 | X230: 0 | Y230: 0 | Z230: 0 | AA230: 0 | AB230: 0 | AC230: 0 | AD230: 0 | AE230: 0 | AF230: 0 | AG230: 0 | AH230: 0 | AI230: 0 | AJ230: 0 | AK230: 0 | AL230: 0 | AM230: 0 | AN230: 0 | AO230: 0 | AP230: 0 | AQ230: 0 | AR230: 0 | AS230: 0 | AT230: 0 | AU230: 0 | AV230: 0 | AW230: 0 | AX230: 0 | AY230: 0 | AZ230: 0 | BA230: 0 | BB230: 0 | BC230: 0 | BD230: 0 | BE230: 0 | BF230: 0 | BG230: 0 | BH230: 0 | BI230: 0 | BJ230: 0
...

Sheet CorrMxData
A1: ILSName | B1: ILSName2 | C1: Aggtype | D1: Year | E1: AggLoss
A2: CB-Baldwin Re Ltd. Series 2023-1 Class A Reset 2025 | C2: AEPCOTVAR | D2: 100 | E2: 749999.99
A3: CB-Baldwin Re Ltd. Series 2023-1 Class A Reset 2025 | B3: CB-Baldwin Re Ltd. Series 2023-1 Class A Reset 2025 | C3: AEPCOTVAR | D3: 100 | E3: 1500000
A4: CB-Baldwin Re Ltd. Series 2023-1 Class A Reset 2025 | B4: CB-Baldwin Re Ltd. Series 2023-1 Class A Reset 2025 | C4: AEPCOTVAR | D4: 100 | E4: 1500000
A5: CB-Baldwin Re Ltd. Series 2023-1 Class A Reset 2025 | B5: CB-Gateway Re Ltd. Series 2025-1 Class A | C5: AEPCOTVAR | D5: 100 | E5: 795818.1
A6: CB-Baldwin Re Ltd. Series 2023-1 Class A Reset 2025 | B6: CB-3264 Re Ltd. Series 2024-1 Class B Reset 2025 | C6: AEPCOTVAR | D6: 100 | E6: 764076.34
A7: CB-Baldwin Re Ltd. Series 2023-1 Class A Reset 2025 | B7: CB-Citrus Re Ltd. Series 2023-1 Class B Reset 2025 | C7: AEPCOTVAR | D7: 100 | E7: 894856.25
A8: CB-Baldwin Re Ltd. Series 2023-1 Class A Reset 2025 | B8: CB-Blue Ridge Re Ltd. Series 2023-1 Class A Reset 2025 | C8: AEPCOTVAR | D8: 100 | E8: 763579.4
A9: CB-Baldwin Re Ltd. Series 2023-1 Class A Reset 2025 | B9: CB-Bayou Re Ltd. Series 2023-1 Class A Reset 2025 | C9: AEPCOTVAR | D9: 100 | E9: 778777.34
A10: CB-Baldwin Re Ltd. Series 2023-1 Class A Reset 2025 | B10: CB-Bayou Re Ltd. Series 2023-1 Class A Reset 2025 | C10: AEPCOTVAR | D10: 100 | E10: 778777.34
A11: CB-Baldwin Re Ltd. Series 2023-1 Class A Reset 2025 | B11: CB-Bayou Re Ltd. Series 2023-1 Class B Reset 2025 | C11: AEPCOTVAR | D11: 100 | E11: 769555.77
A12: CB-Baldwin Re Ltd. Series 2023-1 Class A Reset 2025 | B12: CB-Purple Re Ltd. Series 2024-1 Class A Reset 2025 | C12: AEPCOTVAR | D12: 100 | E12: 755000.01
A13: CB-Baldwin Re Ltd. Series 2023-1 Class A Reset 2025 | B13: CB-Purple Re Ltd. Series 2023-2 Class A Reset 2025 | C13: AEPCOTVAR | D13: 100 | E13: 754999.99
A14: CB-Baldwin Re Ltd. Series 2023-1 Class A Reset 2025 | B14: CB-Bayou Re Ltd. Series 2024-1 Class A Reset 2025 | C14: AEPCOTVAR | D14: 100 | E14: 757499.99
... A21: CB-Baldwin Re Ltd. Series 2023-1 Class A Reset 2025 | B21: CB-Montoya Re Ltd. Series 2025-1 Class B Reset 2025 | C21: AEPCOTVAR | D21: 100 | E21: 792821.49
A22: CB-Baldwin Re Ltd. Series 2023-1 Class A Reset 2025 | C22: AEPCOTVAR | D22: 100 | E22: 749999.99
A23: CB-Baldwin Re Ltd. Series 2023-1 Class A Reset 2025 | B23: CB-Baldwin Re Ltd. Series 2023-1 Class A Reset 2025 | C23: AEPCOTVAR | D23: 100 | E23: 1500000
A24: CB-Baldwin Re Ltd. Series 2023-1 Class A Reset 2025 | B24: CB-Baldwin Re Ltd. Series 2023-1 Class A Reset 2025 | C24: AEPCOTVAR | D24: 100 | E24: 1500000
A25: CB-Baldwin Re Ltd. Series 2023-1 Class A Reset 2025 | B25: CB-Gateway Re Ltd. Series 2025-1 Class A | C25: AEPCOTVAR | D25: 100 | E25: 795818.1
A26: CB-Baldwin Re Ltd. Series 2023-1 Class A Reset 2025 | B26: CB-3264 Re Ltd. Series 2024-1 Class B Reset 2025 | C26: AEPCOTVAR | D26: 100 | E26: 764076.34
A27: CB-Baldwin Re Ltd. Series 2023-1 Class A Reset 2025 | B27: CB-Citrus Re Ltd. Series 2023-1 Class B Reset 2025 | C27: AEPCOTVAR | D27: 100 | E27: 894856.25
A28: CB-Baldwin Re Ltd. Series 2023-1 Class A Reset 2025 | B28: CB-Blue Ridge Re Ltd. Series 2023-1 Class A Reset 2025 | C28: AEPCOTVAR | D28: 100 | E28: 763579.4
A29: CB-Baldwin Re Ltd. Series 2023-1 Class A Reset 2025 | B29: CB-Bayou Re Ltd. Series 2023-1 Class A Reset 2025 | C29: AEPCOTVAR | D29: 100 | E29: 778777.34
A30: CB-Baldwin Re Ltd. Series 2023-1 Class A Reset 2025 | B30: CB-Bayou Re Ltd. Series 2023-1 Class A Reset 2025 | C30: AEPCOTVAR | D30: 100 | E30: 778777.34
A31: CB-Baldwin Re Ltd. Series 2023-1 Class A Reset 2025 | B31: CB-Bayou Re Ltd. Series 2023-1 Class B Reset 2025 | C31: AEPCOTVAR | D31: 100 | E31: 769555.77
A32: CB-Baldwin Re Ltd. Series 2023-1 Class A Reset 2025 | B32: CB-Purple Re Ltd. Series 2024-1 Class A Reset 2025 | C32: AEPCOTVAR | D32: 100 | E32: 755000.01
A33: CB-Baldwin Re Ltd. Series 2023-1 Class A Reset 2025 | B33: CB-Purple Re Ltd. Series 2023-2 Class A Reset 2025 | C33: AEPCOTVAR | D33: 100 | E33: 754999.99
A34: CB-Baldwin Re Ltd. Series 2023-1 Class A Reset 2025 | B34: CB-Bayou Re Ltd. Series 2024-1 Class A Reset 2025 | C34: AEPCOTVAR | D34: 100 | E34: 757499.99
... A41: CB-Baldwin Re Ltd. Series 2023-1 Class A Reset 2025 | B41: CB-Montoya Re Ltd. Series 2025-1 Class B Reset 2025 | C41: AEPCOTVAR | D41: 100 | E41: 792821.49
A42: CB-Gateway Re Ltd. Series 2025-1 Class A | C42: AEPCOTVAR | D42: 100 | E42: 250000
A43: CB-Gateway Re Ltd. Series 2025-1 Class A | B43: CB-Baldwin Re Ltd. Series 2023-1 Class A Reset 2025 | C43: AEPCOTVAR | D43: 100 | E43: 287500
A44: CB-Gateway Re Ltd. Series 2025-1 Class A | B44: CB-Baldwin Re Ltd. Series 2023-1 Class A Reset 2025 | C44: AEPCOTVAR | D44: 100 | E44: 287500
A45: CB-Gateway Re Ltd. Series 2025-1 Class A | B45: CB-Gateway Re Ltd. Series 2025-1 Class A | C45: AEPCOTVAR | D45: 100 | E45: 500000
A46: CB-Gateway Re Ltd. Series 2025-1 Class A | B46: CB-3264 Re Ltd. Series 2024-1 Class B Reset 2025 | C46: AEPCOTVAR | D46: 100 | E46: 455000.16
A47: CB-Gateway Re Ltd. Series 2025-1 Class A | B47: CB-Citrus Re Ltd. Series 2023-1 Class B Reset 2025 | C47: AEPCOTVAR | D47: 100 | E47: 262024.16
A48: CB-Gateway Re Ltd. Series 2025-1 Class A | B48: CB-Blue Ridge Re Ltd. Series 2023-1 Class A Reset 2025 | C48: AEPCOTVAR | D48: 100 | E48: 266545.06
A49: CB-Gateway Re Ltd. Series 2025-1 Class A | B49: CB-Bayou Re Ltd. Series 2023-1 Class A Reset 2025 | C49: AEPCOTVAR | D49: 100 | E49: 474120.94
A50: CB-Gateway Re Ltd. Series 2025-1 Class A | B50: CB-Bayou Re Ltd. Series 2023-1 Class A Reset 2025 | C50: AEPCOTVAR | D50: 100 | E50: 474120.94
A51: CB-Gateway Re Ltd. Series 2025-1 Class A | B51: CB-Bayou Re Ltd. Series 2023-1 Class B Reset 2025 | C51: AEPCOTVAR | D51: 100 | E51: 374436.37
A52: CB-Gateway Re Ltd. Series 2025-1 Class A | B52: CB-Purple Re Ltd. Series 2024-1 Class A Reset 2025 | C52: AEPCOTVAR | D52: 100 | E52: 269622.12
A53: CB-Gateway Re Ltd. Series 2025-1 Class A | B53: CB-Purple Re Ltd. Series 2023-2 Class A Reset 2025 | C53: AEPCOTVAR | D53: 100 | E53: 275000
A54: CB-Gateway Re Ltd. Series 2025-1 Class A | B54: CB-Bayou Re Ltd. Series 2024-1 Class A Reset 2025 | C54: AEPCOTVAR | D54: 100 | E54: 341503.39
... A61: CB-Gateway Re Ltd. Series 2025-1 Class A | B61: CB-Montoya Re Ltd. Series 2025-1 Class B Reset 2025 | C61: AEPCOTVAR | D61: 100 | E61: 322582.58
A62: CB-3264 Re Ltd. Series 2024-1 Class B Reset 2025 | C62: AEPCOTVAR | D62: 100 | E62: 250000.2
A63: CB-3264 Re Ltd. Series 2024-1 Class B Reset 2025 | B63: CB-Baldwin Re Ltd. Series 2023-1 Class A Reset 2025 | C63: AEPCOTVAR | D63: 100 | E63: 263709.97
A64: CB-3264 Re Ltd. Series 2024-1 Class B Reset 2025 | B64: CB-Baldwin Re Ltd. Series 2023-1 Class A Reset 2025 | C64: AEPCOTVAR | D64: 100 | E64: 263709.97
A65: CB-3264 Re Ltd. Series 2024-1 Class B Reset 2025 | B65: CB-Gateway Re Ltd. Series 2025-1 Class A | C65: AEPCOTVAR | D65: 100 | E65: 389013.43
A66: CB-3264 Re Ltd. Series 2024-1 Class B Reset 2025 | B66: CB-3264 Re Ltd. Series 2024-1 Class B Reset 2025 | C66: AEPCOTVAR | D66: 100 | E66: 500000.4
A67: CB-3264 Re Ltd. Series 2024-1 Class B Reset 2025 | B67: CB-Citrus Re Ltd. Series 2023-1 Class B Reset 2025 | C67: AEPCOTVAR | D67: 100 | E67: 254756.12
A68: CB-3264 Re Ltd. Series 2024-1 Class B Reset 2025 | B68: CB-Blue Ridge Re Ltd. Series 2023-1 Class A Reset 2025 | C68: AEPCOTVAR | D68: 100 | E68: 253125.76
A69: CB-3264 Re Ltd. Series 2024-1 Class B Reset 2025 | B69: CB-Bayou Re Ltd. Series 2023-1 Class A Reset 2025 | C69: AEPCOTVAR | D69: 100 | E69: 434884.36
A70: CB-3264 Re Ltd. Series 2024-1 Class B Reset 2025 | B70: CB-Bayou Re Ltd. Series 2023-1 Class A Reset 2025 | C70: AEPCOTVAR | D70: 100 | E70: 434884.36
A71: CB-3264 Re Ltd. Series 2024-1 Class B Reset 2025 | B71: CB-Bayou Re Ltd. Series 2023-1 Class B Reset 2025 | C71: AEPCOTVAR | D71: 100 | E71: 351111.92
A72: CB-3264 Re Ltd. Series 2024-1 Class B Reset 2025 | B72: CB-Purple Re Ltd. Series 2024-1 Class A Reset 2025 | C72: AEPCOTVAR | D72: 100 | E72: 256663.68
A73: CB-3264 Re Ltd. Series 2024-1 Class B Reset 2025 | B73: CB-Purple Re Ltd. Series 2023-2 Class A Reset 2025 | C73: AEPCOTVAR | D73: 100 | E73: 260000.2
A74: CB-3264 Re Ltd. Series 2024-1 Class B Reset 2025 | B74: CB-Bayou Re Ltd. Series 2024-1 Class A Reset 2025 | C74: AEPCOTVAR | D74: 100 | E74: 323639.45
... A81: CB-3264 Re Ltd. Series 2024-1 Class B Reset 2025 | B81: CB-Montoya Re Ltd. Series 2025-1 Class B Reset 2025 | C81: AEPCOTVAR | D81: 100 | E81: 303471.69
A82: CB-Citrus Re Ltd. Series 2023-1 Class B Reset 2025 | C82: AEPCOTVAR | D82: 100 | E82: 249999.65
A83: CB-Citrus Re Ltd. Series 2023-1 Class B Reset 2025 | B83: CB-Baldwin Re Ltd. Series 2023-1 Class A Reset 2025 | C83: AEPCOTVAR | D83: 100 | E83: 489330.76
A84: CB-Citrus Re Ltd. Series 2023-1 Class B Reset 2025 | B84: CB-Baldwin Re Ltd. Series 2023-1 Class A Reset 2025 | C84: AEPCOTVAR | D84: 100 | E84: 489330.76
A85: CB-Citrus Re Ltd. Series 2023-1 Class B Reset 2025 | B85: CB-Gateway Re Ltd. Series 2025-1 Class A | C85: AEPCOTVAR | D85: 100 | E85: 271533.92
A86: CB-Citrus Re Ltd. Series 2023-1 Class B Reset 2025 | B86: CB-3264 Re Ltd. Series 2024-1 Class B Reset 2025 | C86: AEPCOTVAR | D86: 100 | E86: 262205.07
A87: CB-Citrus Re Ltd. Series 2023-1 Class B Reset 2025 | B87: CB-Citrus Re Ltd. Series 2023-1 Class B Reset 2025 | C87: AEPCOTVAR | D87: 100 | E87: 499999.3
A88: CB-Citrus Re Ltd. Series 2023-1 Class B Reset 2025 | B88: CB-Blue Ridge Re Ltd. Series 2023-1 Class A Reset 2025 | C88: AEPCOTVAR | D88: 100 | E88: 262449.26
A89: CB-Citrus Re Ltd. Series 2023-1 Class B Reset 2025 | B89: CB-Bayou Re Ltd. Series 2023-1 Class A Reset 2025 | C89: AEPCOTVAR | D89: 100 | E89: 269999.62
A90: CB-Citrus Re Ltd. Series 2023-1 Class B Reset 2025 | B90: CB-Bayou Re Ltd. Series 2023-1 Class A Reset 2025 | C90: AEPCOTVAR | D90: 100 | E90: 269999.62
A91: CB-Citrus Re Ltd. Series 2023-1 Class B Reset 2025 | B91: CB-Bayou Re Ltd. Series 2023-1 Class B Reset 2025 | C91: AEPCOTVAR | D91: 100 | E91: 265392.42
A92: CB-Citrus Re Ltd. Series 2023-1 Class B Reset 2025 | B92: CB-Purple Re Ltd. Series 2024-1 Class A Reset 2025 | C92: AEPCOTVAR | D92: 100 | E92: 261295.87
A93: CB-Citrus Re Ltd. Series 2023-1 Class B Reset 2025 | B93: CB-Purple Re Ltd. Series 2023-2 Class A Reset 2025 | C93: AEPCOTVAR | D93: 100 | E93: 262499.65
A94: CB-Citrus Re Ltd. Series 2023-1 Class B Reset 2025 | B94: CB-Bayou Re Ltd. Series 2024-1 Class A Reset 2025 | C94: AEPCOTVAR | D94: 100 | E94: 257321.37
... A101: CB-Citrus Re Ltd. Series 2023-1 Class B Reset 2025 | B101: CB-Montoya Re Ltd. Series 2025-1 Class B Reset 2025 | C101: AEPCOTVAR | D101: 100 | E101: 289999.63
A102: CB-Blue Ridge Re Ltd. Series 2023-1 Class A Reset 2025 | C102: AEPCOTVAR | D102: 100 | E102: 250000
A103: CB-Blue Ridge Re Ltd. Series 2023-1 Class A Reset 2025 | B103: CB-Baldwin Re Ltd. Series 2023-1 Class A Reset 2025 | C103: AEPCOTVAR | D103: 100 | E103: 280603.44
A104: CB-Blue Ridge Re Ltd. Series 2023-1 Class A Reset 2025 | B104: CB-Baldwin Re Ltd. Series 2023-1 Class A Reset 2025 | C104: AEPCOTVAR | D104: 100 | E104: 280603.44
A105: CB-Blue Ridge Re Ltd. Series 2023-1 Class A Reset 2025 | B105: CB-Gateway Re Ltd. Series 2025-1 Class A | C105: AEPCOTVAR | D105: 100 | E105: 296862.54
A106: CB-Blue Ridge Re Ltd. Series 2023-1 Class A Reset 2025 | B106: CB-3264 Re Ltd. Series 2024-1 Class B Reset 2025 | C106: AEPCOTVAR | D106: 100 | E106: 261125.51
A107: CB-Blue Ridge Re Ltd. Series 2023-1 Class A Reset 2025 | B107: CB-Citrus Re Ltd. Series 2023-1 Class B Reset 2025 | C107: AEPCOTVAR | D107: 100 | E107: 264755.9
A108: CB-Blue Ridge Re Ltd. Series 2023-1 Class A Reset 2025 | B108: CB-Blue Ridge Re Ltd. Series 2023-1 Class A Reset 2025 | C108: AEPCOTVAR | D108: 100 | E108: 499999.99
A109: CB-Blue Ridge Re Ltd. Series 2023-1 Class A Reset 2025 | B109: CB-Bayou Re Ltd. Series 2023-1 Class A Reset 2025 | C109: AEPCOTVAR | D109: 100 | E109: 266846.66
A110: CB-Blue Ridge Re Ltd. Series 2023-1 Class A Reset 2025 | B110: CB-Bayou Re Ltd. Series 2023-1 Class A Reset 2025 | C110: AEPCOTVAR | D110: 100 | E110: 266846.66
A111: CB-Blue Ridge Re Ltd. Series 2023-1 Class A Reset 2025 | B111: CB-Bayou Re Ltd. Series 2023-1 Class B Reset 2025 | C111: AEPCOTVAR | D111: 100 | E111: 260677.28
A112: CB-Blue Ridge Re Ltd. Series 2023-1 Class A Reset 2025 | B112: CB-Purple Re Ltd. Series 2024-1 Class A Reset 2025 | C112: AEPCOTVAR | D112: 100 | E112: 267724.5
A113: CB-Blue Ridge Re Ltd. Series 2023-1 Class A Reset 2025 | B113: CB-Purple Re Ltd. Series 2023-2 Class A Reset 2025 | C113: AEPCOTVAR | D113: 100 | E113: 270000
A114: CB-Blue Ridge Re Ltd. Series 2023-1 Class A Reset 2025 | B114: CB-Bayou Re Ltd. Series 2024-1 Class A Reset 2025 | C114: AEPCOTVAR | D114: 100 | E114: 257500
... A121: CB-Blue Ridge Re Ltd. Series 2023-1 Class A Reset 2025 | B121: CB-Montoya Re Ltd. Series 2025-1 Class B Reset 2025 | C121: AEPCOTVAR | D121: 100 | E121: 298126.29
A122: CB-Bayou Re Ltd. Series 2023-1 Class A Reset 2025 | C122: AEPCOTVAR | D122: 100 | E122: 499999.2
A123: CB-Bayou Re Ltd. Series 2023-1 Class A Reset 2025 | B123: CB-Baldwin Re Ltd. Series 2023-1 Class A Reset 2025 | C123: AEPCOTVAR | D123: 100 | E123: 529999.2
A124: CB-Bayou Re Ltd. Series 2023-1 Class A Reset 2025 | B124: CB-Baldwin Re Ltd. Series 2023-1 Class A Reset 2025 | C124: AEPCOTVAR | D124: 100 | E124: 529999.2
A125: CB-Bayou Re Ltd. Series 2023-1 Class A Reset 2025 | B125: CB-Gateway Re Ltd. Series 2025-1 Class A | C125: AEPCOTVAR | D125: 100 | E125: 657084.92
A126: CB-Bayou Re Ltd. Series 2023-1 Class A Reset 2025 | B126: CB-3264 Re Ltd. Series 2024-1 Class B Reset 2025 | C126: AEPCOTVAR | D126: 100 | E126: 688730.76
A127: CB-Bayou Re Ltd. Series 2023-1 Class A Reset 2025 | B127: CB-Citrus Re Ltd. Series 2023-1 Class B Reset 2025 | C127: AEPCOTVAR | D127: 100 | E127: 512499.18
A128: CB-Bayou Re Ltd. Series 2023-1 Class A Reset 2025 | B128: CB-Blue Ridge Re Ltd. Series 2023-1 Class A Reset 2025 | C128: AEPCOTVAR | D128: 100 | E128: 504709.54
A129: CB-Bayou Re Ltd. Series 2023-1 Class A Reset 2025 | B129: CB-Bayou Re Ltd. Series 2023-1 Class A Reset 2025 | C129: AEPCOTVAR | D129: 100 | E129: 999998.4
A130: CB-Bayou Re Ltd. Series 2023-1 Class A Reset 2025 | B130: CB-Bayou Re Ltd. Series 2023-1 Class A Reset 2025 | C130: AEPCOTVAR | D130: 100 | E130: 999998.4
A131: CB-Bayou Re Ltd. Series 2023-1 Class A Reset 2025 | B131: CB-Bayou Re Ltd. Series 2023-1 Class B Reset 2025 | C131: AEPCOTVAR | D131: 100 | E131: 749998.95
A132: CB-Bayou Re Ltd. Series 2023-1 Class A Reset 2025 | B132: CB-Purple Re Ltd. Series 2024-1 Class A Reset 2025 | C132: AEPCOTVAR | D132: 100 | E132: 507499.22
A133: CB-Bayou Re Ltd. Series 2023-1 Class A Reset 2025 | B133: CB-Purple Re Ltd. Series 2023-2 Class A Reset 2025 | C133: AEPCOTVAR | D133: 100 | E133: 508226.08
A134: CB-Bayou Re Ltd. Series 2023-1 Class A Reset 2025 | B134: CB-Bayou Re Ltd. Series 2024-1 Class A Reset 2025 | C134: AEPCOTVAR | D134: 100 | E134: 653040.83
... A141: CB-Bayou Re Ltd. Series 2023-1 Class A Reset 2025 | B141: CB-Montoya Re Ltd. Series 2025-1 Class B Reset 2025 | C141: AEPCOTVAR | D141: 100 | E141: 540837.33
A142: CB-Bayou Re Ltd. Series 2023-1 Class A Reset 2025 | C142: AEPCOTVAR | D142: 100 | E142: 499999.2
...

Sheet MarginalAEPMxData
A1: ILSName | B1: ILSName2 | C1: Aggtype | D1: Year | E1: AggLoss
A2: CB-Baldwin Re Ltd. Series 2023-1 Class A Reset 2025 | C2: AEPTVAR | D2: 100 | E2: 749999.99
A3: CB-Baldwin Re Ltd. Series 2023-1 Class A Reset 2025 | B3: CB-Baldwin Re Ltd. Series 2023-1 Class A Reset 2025 | C3: AEPTVAR | D3: 100 | E3: 1500000
A4: CB-Baldwin Re Ltd. Series 2023-1 Class A Reset 2025 | B4: CB-Baldwin Re Ltd. Series 2023-1 Class A Reset 2025 | C4: AEPTVAR | D4: 100 | E4: 1500000
A5: CB-Baldwin Re Ltd. Series 2023-1 Class A Reset 2025 | B5: CB-Gateway Re Ltd. Series 2025-1 Class A | C5: AEPTVAR | D5: 100 | E5: 807734.41
A6: CB-Baldwin Re Ltd. Series 2023-1 Class A Reset 2025 | B6: CB-3264 Re Ltd. Series 2024-1 Class B Reset 2025 | C6: AEPTVAR | D6: 100 | E6: 769731.55
A7: CB-Baldwin Re Ltd. Series 2023-1 Class A Reset 2025 | B7: CB-Citrus Re Ltd. Series 2023-1 Class B Reset 2025 | C7: AEPTVAR | D7: 100 | E7: 949836.26
A8: CB-Baldwin Re Ltd. Series 2023-1 Class A Reset 2025 | B8: CB-Blue Ridge Re Ltd. Series 2023-1 Class A Reset 2025 | C8: AEPTVAR | D8: 100 | E8: 768771.44
A9: CB-Baldwin Re Ltd. Series 2023-1 Class A Reset 2025 | B9: CB-Bayou Re Ltd. Series 2023-1 Class A Reset 2025 | C9: AEPTVAR | D9: 100 | E9: 788777.33
A10: CB-Baldwin Re Ltd. Series 2023-1 Class A Reset 2025 | B10: CB-Bayou Re Ltd. Series 2023-1 Class A Reset 2025 | C10: AEPTVAR | D10: 100 | E10: 788777.33
A11: CB-Baldwin Re Ltd. Series 2023-1 Class A Reset 2025 | B11: CB-Bayou Re Ltd. Series 2023-1 Class B Reset 2025 | C11: AEPTVAR | D11: 100 | E11: 776514.58
A12: CB-Baldwin Re Ltd. Series 2023-1 Class A Reset 2025 | B12: CB-Purple Re Ltd. Series 2024-1 Class A Reset 2025 | C12: AEPTVAR | D12: 100 | E12: 756515.99
A13: CB-Baldwin Re Ltd. Series 2023-1 Class A Reset 2025 | B13: CB-Purple Re Ltd. Series 2023-2 Class A Reset 2025 | C13: AEPTVAR | D13: 100 | E13: 757719.77
A14: CB-Baldwin Re Ltd. Series 2023-1 Class A Reset 2025 | B14: CB-Bayou Re Ltd. Series 2024-1 Class A Reset 2025 | C14: AEPTVAR | D14: 100 | E14: 762321.72
... A21: CB-Baldwin Re Ltd. Series 2023-1 Class A Reset 2025 | B21: CB-Montoya Re Ltd. Series 2025-1 Class B Reset 2025 | C21: AEPTVAR | D21: 100 | E21: 809301.53
A22: CB-Baldwin Re Ltd. Series 2023-1 Class A Reset 2025 | C22: AEPTVAR | D22: 100 | E22: 749999.99
A23: CB-Baldwin Re Ltd. Series 2023-1 Class A Reset 2025 | B23: CB-Baldwin Re Ltd. Series 2023-1 Class A Reset 2025 | C23: AEPTVAR | D23: 100 | E23: 1500000
A24: CB-Baldwin Re Ltd. Series 2023-1 Class A Reset 2025 | B24: CB-Baldwin Re Ltd. Series 2023-1 Class A Reset 2025 | C24: AEPTVAR | D24: 100 | E24: 1500000
A25: CB-Baldwin Re Ltd. Series 2023-1 Class A Reset 2025 | B25: CB-Gateway Re Ltd. Series 2025-1 Class A | C25: AEPTVAR | D25: 100 | E25: 807734.41
A26: CB-Baldwin Re Ltd. Series 2023-1 Class A Reset 2025 | B26: CB-3264 Re Ltd. Series 2024-1 Class B Reset 2025 | C26: AEPTVAR | D26: 100 | E26: 769731.55
A27: CB-Baldwin Re Ltd. Series 2023-1 Class A Reset 2025 | B27: CB-Citrus Re Ltd. Series 2023-1 Class B Reset 2025 | C27: AEPTVAR | D27: 100 | E27: 949836.26
A28: CB-Baldwin Re Ltd. Series 2023-1 Class A Reset 2025 | B28: CB-Blue Ridge Re Ltd. Series 2023-1 Class A Reset 2025 | C28: AEPTVAR | D28: 100 | E28: 768771.44
A29: CB-Baldwin Re Ltd. Series 2023-1 Class A Reset 2025 | B29: CB-Bayou Re Ltd. Series 2023-1 Class A Reset 2025 | C29: AEPTVAR | D29: 100 | E29: 788777.33
A30: CB-Baldwin Re Ltd. Series 2023-1 Class A Reset 2025 | B30: CB-Bayou Re Ltd. Series 2023-1 Class A Reset 2025 | C30: AEPTVAR | D30: 100 | E30: 788777.33
A31: CB-Baldwin Re Ltd. Series 2023-1 Class A Reset 2025 | B31: CB-Bayou Re Ltd. Series 2023-1 Class B Reset 2025 | C31: AEPTVAR | D31: 100 | E31: 776514.58
A32: CB-Baldwin Re Ltd. Series 2023-1 Class A Reset 2025 | B32: CB-Purple Re Ltd. Series 2024-1 Class A Reset 2025 | C32: AEPTVAR | D32: 100 | E32: 756515.99
A33: CB-Baldwin Re Ltd. Series 2023-1 Class A Reset 2025 | B33: CB-Purple Re Ltd. Series 2023-2 Class A Reset 2025 | C33: AEPTVAR | D33: 100 | E33: 757719.77
A34: CB-Baldwin Re Ltd. Series 2023-1 Class A Reset 2025 | B34: CB-Bayou Re Ltd. Series 2024-1 Class A Reset 2025 | C34: AEPTVAR | D34: 100 | E34: 762321.72
... A41: CB-Baldwin Re Ltd. Series 2023-1 Class A Reset 2025 | B41: CB-Montoya Re Ltd. Series 2025-1 Class B Reset 2025 | C41: AEPTVAR | D41: 100 | E41: 809301.53
A42: CB-Gateway Re Ltd. Series 2025-1 Class A | C42: AEPTVAR | D42: 100 | E42: 250000
A43: CB-Gateway Re Ltd. Series 2025-1 Class A | B43: CB-Baldwin Re Ltd. Series 2023-1 Class A Reset 2025 | C43: AEPTVAR | D43: 100 | E43: 807734.41
A44: CB-Gateway Re Ltd. Series 2025-1 Class A | B44: CB-Baldwin Re Ltd. Series 2023-1 Class A Reset 2025 | C44: AEPTVAR | D44: 100 | E44: 807734.41
A45: CB-Gateway Re Ltd. Series 2025-1 Class A | B45: CB-Gateway Re Ltd. Series 2025-1 Class A | C45: AEPTVAR | D45: 100 | E45: 500000
A46: CB-Gateway Re Ltd. Series 2025-1 Class A | B46: CB-3264 Re Ltd. Series 2024-1 Class B Reset 2025 | C46: AEPTVAR | D46: 100 | E46: 500000.2
A47: CB-Gateway Re Ltd. Series 2025-1 Class A | B47: CB-Citrus Re Ltd. Series 2023-1 Class B Reset 2025 | C47: AEPTVAR | D47: 100 | E47: 332045.15
A48: CB-Gateway Re Ltd. Series 2025-1 Class A | B48: CB-Blue Ridge Re Ltd. Series 2023-1 Class A Reset 2025 | C48: AEPTVAR | D48: 100 | E48: 339664.54
A49: CB-Gateway Re Ltd. Series 2025-1 Class A | B49: CB-Bayou Re Ltd. Series 2023-1 Class A Reset 2025 | C49: AEPTVAR | D49: 100 | E49: 749315.49
A50: CB-Gateway Re Ltd. Series 2025-1 Class A | B50: CB-Bayou Re Ltd. Series 2023-1 Class A Reset 2025 | C50: AEPTVAR | D50: 100 | E50: 749315.49
A51: CB-Gateway Re Ltd. Series 2025-1 Class A | B51: CB-Bayou Re Ltd. Series 2023-1 Class B Reset 2025 | C51: AEPTVAR | D51: 100 | E51: 499999.75
A52: CB-Gateway Re Ltd. Series 2025-1 Class A | B52: CB-Purple Re Ltd. Series 2024-1 Class A Reset 2025 | C52: AEPTVAR | D52: 100 | E52: 314407.14
A53: CB-Gateway Re Ltd. Series 2025-1 Class A | B53: CB-Purple Re Ltd. Series 2023-2 Class A Reset 2025 | C53: AEPTVAR | D53: 100 | E53: 323893.33
A54: CB-Gateway Re Ltd. Series 2025-1 Class A | B54: CB-Bayou Re Ltd. Series 2024-1 Class A Reset 2025 | C54: AEPTVAR | D54: 100 | E54: 491514.86
... A61: CB-Gateway Re Ltd. Series 2025-1 Class A | B61: CB-Montoya Re Ltd. Series 2025-1 Class B Reset 2025 | C61: AEPTVAR | D61: 100 | E61: 417136.95
A62: CB-3264 Re Ltd. Series 2024-1 Class B Reset 2025 | C62: AEPTVAR | D62: 100 | E62: 250000.2
A63: CB-3264 Re Ltd. Series 2024-1 Class B Reset 2025 | B63: CB-Baldwin Re Ltd. Series 2023-1 Class A Reset 2025 | C63: AEPTVAR | D63: 100 | E63: 769731.55
A64: CB-3264 Re Ltd. Series 2024-1 Class B Reset 2025 | B64: CB-Baldwin Re Ltd. Series 2023-1 Class A Reset 2025 | C64: AEPTVAR | D64: 100 | E64: 769731.55
A65: CB-3264 Re Ltd. Series 2024-1 Class B Reset 2025 | B65: CB-Gateway Re Ltd. Series 2025-1 Class A | C65: AEPTVAR | D65: 100 | E65: 500000.2
A66: CB-3264 Re Ltd. Series 2024-1 Class B Reset 2025 | B66: CB-3264 Re Ltd. Series 2024-1 Class B Reset 2025 | C66: AEPTVAR | D66: 100 | E66: 500000.4
A67: CB-3264 Re Ltd. Series 2024-1 Class B Reset 2025 | B67: CB-Citrus Re Ltd. Series 2023-1 Class B Reset 2025 | C67: AEPTVAR | D67: 100 | E67: 283874.25
A68: CB-3264 Re Ltd. Series 2024-1 Class B Reset 2025 | B68: CB-Blue Ridge Re Ltd. Series 2023-1 Class A Reset 2025 | C68: AEPTVAR | D68: 100 | E68: 274880.57
A69: CB-3264 Re Ltd. Series 2024-1 Class B Reset 2025 | B69: CB-Bayou Re Ltd. Series 2023-1 Class A Reset 2025 | C69: AEPTVAR | D69: 100 | E69: 749999.4
A70: CB-3264 Re Ltd. Series 2024-1 Class B Reset 2025 | B70: CB-Bayou Re Ltd. Series 2023-1 Class A Reset 2025 | C70: AEPTVAR | D70: 100 | E70: 749999.4
A71: CB-3264 Re Ltd. Series 2024-1 Class B Reset 2025 | B71: CB-Bayou Re Ltd. Series 2023-1 Class B Reset 2025 | C71: AEPTVAR | D71: 100 | E71: 499999.95
A72: CB-3264 Re Ltd. Series 2024-1 Class B Reset 2025 | B72: CB-Purple Re Ltd. Series 2024-1 Class A Reset 2025 | C72: AEPTVAR | D72: 100 | E72: 286997.84
A73: CB-3264 Re Ltd. Series 2024-1 Class B Reset 2025 | B73: CB-Purple Re Ltd. Series 2023-2 Class A Reset 2025 | C73: AEPTVAR | D73: 100 | E73: 295478.51
A74: CB-3264 Re Ltd. Series 2024-1 Class B Reset 2025 | B74: CB-Bayou Re Ltd. Series 2024-1 Class A Reset 2025 | C74: AEPTVAR | D74: 100 | E74: 500000.2
... A81: CB-3264 Re Ltd. Series 2024-1 Class B Reset 2025 | B81: CB-Montoya Re Ltd. Series 2025-1 Class B Reset 2025 | C81: AEPTVAR | D81: 100 | E81: 479116.76
A82: CB-Citrus Re Ltd. Series 2023-1 Class B Reset 2025 | C82: AEPTVAR | D82: 100 | E82: 249999.65
A83: CB-Citrus Re Ltd. Series 2023-1 Class B Reset 2025 | B83: CB-Baldwin Re Ltd. Series 2023-1 Class A Reset 2025 | C83: AEPTVAR | D83: 100 | E83: 949836.26
A84: CB-Citrus Re Ltd. Series 2023-1 Class B Reset 2025 | B84: CB-Baldwin Re Ltd. Series 2023-1 Class A Reset 2025 | C84: AEPTVAR | D84: 100 | E84: 949836.26
A85: CB-Citrus Re Ltd. Series 2023-1 Class B Reset 2025 | B85: CB-Gateway Re Ltd. Series 2025-1 Class A | C85: AEPTVAR | D85: 100 | E85: 332045.15
A86: CB-Citrus Re Ltd. Series 2023-1 Class B Reset 2025 | B86: CB-3264 Re Ltd. Series 2024-1 Class B Reset 2025 | C86: AEPTVAR | D86: 100 | E86: 283874.25
A87: CB-Citrus Re Ltd. Series 2023-1 Class B Reset 2025 | B87: CB-Citrus Re Ltd. Series 2023-1 Class B Reset 2025 | C87: AEPTVAR | D87: 100 | E87: 499999.3
A88: CB-Citrus Re Ltd. Series 2023-1 Class B Reset 2025 | B88: CB-Blue Ridge Re Ltd. Series 2023-1 Class A Reset 2025 | C88: AEPTVAR | D88: 100 | E88: 281856.52
A89: CB-Citrus Re Ltd. Series 2023-1 Class B Reset 2025 | B89: CB-Bayou Re Ltd. Series 2023-1 Class A Reset 2025 | C89: AEPTVAR | D89: 100 | E89: 519999.17
A90: CB-Citrus Re Ltd. Series 2023-1 Class B Reset 2025 | B90: CB-Bayou Re Ltd. Series 2023-1 Class A Reset 2025 | C90: AEPTVAR | D90: 100 | E90: 519999.17
A91: CB-Citrus Re Ltd. Series 2023-1 Class B Reset 2025 | B91: CB-Bayou Re Ltd. Series 2023-1 Class B Reset 2025 | C91: AEPTVAR | D91: 100 | E91: 281633.25
A92: CB-Citrus Re Ltd. Series 2023-1 Class B Reset 2025 | B92: CB-Purple Re Ltd. Series 2024-1 Class A Reset 2025 | C92: AEPTVAR | D92: 100 | E92: 267203.5
A93: CB-Citrus Re Ltd. Series 2023-1 Class B Reset 2025 | B93: CB-Purple Re Ltd. Series 2023-2 Class A Reset 2025 | C93: AEPTVAR | D93: 100 | E93: 270464.27
A94: CB-Citrus Re Ltd. Series 2023-1 Class B Reset 2025 | B94: CB-Bayou Re Ltd. Series 2024-1 Class A Reset 2025 | C94: AEPTVAR | D94: 100 | E94: 260970.9
... A101: CB-Citrus Re Ltd. Series 2023-1 Class B Reset 2025 | B101: CB-Montoya Re Ltd. Series 2025-1 Class B Reset 2025 | C101: AEPTVAR | D101: 100 | E101: 357549.25
A102: CB-Blue Ridge Re Ltd. Series 2023-1 Class A Reset 2025 | C102: AEPTVAR | D102: 100 | E102: 250000
A103: CB-Blue Ridge Re Ltd. Series 2023-1 Class A Reset 2025 | B103: CB-Baldwin Re Ltd. Series 2023-1 Class A Reset 2025 | C103: AEPTVAR | D103: 100 | E103: 768771.44
A104: CB-Blue Ridge Re Ltd. Series 2023-1 Class A Reset 2025 | B104: CB-Baldwin Re Ltd. Series 2023-1 Class A Reset 2025 | C104: AEPTVAR | D104: 100 | E104: 768771.44
A105: CB-Blue Ridge Re Ltd. Series 2023-1 Class A Reset 2025 | B105: CB-Gateway Re Ltd. Series 2025-1 Class A | C105: AEPTVAR | D105: 100 | E105: 339664.54
A106: CB-Blue Ridge Re Ltd. Series 2023-1 Class A Reset 2025 | B106: CB-3264 Re Ltd. Series 2024-1 Class B Reset 2025 | C106: AEPTVAR | D106: 100 | E106: 274880.57
A107: CB-Blue Ridge Re Ltd. Series 2023-1 Class A Reset 2025 | B107: CB-Citrus Re Ltd. Series 2023-1 Class B Reset 2025 | C107: AEPTVAR | D107: 100 | E107: 281856.52
A108: CB-Blue Ridge Re Ltd. Series 2023-1 Class A Reset 2025 | B108: CB-Blue Ridge Re Ltd. Series 2023-1 Class A Reset 2025 | C108: AEPTVAR | D108: 100 | E108: 499999.99
A109: CB-Blue Ridge Re Ltd. Series 2023-1 Class A Reset 2025 | B109: CB-Bayou Re Ltd. Series 2023-1 Class A Reset 2025 | C109: AEPTVAR | D109: 100 | E109: 512383.88
A110: CB-Blue Ridge Re Ltd. Series 2023-1 Class A Reset 2025 | B110: CB-Bayou Re Ltd. Series 2023-1 Class A Reset 2025 | C110: AEPTVAR | D110: 100 | E110: 512383.88
A111: CB-Blue Ridge Re Ltd. Series 2023-1 Class A Reset 2025 | B111: CB-Bayou Re Ltd. Series 2023-1 Class B Reset 2025 | C111: AEPTVAR | D111: 100 | E111: 269550.04
A112: CB-Blue Ridge Re Ltd. Series 2023-1 Class A Reset 2025 | B112: CB-Purple Re Ltd. Series 2024-1 Class A Reset 2025 | C112: AEPTVAR | D112: 100 | E112: 275819.92
A113: CB-Blue Ridge Re Ltd. Series 2023-1 Class A Reset 2025 | B113: CB-Purple Re Ltd. Series 2023-2 Class A Reset 2025 | C113: AEPTVAR | D113: 100 | E113: 279389.85
A114: CB-Blue Ridge Re Ltd. Series 2023-1 Class A Reset 2025 | B114: CB-Bayou Re Ltd. Series 2024-1 Class A Reset 2025 | C114: AEPTVAR | D114: 100 | E114: 259759.96
... A121: CB-Blue Ridge Re Ltd. Series 2023-1 Class A Reset 2025 | B121: CB-Montoya Re Ltd. Series 2025-1 Class B Reset 2025 | C121: AEPTVAR | D121: 100 | E121: 339345.17
A122: CB-Bayou Re Ltd. Series 2023-1 Class A Reset 2025 | C122: AEPTVAR | D122: 100 | E122: 499999.2
A123: CB-Bayou Re Ltd. Series 2023-1 Class A Reset 2025 | B123: CB-Baldwin Re Ltd. Series 2023-1 Class A Reset 2025 | C123: AEPTVAR | D123: 100 | E123: 788777.33
A124: CB-Bayou Re Ltd. Series 2023-1 Class A Reset 2025 | B124: CB-Baldwin Re Ltd. Series 2023-1 Class A Reset 2025 | C124: AEPTVAR | D124: 100 | E124: 788777.33
A125: CB-Bayou Re Ltd. Series 2023-1 Class A Reset 2025 | B125: CB-Gateway Re Ltd. Series 2025-1 Class A | C125: AEPTVAR | D125: 100 | E125: 749315.49
A126: CB-Bayou Re Ltd. Series 2023-1 Class A Reset 2025 | B126: CB-3264 Re Ltd. Series 2024-1 Class B Reset 2025 | C126: AEPTVAR | D126: 100 | E126: 749999.4
A127: CB-Bayou Re Ltd. Series 2023-1 Class A Reset 2025 | B127: CB-Citrus Re Ltd. Series 2023-1 Class B Reset 2025 | C127: AEPTVAR | D127: 100 | E127: 519999.17
A128: CB-Bayou Re Ltd. Series 2023-1 Class A Reset 2025 | B128: CB-Blue Ridge Re Ltd. Series 2023-1 Class A Reset 2025 | C128: AEPTVAR | D128: 100 | E128: 512383.88
A129: CB-Bayou Re Ltd. Series 2023-1 Class A Reset 2025 | B129: CB-Bayou Re Ltd. Series 2023-1 Class A Reset 2025 | C129: AEPTVAR | D129: 100 | E129: 999998.4
A130: CB-Bayou Re Ltd. Series 2023-1 Class A Reset 2025 | B130: CB-Bayou Re Ltd. Series 2023-1 Class A Reset 2025 | C130: AEPTVAR | D130: 100 | E130: 999998.4
A131: CB-Bayou Re Ltd. Series 2023-1 Class A Reset 2025 | B131: CB-Bayou Re Ltd. Series 2023-1 Class B Reset 2025 | C131: AEPTVAR | D131: 100 | E131: 749998.95
A132: CB-Bayou Re Ltd. Series 2023-1 Class A Reset 2025 | B132: CB-Purple Re Ltd. Series 2024-1 Class A Reset 2025 | C132: AEPTVAR | D132: 100 | E132: 518142.24
A133: CB-Bayou Re Ltd. Series 2023-1 Class A Reset 2025 | B133: CB-Purple Re Ltd. Series 2023-2 Class A Reset 2025 | C133: AEPTVAR | D133: 100 | E133: 523226.08
A134: CB-Bayou Re Ltd. Series 2023-1 Class A Reset 2025 | B134: CB-Bayou Re Ltd. Series 2024-1 Class A Reset 2025 | C134: AEPTVAR | D134: 100 | E134: 749999.2
... A141: CB-Bayou Re Ltd. Series 2023-1 Class A Reset 2025 | B141: CB-Montoya Re Ltd. Series 2025-1 Class B Reset 2025 | C141: AEPTVAR | D141: 100 | E141: 603346.97
A142: CB-Bayou Re Ltd. Series 2023-1 Class A Reset 2025 | C142: AEPTVAR | D142: 100 | E142: 499999.2
...

Sheet Guidelines Summary
A1: Limit by Security Instrument
A2: SecurityInstrument | B2: Exposed Limit | C2: Actual % of AUM | D2: Guideline | E2: Guideline Check | F2: EL (%) | G2: AUM (%) | H2: Premium (%) | I2: Premium ($)
A3: Cat Bond | B3: 5489523.7 | C3: 1.3723809 | D3: 0.05 | E3: Breached | F3: 0.99999673 | G3: 1.463873 | H3: 0.9999996 | I3: 755446.7
A10: PML Summary
A11: PerilRegion | B11: Actual 100 yr Occ PML ($) | C11: Actual 500 yr Agg PML ($) | D11: Actual 100 yr Occ PML (%) | E11: Actual 500 yr Occ PML (%) | F11: Guideline 100 yr Occ PML (%) | G11: Guideline 500 yr Agg PML (%) | H11: Guideline Check 100 yr Occ PML (%) | I11: Guideline Check 100 yr Occ PML (%)
A12: US Hurricanes | B12: 2315589.4 | C12: 2791852.9 | D12: 0.57889735 | E12: 0.69796323 | F12: 0.35 | G12: 0.5 | H12: Breached | I12: Breached
A13: Florida Hurricane | B13: 500000.8 | C13: 1116482.5 | D13: 0.1250002 | E13: 0.27912063 | F13: 0.3 | G13: 0.5 | H13: OK | I13: OK
A14: Texas Hurricane | B14: 798142.53 | C14: 999998.95 | D14: 0.19953563 | E14: 0.24999974 | F14: 0.3 | G14: 0.5 | H14: OK | I14: OK
A15: Gulf of Mexico WS | B15: 2201255.2 | C15: 2499998.4 | D15: 0.55031381 | E15: 0.62499961 | F15: 0.3 | G15: 0.5 | H15: Breached | I15: Breached
A16: California Earthquake | B16: 0 | C16: 0 | D16: 0 | E16: 0 | F16: 0.2 | G16: 0.35 | H16: OK | I16: OK
A17: US Earthquake xl CA | B17: 0 | C17: 0 | D17: 0 | E17: 0 | F17: 0.3 | G17: 0.45 | H17: OK | I17: OK
A18: US Inland Flood | B18: 0 | C18: 0 | D18: 0 | E18: 0 | F18: 0.2 | G18: 0.35 | H18: OK | I18: OK
A19: Japan Earthquake | B19: 0 | C19: 0 | D19: 0 | E19: 0 | F19: 0.2 | G19: 0.3 | H19: OK | I19: OK
A20: Japan Typhoon | B20: 0 | C20: 0 | D20: 0 | E20: 0 | F20: 0.3 | G20: 0.5 | H20: OK | I20: OK
A21: US Severe Storm | B21: 0 | C21: 0 | D21: 0 | E21: 0 | F21: 0.2 | G21: 0.35 | H21: OK | I21: OK
A22: US Winter Storm | B22: 0 | C22: 0 | D22: 0 | E22: 0 | F22: 0.2 | G22: 0.35 | H22: OK | I22: OK
A23: US WildFire | B23: 0 | C23: 0 | D23: 0 | E23: 0 | F23: 0.2 | G23: 0.35 | H23: OK | I23: OK
... A34: all other EQ | B34: 0 | C34: 0 | D34: 0 | E34: 0 | F34: 0.2 | G34: 0.3 | H34: OK | I34: OK
A40: Issuer | B40: Exposed Limit | C40: Actual % of AUM | D40: Guideline | E40: Guideline Check
B41: 5249998.8 | C41: 1.3124997 | D41: 0.3 | E41: Breached
A42: American Coastal | B42: 500000 | C42: 0.19857936 | D42: 0.1 | E42: Breached
A43: American European Insurance | B43: 250000 | C43: 0.099289682 | D43: 0.1 | E43: Breached
A44: American Family | B44: 499999.75 | C44: 0.19857926 | D44: 0.1 | E44: Breached
A45: Ariel Re | B45: 249999.75 | C45: 0.099289582 | D45: 0.1 | E45: Breached
A46: Beazley | B46: 250000 | C46: 0.099289682 | D46: 0.1 | E46: Breached
A47: Brookfield Property | B47: 250000 | C47: 0.099289682 | D47: 0.1 | E47: Breached
A48: CEA | B48: 499998.75 | C48: 0.19857887 | D48: 0.1 | E48: Breached
A49: Fidelis | B49: 500000.4 | C49: 0.19857952 | D49: 0.1 | E49: Breached
A50: FL Citizens | B50: 1000001.5 | C50: 0.39715932 | D50: 0.1 | E50: Breached
A51: FL Peninsula | B51: 250000.5 | C51: 0.09928988 | D51: 0.1 | E51: Breached
A52: GeoVera | B52: 749999.25 | C52: 0.29786875 | D52: 0.1 | E52: Breached
A53: Gryphon Mutual (Blackstone) | B53: 500000.5 | C53: 0.19857956 | D53: 0.1 | E53: Breached
... A78: Zenkyoren | B78: 500001 | C78: 0.19857976 | D78: 0.1 | E78: Breached

Sheet Region Peril
A4: ID | B4: RegionPerilDescription | C4: AAL | D4: OtherAAL | E4: VAR_100 | F4: TVAR_100 | G4: CoTVAR_100 | H4: AEP_100_OtherAAL | I4: PnL | J4: Allianz | K4: CAT Bond | L4: ILW Long | M4: ILW Short | N4: Reinsurance | O4: Retro QS | P4: Retro XOL | Q4: Side Car | R4: Mitsui Sumitomo | S4: NC Farm Bureau | T4: Reinsurance | U4: Retro QS | V4: Retro XOL | W4: Side Car | X4: Talanx AG (Via Hannover Re) | Y4: Texaf Farm Bureau | Z4: Zenkyoren
A5: 1 | B5: WWAP | C5: 144605.53 | D5: -6.1118044e-10 | E5: 2487342.8 | F5: 2737508.4 | G5: 2737508.4 | H5: 2487342.8 | I5: -1737421 | J5: 0 | K5: 0 | L5: 0 | M5: 0 | N5: 0 | O5: 0 | P5: 0 | Q5: 0 | R5: 0 | S5: 0 | T5: 0 | U5: 0 | V5: 0 | W5: 0 | X5: 0 | Y5: 0 | Z5: 0
A6: 2 | B6: US Hurricanes | C6: 143111.55 | D6: 1493.9802 | E6: 2487342.8 | F6: 2735008.4 | G6: 2735008.4 | H6: 2488836.7 | I6: -1738915 | J6: 0 | K6: 0 | L6: 0 | M6: 0 | N6: 0 | O6: 0 | P6: 0 | Q6: 0 | R6: 0 | S6: 0 | T6: 0 | U6: 0 | V6: 0 | W6: 0 | X6: 0 | Y6: 0 | Z6: 0
A7: 3 | B7: Florida Hurricane | C7: 18542.427 | D7: 126063.1 | E7: 512594.51 | F7: 939853.42 | G7: 193660.88 | H7: 638657.61 | I7: 111264.09 | J7: 0 | K7: 0 | L7: 0 | M7: 0 | N7: 0 | O7: 0 | P7: 0 | Q7: 0 | R7: 0 | S7: 0 | T7: 0 | U7: 0 | V7: 0 | W7: 0 | X7: 0 | Y7: 0 | Z7: 0
A8: 4 | B8: Texas Hurricane | C8: 18882.68 | D8: 125722.85 | E8: 800362.45 | F8: 1013223 | G8: 40877.925 | H8: 926085.3 | I8: -176163.6 | J8: 0 | K8: 0 | L8: 0 | M8: 0 | N8: 0 | O8: 0 | P8: 0 | Q8: 0 | R8: 0 | S8: 0 | T8: 0 | U8: 0 | V8: 0 | W8: 0 | X8: 0 | Y8: 0 | Z8: 0
A9: 5 | B9: Louisiana Hurricane | C9: 49150.736 | D9: 95454.791 | E9: 2180673.9 | F9: 2488710.6 | G9: 2113591.4 | H9: 2276128.7 | I9: -1526207 | J9: 0 | K9: 0 | L9: 0 | M9: 0 | N9: 0 | O9: 0 | P9: 0 | Q9: 0 | R9: 0 | S9: 0 | T9: 0 | U9: 0 | V9: 0 | W9: 0 | X9: 0 | Y9: 0 | Z9: 0
A10: 6 | B10: Northeast Hurricane | C10: 14352.056 | D10: 130253.47 | E10: 749999.99 | F10: 1169632.5 | G10: 43999.442 | H10: 880253.46 | I10: -130331.76 | J10: 0 | K10: 0 | L10: 0 | M10: 0 | N10: 0 | O10: 0 | P10: 0 | Q10: 0 | R10: 0 | S10: 0 | T10: 0 | U10: 0 | V10: 0 | W10: 0 | X10: 0 | Y10: 0 | Z10: 0
A11: 7 | B11: Southeast Hurricane | C11: 19436.085 | D11: 125169.44 | E11: 688091.35 | F11: 1227872.9 | G11: 89519.365 | H11: 813260.79 | I11: -63339.094 | J11: 0 | K11: 0 | L11: 0 | M11: 0 | N11: 0 | O11: 0 | P11: 0 | Q11: 0 | R11: 0 | S11: 0 | T11: 0 | U11: 0 | V11: 0 | W11: 0 | X11: 0 | Y11: 0 | Z11: 0
A12: 8 | B12: Gulf of Mexico WS | C12: 54724.323 | D12: 89881.204 | E12: 2292829.4 | F12: 2500903.7 | G12: 2256824.6 | H12: 2382710.6 | I12: -1632788.9 | J12: 0 | K12: 0 | L12: 0 | M12: 0 | N12: 0 | O12: 0 | P12: 0 | Q12: 0 | R12: 0 | S12: 0 | T12: 0 | U12: 0 | V12: 0 | W12: 0 | X12: 0 | Y12: 0 | Z12: 0
A13: 9 | B13: California Earthquake | C13: 293.23046 | D13: 144312.3 | E13: 0 | F13: 29323.046 | G13: 2499.999 | H13: 144312.3 | I13: 605609.4 | J13: 0 | K13: 0 | L13: 0 | M13: 0 | N13: 0 | O13: 0 | P13: 0 | Q13: 0 | R13: 0 | S13: 0 | T13: 0 | U13: 0 | V13: 0 | W13: 0 | X13: 0 | Y13: 0 | Z13: 0
A14: 10 | B14: US Earthquake xl CA | C14: 213.54244 | D14: 144391.98 | E14: 0 | F14: 21354.244 | G14: 0 | H14: 144391.98 | I14: 605529.72 | J14: 0 | K14: 0 | L14: 0 | M14: 0 | N14: 0 | O14: 0 | P14: 0 | Q14: 0 | R14: 0 | S14: 0 | T14: 0 | U14: 0 | V14: 0 | W14: 0 | X14: 0 | Y14: 0 | Z14: 0
A15: 11 | B15: US Inland Flood | C15: 0 | D15: 144605.53 | E15: 0 | F15: 0 | G15: 0 | H15: 144605.53 | I15: 605316.17 | J15: 0 | K15: 0 | L15: 0 | M15: 0 | N15: 0 | O15: 0 | P15: 0 | Q15: 0 | R15: 0 | S15: 0 | T15: 0 | U15: 0 | V15: 0 | W15: 0 | X15: 0 | Y15: 0 | Z15: 0
A16: 12 | B16: Europe Tropical Cyclone | C16: 0 | D16: 144605.53 | E16: 0 | F16: 0 | G16: 0 | H16: 144605.53 | I16: 605316.17 | J16: 0 | K16: 0 | L16: 0 | M16: 0 | N16: 0 | O16: 0 | P16: 0 | Q16: 0 | R16: 0 | S16: 0 | T16: 0 | U16: 0 | V16: 0 | W16: 0 | X16: 0 | Y16: 0 | Z16: 0
... A28: 24 | B28: all other EQ | C28: 24.99999 | D28: 144580.53 | E28: 0 | F28: 2499.999 | G28: 0 | H28: 144580.53 | I28: 605341.17 | J28: 0 | K28: 0 | L28: 0 | M28: 0 | N28: 0 | O28: 0 | P28: 0 | Q28: 0 | R28: 0 | S28: 0 | T28: 0 | U28: 0 | V28: 0 | W28: 0 | X28: 0 | Y28: 0 | Z28: 0

Sheet AAL by Month
A1: Monthly Earning Pattern | P1: Monthly Premium Break-up
A2: ILSName | B2: Jan | C2: Feb | D2: Mar | E2: Apr | F2: May | G2: June | H2: July | I2: Aug | J2: Sept | K2: Oct | L2: Nov | M2: Dec | P2: Month | Q2: Gross Premium | R2: Premium Share
A3: Portfolio | B3: 0 | C3: 0.00026177278 | D3: 0.0003267203 | E3: 0 | F3: 0.0011095445 | G3: 0.022919838 | H3: 0.15359933 | I3: 0.29018962 | J3: 0.32702355 | K3: 0.18568892 | L3: 0.01705044 | M3: 0.0018269883 | P3: 2 | Q3: 197.75538 | R3: 0.00026177278
A4: CB-Baldwin Re Ltd. Series 2023-1 Class A Reset 2025 | B4: 0 | C4: 0.0028924115 | D4: 0.0036100375 | E4: 0 | F4: 0.0063385328 | G4: 0.0070436204 | H4: 0.15485523 | I4: 0.23836985 | J4: 0.38686087 | K4: 0.19429829 | L4: 0.0057307378 | M4: 0 | P4: 3 | Q4: 246.81978 | R4: 0.0003267203
A5: CB-Baldwin Re Ltd. Series 2023-1 Class A Reset 2025 | B5: 0 | C5: 0.0028924115 | D5: 0.0036100375 | E5: 0 | F5: 0.0063385328 | G5: 0.0070436204 | H5: 0.15485523 | I5: 0.23836985 | J5: 0.38686087 | K5: 0.19429829 | L5: 0.0057307378 | M5: 0 | P5: 5 | Q5: 838.20174 | R5: 0.0011095445
A6: CB-Gateway Re Ltd. Series 2025-1 Class A | B6: 0 | C6: 0 | D6: 0 | E6: 0 | F6: 0 | G6: 0.025169109 | H6: 0.15598207 | I6: 0.3242963 | J6: 0.32021457 | K6: 0.15777471 | L6: 0.01656369 | M6: 0 | P6: 6 | Q6: 17314.716 | R6: 0.022919838
A7: CB-3264 Re Ltd. Series 2024-1 Class B Reset 2025 | B7: 0 | C7: 0 | D7: 0 | E7: 0 | F7: 0.0048651298 | G7: 0.024631031 | H7: 0.14762059 | I7: 0.33247406 | J7: 0.3181842 | K7: 0.15886893 | L7: 0.013359575 | M7: 0 | P7: 7 | Q7: 116036.11 | R7: 0.15359933
A8: CB-Citrus Re Ltd. Series 2023-1 Class B Reset 2025 | B8: 0 | C8: 0 | D8: 0 | E8: 0 | F8: 0 | G8: 0.0075515251 | H8: 0.17212246 | I8: 0.28414359 | J8: 0.33628088 | K8: 0.15264839 | L8: 0.031619609 | M8: 0.015633117 | P8: 8 | Q8: 219222.79 | R8: 0.29018962
A9: CB-Blue Ridge Re Ltd. Series 2023-1 Class A Reset 2025 | B9: 0 | C9: 0 | D9: 0 | E9: 0 | F9: 0 | G9: 0.012844112 | H9: 0.14927831 | I9: 0.27728414 | J9: 0.32860554 | K9: 0.21968485 | L9: 0.01230302 | M9: 0 | P9: 9 | Q9: 247048.86 | R9: 0.32702355
A10: CB-Bayou Re Ltd. Series 2023-1 Class A Reset 2025 | B10: 0 | C10: 0 | D10: 0 | E10: 0 | F10: 0 | G10: 0.039846408 | H10: 0.1796604 | I10: 0.2785281 | J10: 0.2976105 | K10: 0.18811369 | L10: 0.01624041 | M10: 0 | P10: 10 | Q10: 140278.08 | R10: 0.18568892
A11: CB-Bayou Re Ltd. Series 2023-1 Class A Reset 2025 | B11: 0 | C11: 0 | D11: 0 | E11: 0 | F11: 0 | G11: 0.039846408 | H11: 0.1796604 | I11: 0.2785281 | J11: 0.2976105 | K11: 0.18811369 | L11: 0.01624041 | M11: 0 | P11: 11 | Q11: 12880.699 | R11: 0.01705044
A12: CB-Bayou Re Ltd. Series 2023-1 Class B Reset 2025 | B12: 0 | C12: 0 | D12: 0 | E12: 0 | F12: 0 | G12: 0.036139973 | H12: 0.18499048 | I12: 0.28995057 | J12: 0.30115588 | K12: 0.17710699 | L12: 0.010656668 | M12: 0 | P12: 12 | Q12: 1380.1923 | R12: 0.0018269883
A13: CB-Purple Re Ltd. Series 2024-1 Class A Reset 2025 | B13: 0 | C13: 0 | D13: 0 | E13: 0 | F13: 0 | G13: 0.028890805 | H13: 0.12019188 | I13: 0.32100495 | J13: 0.30145733 | K13: 0.20428272 | L13: 0.024172594 | M13: 0 | P13: 11 | Q13: 36811.59 | R13: 0.083444062
A14: CB-Purple Re Ltd. Series 2023-2 Class A Reset 2025 | B14: 0 | C14: 0 | D14: 0 | E14: 0 | F14: 0 | G14: 0.028857961 | H14: 0.1173204 | I14: 0.30545203 | J14: 0.31246494 | K14: 0.21437376 | L14: 0.02153071 | M14: 0 | P14: 12 | Q14: 48491.242 | R14: 0.10991935
A15: CB-Bayou Re Ltd. Series 2024-1 Class A Reset 2025 | B15: 0 | C15: 0 | D15: 0 | E15: 0 | F15: 0 | G15: 0.03159944 | H15: 0.18225097 | I15: 0.29256758 | J15: 0.2882632 | K15: 0.18170206 | L15: 0.02361632 | M15: 0
A16: CB-Bayou Re Ltd. Series 2024-1 Class B Reset 2025 | B16: 0 | C16: 0 | D16: 0 | E16: 0 | F16: 0 | G16: 0.036139973 | H16: 0.18499048 | I16: 0.28995057 | J16: 0.30115588 | K16: 0.17710699 | L16: 0.010656668 | M16: 0
A17: CB-Bayou Re Ltd. Series 2025-1 Class A | B17: 0 | C17: 0 | D17: 0 | E17: 0 | F17: 0 | G17: 0.042096505 | H17: 0.18203148 | I17: 0.28011761 | J17: 0.29448478 | K17: 0.18038246 | L17: 0.020887272 | M17: 0
A18: CB-Charles River Re Ltd. Series 2024-1 Class A Reset 2025 | B18: 0 | C18: 0 | D18: 0 | E18: 0 | F18: 0 | G18: 0.0075399748 | H18: 0.14547916 | I18: 0.28929805 | J18: 0.35737251 | K18: 0.18905342 | L18: 0.011256889 | M18: 0
A19: CB-Charles River Re Ltd. Series 2024-1 Class A Reset 2025 | B19: 0 | C19: 0 | D19: 0 | E19: 0 | F19: 0 | G19: 0.0075399748 | H19: 0.14547916 | I19: 0.28929805 | J19: 0.35737251 | K19: 0.18905342 | L19: 0.011256889 | M19: 0
A20: CB-Gateway Re Ltd. Series 2023-1 Class A Reset 2025 | B20: 0 | C20: 0 | D20: 0 | E20: 0 | F20: 0 | G20: 0.027425774 | H20: 0.15980233 | I20: 0.33084559 | J20: 0.30602603 | K20: 0.16374264 | L20: 0.012158077 | M20: 0
A21: CB-Gateway Re Ltd. Series 2023-1 Class B Reset 2025 | B21: 0 | C21: 0 | D21: 0 | E21: 0 | F21: 0.00075295401 | G21: 0.027878758 | H21: 0.16413676 | I21: 0.31382289 | J21: 0.31779938 | K21: 0.16289011 | L21: 0.012722244 | M21: 0
A22: CB-Montoya Re Ltd. Series 2025-1 Class B Reset 2025 | B22: 0 | C22: 0 | D22: 0 | E22: 0 | F22: 0 | G22: 0.010381811 | H22: 0.036057237 | I22: 0.18521528 | J22: 0.36622743 | K22: 0.30866859 | L22: 0.070566936 | M22: 0.02288307
A23: CB-Nakama Re Ltd. Series 2023-1 Class 2 Reset 2025 | B23: 0.096128275 | C23: 0.088183544 | D23: 0.059870369 | E23: 0.10501023 | F23: 0.1174465 | G23: 0.039558268 | H23: 0.080546696 | I23: 0.08079033 | J23: 0.12094031 | K23: 0.081782039 | L23: 0.073921466 | M23: 0.055823048
A24: CB-Nakama Re Pte. Ltd. Series 2024-1 Class 1 Reset 2025 | B24: 0.081890928 | C24: 0.061007285 | D24: 0.038041983 | E24: 0.10144529 | F24: 0.1417009 | G24: 0.02713517 | H24: 0.13948727 | I24: 0.07387034 | J24: 0.11412595 | K24: 0.10144529 | L24: 0.076083966 | M24: 0.043765269
A25: CB-Logistics Re Ltd. Series 2024-1 Class A | B25: 0.072013814 | C25: 0.064373577 | D25: 0.070332097 | E25: 0.086565384 | F25: 0.11341982 | G25: 0.062734055 | H25: 0.065853896 | I25: 0.082247618 | J25: 0.077227432 | K25: 0.090739301 | L25: 0.10519655 | M25: 0.10929644
A26: CB-Tomoni Re Pte. Ltd. Series 2022-1 Class B-1 Reset 2025 | B26: 0.013216618 | C26: 0.006608309 | D26: 0.025158196 | E26: 0.046258163 | F26: 0.033041545 | G26: 0.042062563 | H26: 0.076911864 | I26: 0.1453828 | J26: 0.26212679 | K26: 0.18026949 | L26: 0.087004588 | M26: 0.081958949
... A61: CB-Herbie Re Ltd. Series 2025-1 Class A | B61: 0.0070952842 | C61: 0.0042233753 | D61: 0.004373934 | E61: 0.0094153344 | F61: 0.020500193 | G61: 0.034965392 | H61: 0.063936352 | I61: 0.15873245 | J61: 0.25188117 | K61: 0.19329971 | L61: 0.076118701 | M61: 0.082940629

Sheet Port YELT
A1: EventID | B1: Year | C1: Day | D1: Loss | E1: ILSType | F1: Fronting | G1: Peril | H1: Region | I1: Country | J1: SubRegion

Sheet BoundPositions
A4: ILSName | B4: Hedges | C4: ExpirationDate | D4: TTM | E4: Fronting | F4: SecurityInstrument | G4: OccurenceLimit | H4: AggregateLimit | I4: Premium | J4: COMPANYOccurenceLimit | K4: COMPANYAggregateLimit | L4: Quantity | M4: Fronted | N4: CollateralFronted | O4: BondPrice | P4: BondCoupon | Q4: COMPANYShare | R4: BondInitialSpread | S4: BondRedemptionPrice | T4: ROL | U4: Premium | V4: CoTVAR1000 | W4: InvestedAUM | X4: ExpectedLoss | AB4: ActualAUMPercent | AC4: SingleRiskGuideline | AD4: InitialFees | AE4: Expenses | AF4: FrontingFee | AG4: NonModeledAndCOMPANYView | AH4: LossRatio | AI4: CoTVAR100 | AJ4: Return | AK4: ReturnonCoTVAR100 | AL4: CUSIP
A5: CB-3264 Re Ltd. Series 2024-1 Class B Reset 2025 | C5: 47684 | D5: 1459 | F5: Cat Bond | G5: 0 | H5: 0 | I5: 13104000 | J5: 250000.2 | K5: 250000.2 | L5: 250000 | N5: 0 | O5: 111.2 | P5: 0.2184 | Q5: 0.00416667 | R5: 0 | S5: 0 | T5: 0.1684 | U5: 54600.044 | V5: 235648.26 | W5: 278000.22 | X5: 13726.648 | Y5: 54578.208 | Z5: 250000.2 | AA5: 250000.2 | AB5: 0.06250005 | AC5: 0 | AD5: 0 | AE5: 0 | AF5: 0 | AG5: 0 | AH5: 0.25140361 | AI5: 239229.97 | AJ5: 40873.395 | AK5: 0.17085399 | AL5: 88577CAD3
A6: CB-Baldwin Re Ltd. Series 2023-1 Class A Reset 2025 | C6: 47947 | D6: 1722 | F6: Cat Bond | G6: 0 | H6: 0 | I6: 9052122 | J6: 250000 | K6: 250000 | L6: 250000 | N6: 0 | O6: 102.2 | P6: 0.09052122 | Q6: 0.0025 | R6: 0 | S6: 0 | T6: 0.07763305 | U6: 22630.305 | V6: 125000 | W6: 255500 | X6: 4362.4382 | Y6: 31430.038 | Z6: 250000 | AA6: 250000 | AB6: 0.0625 | AC6: 0 | AD6: 0 | AE6: 0 | AF6: 0 | AG6: 0 | AH6: 0.19276975 | AI6: 27500 | AJ6: 18267.867 | AK6: 0.66428607 | AL6: 05826BAB2
A7: CB-Baldwin Re Ltd. Series 2023-1 Class A Reset 2025 | C7: 47947 | D7: 1722 | F7: Cat Bond | G7: 0 | H7: 0 | I7: 9052122 | J7: 500000 | K7: 500000 | L7: 500000 | N7: 0 | O7: 102.2 | P7: 0.09052122 | Q7: 0.005 | R7: 0 | S7: 0 | T7: 0.07763305 | U7: 45260.61 | V7: 250000 | W7: 511000 | X7: 8724.8763 | Y7: 62860.075 | Z7: 500000 | AA7: 500000 | AB7: 0.125 | AC7: 0 | AD7: 0 | AE7: 0 | AF7: 0 | AG7: 0 | AH7: 0.19276975 | AI7: 54999.999 | AJ7: 36535.734 | AK7: 0.66428607 | AL7: 05826BAB2
A8: CB-Bayou Re Ltd. Series 2023-1 Class A Reset 2025 | C8: 47981 | D8: 1756 | F8: Cat Bond | G8: 0 | H8: 0 | I8: 19670546 | J8: 499999.2 | K8: 499999.2 | L8: 500000 | N8: 0 | O8: 104.6 | P8: 0.16392122 | Q8: 0.00416666 | R8: 0 | S8: 0 | T8: 0.09716635 | U8: 81960.479 | V8: 499999.2 | W8: 522999.16 | X8: 12314.934 | Y8: 75270.131 | Z8: 249999.6 | AA8: 249999.6 | AB8: 0.1249998 | AC8: 0 | AD8: 0 | AE8: 0 | AF8: 0 | AG8: 0 | AH8: 0.15025454 | AI8: 483776.62 | AJ8: 69645.545 | AK8: 0.28792439 | AL8: 07304LAA9
A9: CB-Bayou Re Ltd. Series 2023-1 Class B Reset 2025 | C9: 47684 | D9: 1459 | F9: Cat Bond | G9: 0 | H9: 0 | I9: 17178000 | J9: 249999.75 | K9: 249999.75 | L9: 250000 | N9: 0 | O9: 110.85 | P9: 0.22904 | Q9: 0.00333333 | R9: 0 | S9: 0 | T9: 0.17904 | U9: 57259.943 | V9: 249999.75 | W9: 277124.72 | X9: 8938.0549 | Y9: 44491.424 | Z9: 249999.75 | AA9: 249999.75 | AB9: 0.062499937 | AC9: 0 | AD9: 0 | AE9: 0 | AF9: 0 | AG9: 0 | AH9: 0.15609612 | AI9: 247055.54 | AJ9: 48321.888 | AK9: 0.19559119 | AL9: 07304LAB7
A10: CB-Bayou Re Ltd. Series 2024-1 Class A Reset 2025 | C10: 47684 | D10: 1459 | F10: Cat Bond | G10: 0 | H10: 0 | I10: 24344000 | J10: 250000 | K10: 250000 | L10: 250000 | N10: 0 | O10: 107.01 | P10: 0.12172 | Q10: 0.00125 | R10: 0 | S10: 0 | T10: 0.07172 | U10: 30430 | V10: 248217.23 | W10: 267525 | X10: 3175.7687 | Y10: 27158.315 | Z10: 250000 | AA10: 250000 | AB10: 0.0625 | AC10: 0 | AD10: 0 | AE10: 0 | AF10: 0 | AG10: 0 | AH10: 0.10436308 | AI10: 221837.22 | AJ10: 27254.231 | AK10: 0.12285689 | AL10: 07304LAC5
A11: CB-Bayou Re Ltd. Series 2024-1 Class B Reset 2025 | C11: 47684 | D11: 1459 | F11: Cat Bond | G11: 0 | H11: 0 | I11: 16755000 | J11: 249999.75 | K11: 249999.75 | L11: 250000 | N11: 0 | O11: 112.83 | P11: 0.2234 | Q11: 0.00333333 | R11: 0 | S11: 0 | T11: 0.1734 | U11: 55849.944 | V11: 249999.75 | W11: 282074.72 | X11: 8938.0549 | Y11: 44491.424 | Z11: 249999.75 | AA11: 249999.75 | AB11: 0.062499937 | AC11: 0 | AD11: 0 | AE11: 0 | AF11: 0 | AG11: 0 | AH11: 0.16003695 | AI11: 247055.54 | AJ11: 46911.889 | AK11: 0.18988398 | AL11: 07304LAD3
A12: CB-Bayou Re Ltd. Series 2025-1 Class A | C12: 47684 | D12: 1459 | F12: Cat Bond | G12: 0 | H12: 0 | I12: 30352000 | J12: 250000.8 | K12: 250000.8 | L12: 250000 | N12: 0 | O12: 101.15 | P12: 0.1084 | Q12: 0.00089286 | R12: 0 | S12: 0 | T12: 0.0584 | U12: 27100.087 | V12: 250000.8 | W12: 252875.81 | X12: 4574.2205 | Y12: 32563.656 | Z12: 250000.8 | AA12: 250000.8 | AB12: 0.0625002 | AC12: 0 | AD12: 0 | AE12: 0 | AF12: 0 | AG12: 0 | AH12: 0.16878988 | AI12: 231466.18 | AJ12: 22525.866 | AK12: 0.097318177 | AL12: 07304LAE1
A13: CB-Blue Ridge Re Ltd. Series 2023-1 Class A Reset 2025 | C13: 47942 | D13: 1717 | F13: Cat Bond | G13: 0 | H13: 0 | I13: 18504244 | J13: 250000 | K13: 250000 | L13: 250000 | N13: 0 | O13: 102.85 | P13: 0.09252122 | Q13: 0.00125 | R13: 0 | S13: 0 | T13: 0.06542801 | U13: 23130.305 | V13: 64968.745 | W13: 257125 | X13: 5261.3499 | Y13: 34138.577 | Z13: 250000 | AA13: 250000 | AB13: 0.0625 | AC13: 0 | AD13: 0 | AE13: 0 | AF13: 0 | AG13: 0 | AH13: 0.22746565 | AI13: 12621.071 | AJ13: 17868.955 | AK13: 1.4158034 | AL13: 096003AA6
A14: CB-Charles River Re Ltd. Series 2024-1 Class A Reset 2025 | C14: 47968 | D14: 1743 | F14: Cat Bond | G14: 0 | H14: 0 | I14: 14542652 | J14: 500000 | K14: 500000 | L14: 500000 | N14: 0 | O14: 102 | P14: 0.11634122 | Q14: 0.004 | R14: 0 | S14: 0 | T14: 0.10341629 | U14: 58170.61 | V14: 354842.72 | W14: 510000 | X14: 13753.7 | Y14: 76189.314 | Z14: 500000 | AA14: 500000 | AB14: 0.125 | AC14: 0 | AD14: 0 | AE14: 0 | AF14: 0 | AG14: 0 | AH14: 0.23643727 | AI14: 73555.247 | AJ14: 44416.91 | AK14: 0.60385781 | AL14: 159873AA6
A15: CB-Charles River Re Ltd. Series 2024-1 Class A Reset 2025 | C15: 47968 | D15: 1743 | F15: Cat Bond | G15: 0 | H15: 0 | I15: 14542652 | J15: 250000 | K15: 250000 | L15: 250000 | N15: 0 | O15: 102 | P15: 0.11634122 | Q15: 0.002 | R15: 0 | S15: 0 | T15: 0.10341629 | U15: 29085.305 | V15: 177421.36 | W15: 255000 | X15: 6876.85 | Y15: 38094.657 | Z15: 250000 | AA15: 250000 | AB15: 0.0625 | AC15: 0 | AD15: 0 | AE15: 0 | AF15: 0 | AG15: 0 | AH15: 0.23643727 | AI15: 36777.623 | AJ15: 22208.455 | AK15: 0.60385781 | AL15: 159873AA6
A16: CB-Citrus Re Ltd. Series 2023-1 Class B Reset 2025 | C16: 48099 | D16: 1874 | F16: Cat Bond | G16: 0 | H16: 0 | I16: 14618940 | J16: 249999.65 | K16: 249999.65 | L16: 250000 | N16: 0 | O16: 103.85 | P16: 0.12712122 | Q16: 0.00217391 | R16: 0 | S16: 0 | T16: 0.07397631 | U16: 31780.261 | V16: 74999.895 | W16: 259624.64 | X16: 6325.1773 | Y16: 38963.371 | Z16: 249999.65 | AA16: 249999.65 | AB16: 0.062499912 | AC16: 0 | AD16: 0 | AE16: 0 | AF16: 0 | AG16: 0 | AH16: 0.19902849 | AI16: 22499.968 | AJ16: 25455.083 | AK16: 1.1313386 | AL16: 177510AM6
... A62: CB-Wrigley Re Ltd. Series 2023-1 Class B Reset 2025 | C62: 46241 | D62: 22 | F62: Cat Bond | G62: 0 | H62: 150000000 | I62: 15765000 | J62: 250000.5 | K62: 250000.5 | L62: 250000 | N62: 0 | O62: 103.15 | P62: 0.1051 | Q62: 0.00166667 | R62: 0.06682648 | S62: 0 | T62: 0.06387253 | U62: 26275.053 | V62: 0 | W62: 257875.52 | X62: 2083.8866 | Y62: 22268.934 | Z62: 0 | AA62: 250000.5 | AB62: 0.09928988 | AC62: 0 | AD62: 0 | AE62: 0 | AF62: 0 | AG62: 0 | AH62: 0.079310464 | AI62: 24804.643 | AJ62: 24191.166 | AK62: 0.97526767 | AL62: 982533AC5

Sheet Bound Portfolio Report
A7: Sr.No | B7: Name | C7: Issuer | D7: Series | E7: Class | F7: Reset | G7: Renewal | H7: Loss Basis | I7: Cusip ID | J7: NRE_ID | K7: ISINID | L7: AttachProb | M7: ExhaustProb | N7: CurrExchangeFactor | O7: No of Reinstatement | P7: Hedges | Q7: Bound Date | R7: Expiration Date | S7: TTM | T7: Fronting | U7: Security Instrument | V7: Tranche | W7: SponsorTier | X7: ReinRetro | Y7: OccAgg/QS | Z7: layer_group | AA7: Qscore | AB7: Occ Limit (100%) | AC7: Aggregate Limit (100%) | AD7: 100% Premium | AE7: COMPANY Occ Limit | AF7: COMPANY Agg Limit | AG7: Quantity | AH7: Fronted | AI7: Collateral (Fronted) | AJ7: Collateral Premium | AK7: Collateral Fee | AL7: Bond Price @Binding | AM7: Bond Coupon | AN7: Bond Buy or Sell | AO7: Bond Buy Date | AP7: BondSellPrice | AQ7: Bond Sell Date | AR7: COMPANY Share | AS7: Bond Initial Spread | AT7: Bond Redemption | AU7: ROL | AV7: Realised Gain | AW7: Premium | AX7: Co-TVAR 1000 | AY7: Invested AUM | AZ7: Exp. Loss | BA7: SD | BB7: 5 AEP | BC7: 10 AEP | BD7: 20 AEP | BE7: 25 AEP | BF7: 50 AEP | BG7: 75 AEP | BH7: 100 AEP | BI7: 500 AEP | BJ7: Breakeven Probability | BK7: Actual % of AUM | BL7: Single Risk Guideline | BM7: Guideline Check | BN7: Initial Fees | BO7: UW Expenses | BP7: Fronting Fee | BQ7: MaxContLiab | BR7: Non-Modeled + COMPANY View | BS7: Exception Approval | BT7: Loss Ratio | BU7: Co-TVAR 100 | BV7: Return | BW7: Return on Co-TVAR 100 | BX7: Profit (%) | BY7: Quantity Pledged | BZ7: Pledged % | CA7: Avg Rate Change Projection | CB7: ContractWordingReceivedDate | CC7: ContractWordingForwardedtoAONART | CD7: AuthorizationDate | CE7: ConfirmationNoticeDate | CF7: ContractExecutedDate | CG7: TreatyType | CH7: CoverageType
A8: 1 | B8: CB-Baldwin Re Ltd. Series 2023-1 Class A Reset 2025 | D8: 2023-1 | E8: Class A | F8: 2025 | H8: LOD | I8: 05826BAB2 | J8: 0 | L8: 0.0218 | M8: 0 | N8: 1 | O8: 0 | Q8: 46486 | R8: 47947 | S8: 1722 | U8: Cat Bond | V8: Mezz | W8: 1 | AB8: 0 | AC8: 0 | AD8: 9052122 | AE8: 250000 | AF8: 250000 | AG8: 250000 | AI8: 0 | AL8: 102.2 | AM8: 0.09052122 | AN8: Buy | AO8: 46486 | AP8: 0 | AR8: 0.0025 | AS8: 0 | AT8: 0 | AU8: 0.07763305 | AV8: 0 | AW8: 22630.305 | AX8: 125000 | AY8: 255500 | AZ8: 4362.4382 | BA8: 31430.038 | BB8: 0 | BC8: 0 | BD8: 0 | BE8: 0 | BF8: 45891.369 | BG8: 250000 | BH8: 250000 | BI8: 250000 | BJ8: 0.9787 | BK8: 0.0625 | BL8: 0 | BM8: Breached | BN8: 0 | BO8: 0 | BP8: 0 | BQ8: 250000 | BR8: 0 | BS8: 0 | BT8: 0.19276975 | BU8: 27500 | BV8: 18267.867 | BW8: 0.66428607 | BX8: 0.80723025 | BY8: 0 | BZ8: 0 | CA8: 0 | CB8: 46486 | CC8: 46486 | CG8: Indemnity | CH8: Occurrence
A9: 2 | B9: CB-Baldwin Re Ltd. Series 2023-1 Class A Reset 2025 | D9: 2023-1 | E9: Class A | F9: 2025 | H9: LOD | I9: 05826BAB2 | J9: 0 | L9: 0.0218 | M9: 0 | N9: 1 | O9: 0 | Q9: 46486 | R9: 47947 | S9: 1722 | U9: Cat Bond | V9: Mezz | W9: 1 | AB9: 0 | AC9: 0 | AD9: 9052122 | AE9: 500000 | AF9: 500000 | AG9: 500000 | AI9: 0 | AL9: 102.2 | AM9: 0.09052122 | AN9: Buy | AO9: 46486 | AP9: 0 | AR9: 0.005 | AS9: 0 | AT9: 0 | AU9: 0.07763305 | AV9: 0 | AW9: 45260.61 | AX9: 250000 | AY9: 511000 | AZ9: 8724.8763 | BA9: 62860.075 | BB9: 0 | BC9: 0 | BD9: 0 | BE9: 0 | BF9: 91782.737 | BG9: 499999.99 | BH9: 500000 | BI9: 500000 | BJ9: 0.9787 | BK9: 0.125 | BL9: 0 | BM9: Breached | BN9: 0 | BO9: 0 | BP9: 0 | BQ9: 500000 | BR9: 0 | BS9: 0 | BT9: 0.19276975 | BU9: 54999.999 | BV9: 36535.734 | BW9: 0.66428607 | BX9: 0.80723025 | BY9: 0 | BZ9: 0 | CA9: 0 | CB9: 46486 | CC9: 46486 | CG9: Indemnity | CH9: Occurrence
A10: 3 | B10: CB-Gateway Re Ltd. Series 2025-1 Class A | D10: 2025-1 | E10: Class A | H10: LOD | I10: 36779CAQ9 | J10: 0 | L10: 0.0547 | M10: 0 | N10: 1 | O10: 0 | Q10: 46223 | R10: 47684 | S10: 1459 | U10: Cat Bond | V10: Mezz | W10: 1 | AB10: 0 | AC10: 0 | AD10: 11464254 | AE10: 250000 | AF10: 250000 | AG10: 250000 | AI10: 0 | AL10: 107.38 | AM10: 0.14330317 | AN10: Buy | AO10: 46223 | AP10: 0 | AR10: 0.003125 | AS10: 0 | AT10: 0 | AU10: 0.09330317 | AV10: 0 | AW10: 35825.793 | AX10: 233744.33 | AY10: 268450 | AZ10: 8871.454 | BA10: 42643.72 | BB10: 0 | BC10: 0 | BD10: 26901.347 | BE10: 76443.178 | BF10: 250000 | BG10: 250000 | BH10: 250000 | BI10: 250000 | BJ10: 0.9528 | BK10: 0.0625 | BL10: 0 | BM10: Breached | BN10: 0 | BO10: 0 | BP10: 0 | BQ10: 250000 | BR10: 0 | BS10: 0 | BT10: 0.24762757 | BU10: 241763.73 | BV10: 26954.339 | BW10: 0.11149042 | BX10: 0.75237243 | BY10: 0 | BZ10: 0 | CA10: 0 | CB10: 46223 | CC10: 46223 | CG10: Indemnity | CH10: Occurrence
A11: 4 | B11: CB-3264 Re Ltd. Series 2024-1 Class B Reset 2025 | D11: 2024-1 | E11: Class B | F11: 2025 | H11: LOD | I11: 88577CAD3 | J11: 0 | L11: 0.0696 | M11: 0 | N11: 1 | O11: 0 | Q11: 46223 | R11: 47684 | S11: 1459 | U11: Cat Bond | V11: Equity | W11: 1 | AB11: 0 | AC11: 0 | AD11: 13104000 | AE11: 250000.2 | AF11: 250000.2 | AG11: 250000 | AI11: 0 | AL11: 111.2 | AM11: 0.2184 | AN11: Buy | AO11: 46223 | AP11: 0 | AR11: 0.00416667 | AS11: 0 | AT11: 0 | AU11: 0.1684 | AV11: 0 | AW11: 54600.044 | AX11: 235648.26 | AY11: 278000.22 | AZ11: 13726.648 | BA11: 54578.208 | BB11: 0 | BC11: 0 | BD11: 163213.85 | BE11: 250000.2 | BF11: 250000.2 | BG11: 250000.2 | BH11: 250000.2 | BI11: 250000.2 | BJ11: 0.9376 | BK11: 0.06250005 | BL11: 0 | BM11: Breached | BN11: 0 | BO11: 0 | BP11: 0 | BQ11: 250000.2 | BR11: 0 | BS11: 0 | BT11: 0.25140361 | BU11: 239229.97 | BV11: 40873.395 | BW11: 0.17085399 | BX11: 0.74859639 | BY11: 0 | BZ11: 0 | CA11: 0 | CB11: 46223 | CC11: 46223 | CG11: Indemnity | CH11: Occurrence
A12: 5 | B12: CB-Citrus Re Ltd. Series 2023-1 Class B Reset 2025 | D12: 2023-1 | E12: Class B | F12: 2025 | H12: LOD | I12: 177510AM6 | J12: 0 | L12: 0.0263 | M12: 0.0239 | N12: 1 | O12: 0 | Q12: 46638 | R12: 48099 | S12: 1874 | U12: Cat Bond | V12: Mezz | W12: 1 | AB12: 0 | AC12: 0 | AD12: 14618940 | AE12: 249999.65 | AF12: 249999.65 | AG12: 250000 | AI12: 0 | AL12: 103.85 | AM12: 0.12712122 | AN12: Buy | AO12: 46638 | AP12: 0 | AR12: 0.00217391 | AS12: 0 | AT12: 0 | AU12: 0.07397631 | AV12: 0 | AW12: 31780.261 | AX12: 74999.895 | AY12: 259624.64 | AZ12: 6325.1773 | BA12: 38963.371 | BB12: 0 | BC12: 0 | BD12: 0 | BE12: 0 | BF12: 249999.65 | BG12: 249999.65 | BH12: 249999.65 | BI12: 249999.65 | BJ12: 0.9739 | BK12: 0.062499912 | BL12: 0 | BM12: Breached | BN12: 0 | BO12: 0 | BP12: 0 | BQ12: 249999.65 | BR12: 0 | BS12: 0 | BT12: 0.19902849 | BU12: 22499.968 | BV12: 25455.083 | BW12: 1.1313386 | BX12: 0.80097151 | BY12: 0 | BZ12: 0 | CA12: 0 | CB12: 46638 | CC12: 46638 | CG12: Indemnity | CH12: Occurrence
A13: 6 | B13: CB-Blue Ridge Re Ltd. Series 2023-1 Class A Reset 2025 | D13: 2023-1 | E13: Class A | F13: 2025 | H13: LOD | I13: 096003AA6 | J13: 0 | L13: 0.028 | M13: 0.016 | N13: 1 | O13: 0 | Q13: 46481 | R13: 47942 | S13: 1717 | U13: Cat Bond | V13: Mezz | W13: 1 | AB13: 0 | AC13: 0 | AD13: 18504244 | AE13: 250000 | AF13: 250000 | AG13: 250000 | AI13: 0 | AL13: 102.85 | AM13: 0.09252122 | AN13: Buy | AO13: 46481 | AP13: 0 | AR13: 0.00125 | AS13: 0 | AT13: 0 | AU13: 0.06542801 | AV13: 0 | AW13: 23130.305 | AX13: 64968.745 | AY13: 257125 | AZ13: 5261.3499 | BA13: 34138.577 | BB13: 0 | BC13: 0 | BD13: 0 | BE13: 0 | BF13: 135707.53 | BG13: 250000 | BH13: 250000 | BI13: 250000 | BJ13: 0.9736 | BK13: 0.0625 | BL13: 0 | BM13: Breached | BN13: 0 | BO13: 0 | BP13: 0 | BQ13: 250000 | BR13: 0 | BS13: 0 | BT13: 0.22746565 | BU13: 12621.071 | BV13: 17868.955 | BW13: 1.4158034 | BX13: 0.77253435 | BY13: 0 | BZ13: 0 | CA13: 0 | CB13: 46481 | CC13: 46481 | CG13: Indemnity | CH13: Occurrence
A14: 7 | B14: CB-Bayou Re Ltd. Series 2023-1 Class A Reset 2025 | D14: 2023-1 | E14: Class A | F14: 2025 | H14: LOD | I14: 07304LAA9 | J14: 0 | L14: 0.0284 | M14: 0.0212 | N14: 1 | O14: 0 | Q14: 46520 | R14: 47981 | S14: 1756 | U14: Cat Bond | V14: Mezz | W14: 1 | AB14: 0 | AC14: 0 | AD14: 19670546 | AE14: 249999.6 | AF14: 249999.6 | AG14: 250000 | AI14: 0 | AL14: 104.6 | AM14: 0.16392122 | AN14: Buy | AO14: 46520 | AP14: 0 | AR14: 0.00208333 | AS14: 0 | AT14: 0 | AU14: 0.09716635 | AV14: 0 | AW14: 40980.239 | AX14: 249999.6 | AY14: 261499.58 | AZ14: 6157.467 | BA14: 37635.065 | BB14: 0 | BC14: 0 | BD14: 0 | BE14: 0 | BF14: 249999.6 | BG14: 249999.6 | BH14: 249999.6 | BI14: 249999.6 | BJ14: 0.9725 | BK14: 0.0624999 | BL14: 0 | BM14: Breached | BN14: 0 | BO14: 0 | BP14: 0 | BQ14: 249999.6 | BR14: 0 | BS14: 0 | BT14: 0.15025454 | BU14: 241888.31 | BV14: 34822.772 | BW14: 0.1439622 | BX14: 0.84974546 | BY14: 0 | BZ14: 0 | CA14: 0 | CB14: 46520 | CC14: 46520 | CG14: Indemnity | CH14: Occurrence
A15: 8 | B15: CB-Bayou Re Ltd. Series 2023-1 Class A Reset 2025 | D15: 2023-1 | E15: Class A | F15: 2025 | H15: LOD | I15: 07304LAA9 | J15: 0 | L15: 0.0284 | M15: 0.0212 | N15: 1 | O15: 0 | Q15: 46520 | R15: 47981 | S15: 1756 | U15: Cat Bond | V15: Mezz | W15: 1 | AB15: 0 | AC15: 0 | AD15: 19670546 | AE15: 249999.6 | AF15: 249999.6 | AG15: 250000 | AI15: 0 | AL15: 104.6 | AM15: 0.16392122 | AN15: Buy | AO15: 46520 | AP15: 0 | AR15: 0.00208333 | AS15: 0 | AT15: 0 | AU15: 0.09716635 | AV15: 0 | AW15: 40980.239 | AX15: 249999.6 | AY15: 261499.58 | AZ15: 6157.467 | BA15: 37635.065 | BB15: 0 | BC15: 0 | BD15: 0 | BE15: 0 | BF15: 249999.6 | BG15: 249999.6 | BH15: 249999.6 | BI15: 249999.6 | BJ15: 0.9725 | BK15: 0.0624999 | BL15: 0 | BM15: Breached | BN15: 0 | BO15: 0 | BP15: 0 | BQ15: 249999.6 | BR15: 0 | BS15: 0 | BT15: 0.15025454 | BU15: 241888.31 | BV15: 34822.772 | BW15: 0.1439622 | BX15: 0.84974546 | BY15: 0 | BZ15: 0 | CA15: 0 | CB15: 46520 | CC15: 46520 | CG15: Indemnity | CH15: Occurrence
A16: 9 | B16: CB-Bayou Re Ltd. Series 2023-1 Class B Reset 2025 | D16: 2023-1 | E16: Class B | F16: 2025 | H16: LOD | I16: 07304LAB7 | J16: 0 | L16: 0.0453 | M16: 0.0286 | N16: 1 | O16: 0 | Q16: 46223 | R16: 47684 | S16: 1459 | U16: Cat Bond | V16: Equity | W16: 1 | AB16: 0 | AC16: 0 | AD16: 17178000 | AE16: 249999.75 | AF16: 249999.75 | AG16: 250000 | AI16: 0 | AL16: 110.85 | AM16: 0.22904 | AN16: Buy | AO16: 46223 | AP16: 0 | AR16: 0.00333333 | AS16: 0 | AT16: 0 | AU16: 0.17904 | AV16: 0 | AW16: 57259.943 | AX16: 249999.75 | AY16: 277124.72 | AZ16: 8938.0549 | BA16: 44491.424 | BB16: 0 | BC16: 0 | BD16: 0 | BE16: 55697.168 | BF16: 249999.75 | BG16: 249999.75 | BH16: 249999.75 | BI16: 249999.75 | BJ16: 0.9601 | BK16: 0.062499937 | BL16: 0 | BM16: Breached | BN16: 0 | BO16: 0 | BP16: 0 | BQ16: 249999.75 | BR16: 0 | BS16: 0 | BT16: 0.15609612 | BU16: 247055.54 | BV16: 48321.888 | BW16: 0.19559119 | BX16: 0.84390388 | BY16: 0 | BZ16: 0 | CA16: 0 | CB16: 46223 | CC16: 46223 | CG16: Indemnity | CH16: Occurrence
A17: 10 | B17: CB-Purple Re Ltd. Series 2024-1 Class A Reset 2025 | D17: 2024-1 | E17: Class A | F17: 2025 | H17: LOD | I17: 74639NAC7 | J17: 0 | L17: 0.02 | M17: 0 | N17: 1 | O17: 0 | Q17: 46491 | R17: 47952 | S17: 1727 | U17: Cat Bond | V17: Equity | W17: 1 | AB17: 0 | AC17: 0 | AD17: 27569056 | AE17: 250000.8 | AF17: 250000.8 | AG17: 250000 | AI17: 0 | AL17: 102.6 | AM17: 0.13128122 | AN17: Buy | AO17: 46491 | AP17: 0 | AR17: 0.00119048 | AS17: 0 | AT17: 0 | AU17: 0.11496279 | AV17: 0 | AW17: 32820.41 | AX17: 2244.4372 | AY17: 256500.82 | AZ17: 4326.6512 | BA17: 31900.15 | BB17: 0 | BC17: 0 | BD17: 0 | BE17: 0 | BF17: 4762.8988 | BG17: 250000.8 | BH17: 250000.8 | BI17: 250000.8 | BJ17: 0.9809 | BK17: 0.0625002 | BL17: 0 | BM17: Breached | BN17: 0 | BO17: 0 | BP17: 0 | BQ17: 250000.8 | BR17: 0 | BS17: 0 | BT17: 0.13182807 | BU17: 15643.036 | BV17: 28493.759 | BW17: 1.821498 | BX17: 0.86817193 | BY17: 0 | BZ17: 0 | CA17: 0 | CB17: 46491 | CC17: 46491 | CG17: Indemnity | CH17: Occurrence
A18: 11 | B18: CB-Purple Re Ltd. Series 2023-2 Class A Reset 2025 | D18: 2023-2 | E18: Class A | F18: 2025 | H18: LOD | I18: 74639NAB9 | J18: 0 | L18: 0.022 | M18: 0 | N18: 1 | O18: 0 | Q18: 46638 | R18: 48099 | S18: 1874 | U18: Cat Bond | V18: Equity | W18: 1 | AB18: 0 | AC18: 0 | AD18: 14582122 | AE18: 250000 | AF18: 250000 | AG18: 250000 | AI18: 0 | AL18: 102.9 | AM18: 0.14582122 | AN18: Buy | AO18: 46638 | AP18: 0 | AR18: 0.0025 | AS18: 0 | AT18: 0 | AU18: 0.10549349 | AV18: 0 | AW18: 36455.305 | AX18: 25000 | AY18: 257250 | AZ18: 5230.969 | BA18: 35499.775 | BB18: 0 | BC18: 0 | BD18: 0 | BE18: 0 | BF18: 250000 | BG18: 250000 | BH18: 250000 | BI18: 250000 | BJ18: 0.9785 | BK18: 0.0625 | BL18: 0 | BM18: Breached | BN18: 0 | BO18: 0 | BP18: 0 | BQ18: 250000 | BR18: 0 | BS18: 0 | BT18: 0.14348992 | BU18: 20000 | BV18: 31224.336 | BW18: 1.5612168 | BX18: 0.85651008 | BY18: 0 | BZ18: 0 | CA18: 0 | CB18: 46638 | CC18: 46638 | CG18: Indemnity | CH18: Occurrence
A19: 12 | B19: CB-Bayou Re Ltd. Series 2024-1 Class A Reset 2025 | D19: 2024-1 | E19: Class A | F19: 2025 | H19: LOD | I19: 07304LAC5 | J19: 0 | L19: 0.0151 | M19: 0 | N19: 1 | O19: 0 | Q19: 46223 | R19: 47684 | S19: 1459 | U19: Cat Bond | V19: Mezz | W19: 1 | AB19: 0 | AC19: 0 | AD19: 24344000 | AE19: 250000 | AF19: 250000 | AG19: 250000 | AI19: 0 | AL19: 107.01 | AM19: 0.12172 | AN19: Buy | AO19: 46223 | AP19: 0 | AR19: 0.00125 | AS19: 0 | AT19: 0 | AU19: 0.07172 | AV19: 0 | AW19: 30430 | AX19: 248217.23 | AY19: 267525 | AZ19: 3175.7687 | BA19: 27158.315 | BB19: 0 | BC19: 0 | BD19: 0 | BE19: 0 | BF19: 0 | BG19: 89132.741 | BH19: 250000 | BI19: 250000 | BJ19: 0.9854 | BK19: 0.0625 | BL19: 0 | BM19: Breached | BN19: 0 | BO19: 0 | BP19: 0 | BQ19: 250000 | BR19: 0 | BS19: 0 | BT19: 0.10436308 | BU19: 221837.22 | BV19: 27254.231 | BW19: 0.12285689 | BX19: 0.89563692 | BY19: 0 | BZ19: 0 | CA19: 0 | CB19: 46223 | CC19: 46223 | CG19: Indemnity | CH19: Occurrence
A20: 13 | B20: CB-Bayou Re Ltd. Series 2024-1 Class B Reset 2025 | D20: 2024-1 | E20: Class B | F20: 2025 | H20: LOD | I20: 07304LAD3 | J20: 0 | L20: 0.0453 | M20: 0 | N20: 1 | O20: 0 | Q20: 46223 | R20: 47684 | S20: 1459 | U20: Cat Bond | V20: Equity | W20: 1 | AB20: 0 | AC20: 0 | AD20: 16755000 | AE20: 249999.75 | AF20: 249999.75 | AG20: 250000 | AI20: 0 | AL20: 112.83 | AM20: 0.2234 | AN20: Buy | AO20: 46223 | AP20: 0 | AR20: 0.00333333 | AS20: 0 | AT20: 0 | AU20: 0.1734 | AV20: 0 | AW20: 55849.944 | AX20: 249999.75 | AY20: 282074.72 | AZ20: 8938.0549 | BA20: 44491.424 | BB20: 0 | BC20: 0 | BD20: 0 | BE20: 55697.168 | BF20: 249999.75 | BG20: 249999.75 | BH20: 249999.75 | BI20: 249999.75 | BJ20: 0.9601 | BK20: 0.062499937 | BL20: 0 | BM20: Breached | BN20: 0 | BO20: 0 | BP20: 0 | BQ20: 249999.75 | BR20: 0 | BS20: 0 | BT20: 0.16003695 | BU20: 247055.54 | BV20: 46911.889 | BW20: 0.18988398 | BX20: 0.83996305 | BY20: 0 | BZ20: 0 | CA20: 0 | CB20: 46223 | CC20: 46223 | CG20: Indemnity | CH20: Occurrence
A21: 14 | B21: CB-Bayou Re Ltd. Series 2025-1 Class A | D21: 2025-1 | E21: Class A | H21: LOD | I21: 07304LAE1 | J21: 0 | L21: 0.0212 | M21: 0 | N21: 1 | O21: 0 | Q21: 46223 | R21: 47684 | S21: 1459 | U21: Cat Bond | V21: Mezz | W21: 1 | AB21: 0 | AC21: 0 | AD21: 30352000 | AE21: 250000.8 | AF21: 250000.8 | AG21: 250000 | AI21: 0 | AL21: 101.15 | AM21: 0.1084 | AN21: Buy | AO21: 46223 | AP21: 0 | AR21: 0.00089286 | AS21: 0 | AT21: 0 | AU21: 0.0584 | AV21: 0 | AW21: 27100.087 | AX21: 250000.8 | AY21: 252875.81 | AZ21: 4574.2205 | BA21: 32563.656 | BB21: 0 | BC21: 0 | BD21: 0 | BE21: 0 | BF21: 56345.449 | BG21: 250000.8 | BH21: 250000.8 | BI21: 250000.8 | BJ21: 0.9794 | BK21: 0.0625002 | BL21: 0 | BM21: Breached | BN21: 0 | BO21: 0 | BP21: 0 | BQ21: 250000.8 | BR21: 0 | BS21: 0 | BT21: 0.16878988 | BU21: 231466.18 | BV21: 22525.866 | BW21: 0.097318177 | BX21: 0.83121012 | BY21: 0 | BZ21: 0 | CA21: 0 | CB21: 46223 | CC21: 46223 | CG21: Indemnity | CH21: Occurrence
A22: 15 | B22: CB-Charles River Re Ltd. Series 2024-1 Class A Reset 2025 | D22: 2024-1 | E22: Class A | F22: 2025 | H22: LOD | I22: 159873AA6 | J22: 0 | L22: 0.0397 | M22: 0 | N22: 1 | O22: 0 | Q22: 46507 | R22: 47968 | S22: 1743 | U22: Cat Bond | V22: Equity | W22: 1 | AB22: 0 | AC22: 0 | AD22: 14542652 | AE22: 250000 | AF22: 250000 | AG22: 250000 | AI22: 0 | AL22: 102 | AM22: 0.11634122 | AN22: Buy | AO22: 46507 | AP22: 0 | AR22: 0.002 | AS22: 0 | AT22: 0 | AU22: 0.10341629 | AV22: 0 | AW22: 29085.305 | AX22: 177421.36 | AY22: 255000 | AZ22: 6876.85 | BA22: 38094.657 | BB22: 0 | BC22: 0 | BD22: 0 | BE22: 0 | BF22: 225035.29 | BG22: 250000 | BH22: 250000 | BI22: 250000 | BJ22: 0.9643 | BK22: 0.0625 | BL22: 0 | BM22: Breached | BN22: 0 | BO22: 0 | BP22: 0 | BQ22: 250000 | BR22: 0 | BS22: 0 | BT22: 0.23643727 | BU22: 36777.623 | BV22: 22208.455 | BW22: 0.60385781 | BX22: 0.76356273 | BY22: 0 | BZ22: 0 | CA22: 0 | CB22: 46507 | CC22: 46507 | CG22: Indemnity | CH22: Occurrence
A23: 16 | B23: CB-Charles River Re Ltd. Series 2024-1 Class A Reset 2025 | D23: 2024-1 | E23: Class A | F23: 2025 | H23: LOD | I23: 159873AA6 | J23: 0 | L23: 0.0397 | M23: 0 | N23: 1 | O23: 0 | Q23: 46507 | R23: 47968 | S23: 1743 | U23: Cat Bond | V23: Equity | W23: 1 | AB23: 0 | AC23: 0 | AD23: 14542652 | AE23: 500000 | AF23: 500000 | AG23: 500000 | AI23: 0 | AL23: 102 | AM23: 0.11634122 | AN23: Buy | AO23: 46507 | AP23: 0 | AR23: 0.004 | AS23: 0 | AT23: 0 | AU23: 0.10341629 | AV23: 0 | AW23: 58170.61 | AX23: 354842.72 | AY23: 510000 | AZ23: 13753.7 | BA23: 76189.314 | BB23: 0 | BC23: 0 | BD23: 0 | BE23: 0 | BF23: 450070.58 | BG23: 500000 | BH23: 500000 | BI23: 500000 | BJ23: 0.9643 | BK23: 0.125 | BL23: 0 | BM23: Breached | BN23: 0 | BO23: 0 | BP23: 0 | BQ23: 500000 | BR23: 0 | BS23: 0 | BT23: 0.23643727 | BU23: 73555.247 | BV23: 44416.91 | BW23: 0.60385781 | BX23: 0.76356273 | BY23: 0 | BZ23: 0 | CA23: 0 | CB23: 46507 | CC23: 46507 | CG23: Indemnity | CH23: Occurrence
A24: 17 | B24: CB-Gateway Re Ltd. Series 2023-1 Class A Reset 2025 | D24: 2023-1 | E24: Class A | F24: 2025 | H24: LOD | I24: 36779CAC0 | J24: 0 | L24: 0.047 | M24: 0 | N24: 1 | O24: 0 | Q24: 46223 | R24: 47684 | S24: 1459 | U24: Cat Bond | V24: Equity | W24: 1 | AB24: 0 | AC24: 0 | AD24: 53318697 | AE24: 249999 | AF24: 249999 | AG24: 250000 | AI24: 0 | AL24: 104.45 | AM24: 0.17772899 | AN24: Buy | AO24: 46223 | AP24: 0 | AR24: 0.00083333 | AS24: 0 | AT24: 0 | AU24: 0.12772899 | AV24: 0 | AW24: 44432.07 | AX24: 233555.66 | AY24: 261123.96 | AZ24: 7755.2634 | BA24: 40066.635 | BB24: 0 | BC24: 0 | BD24: 0 | BE24: 43574.494 | BF24: 249999 | BG24: 249999 | BH24: 249999 | BI24: 249999 | BJ24: 0.9601 | BK24: 0.06249975 | BL24: 0 | BM24: Breached | BN24: 0 | BO24: 0 | BP24: 0 | BQ24: 249999 | BR24: 0 | BS24: 0 | BT24: 0.17454202 | BU24: 230980.65 | BV24: 36676.806 | BW24: 0.15878735 | BX24: 0.82545798 | BY24: 0 | BZ24: 0 | CA24: 0 | CB24: 46223 | CC24: 46223 | CG24: Indemnity | CH24: Occurrence
A25: 18 | B25: CB-Gateway Re Ltd. Series 2023-1 Class B Reset 2025 | D25: 2023-1 | E25: Class B | F25: 2025 | H25: LOD | I25: 36779CAD8 | J25: 0 | L25: 0.0686 | M25: 0 | N25: 1 | O25: 0 | Q25: 46223 | R25: 47684 | S25: 1459 | U25: Cat Bond | V25: Equity | W25: 1 | AB25: 0 | AC25: 0 | AD25: 13667500 | AE25: 249999.75 | AF25: 249999.75 | AG25: 250000 | AI25: 0 | AL25: 106.74 | AM25: 0.2485 | AN25: Buy | AO25: 46223 | AP25: 0 | AR25: 0.00454545 | AS25: 0 | AT25: 0 | AU25: 0.1985 | AV25: 0 | AW25: 62124.938 | AX25: 249999.75 | AY25: 266849.73 | AZ25: 14224.944 | BA25: 55958.534 | BB25: 0 | BC25: 0 | BD25: 215926.27 | BE25: 249999.75 | BF25: 249999.75 | BG25: 249999.75 | BH25: 249999.75 | BI25: 249999.75 | BJ25: 0.9378 | BK25: 0.062499938 | BL25: 0 | BM25: Breached | BN25: 0 | BO25: 0 | BP25: 0 | BQ25: 249999.75 | BR25: 0 | BS25: 0 | BT25: 0.22897317 | BU25: 241323.55 | BV25: 47899.994 | BW25: 0.19848868 | BX25: 0.77102683 | BY25: 0 | BZ25: 0 | CA25: 0 | CB25: 46223 | CC25: 46223 | CG25: Indemnity | CH25: Occurrence
A26: 19 | B26: CB-Montoya Re Ltd. Series 2025-1 Class B Reset 2025 | D26: 2025-1 | E26: Class B | F26: 2025 | H26: LOD | I26: 613752AE4 | J26: 0 | L26: 0.0334 | M26: 0.0313 | N26: 1 | O26: 0 | Q26: 46481 | R26: 47942 | S26: 1717 | U26: Cat Bond | V26: Equity | W26: 1 | AB26: 0 | AC26: 0 | AD26: 3183636.6 | AE26: 249999.9 | AF26: 249999.9 | AG26: 250000 | AI26: 0 | AL26: 100.2 | AM26: 0.10612122 | AN26: Buy | AO26: 46481 | AP26: 0 | AR26: 0.00833333 | AS26: 0 | AT26: 0 | AU26: 0.10523115 | AV26: 0 | AW26: 26530.294 | AX26: 199999.92 | AY26: 250499.9 | AZ26: 7224.1726 | BA26: 40913.053 | BB26: 0 | BC26: 0 | BD26: 0 | BE26: 0 | BF26: 249999.9 | BG26: 249999.9 | BH26: 249999.9 | BI26: 249999.9 | BJ26: 0.9684 | BK26: 0.062499975 | BL26: 0 | BM26: Breached | BN26: 0 | BO26: 0 | BP26: 0 | BQ26: 249999.9 | BR26: 0 | BS26: 0 | BT26: 0.272299 | BU26: 89422.452 | BV26: 19306.122 | BW26: 0.21589792 | BX26: 0.727701 | BY26: 0 | BZ26: 0 | CA26: 0 | CB26: 46481 | CC26: 46481 | CG26: Indemnity | CH26: Occurrence
A27: 20 | B27: CB-Nakama Re Ltd. Series 2023-1 Class 2 Reset 2025 | D27: 2023-1 | E27: Class 2 | F27: 2025 | H27: LOD | I27: 62983QAP8 | J27: 0 | L27: 0.017 | M27: 0.0143 | N27: 1 | O27: 0 | Q27: 45917 | R27: 47378 | S27: 1153 | U27: Cat Bond | V27: Mezz | W27: 1 | AB27: 0 | AC27: 0 | AD27: 11692875 | AE27: 250000.5 | AF27: 250000.5 | AG27: 250000 | AI27: 0 | AL27: 104.5 | AM27: 0.0779525 | AN27: Buy | AO27: 45917 | AP27: 0 | AR27: 0.00166667 | AS27: 0 | AT27: 0 | AU27: 0.06168451 | AV27: 0 | AW27: 19488.164 | AX27: 0 | AY27: 261250.52 | AZ27: 3849.7341 | BA27: 30359.382 | BB27: 0 | BC27: 0 | BD27: 0 | BE27: 0 | BF27: 0 | BG27: 250000.5 | BH27: 250000.5 | BI27: 250000.5 | BJ27: 0.9835 | BK27: 0.010416688 | BL27: 0 | BM27: Breached | BN27: 0 | BO27: 0 | BP27: 0 | BQ27: 250000.5 | BR27: 0 | BS27: 0 | BT27: 0.19754217 | BU27: 10000.02 | BV27: 15638.43 | BW27: 1.5638399 | BX27: 0.80245783 | BY27: 0 | BZ27: 0 | CA27: 0 | CB27: 45917 | CC27: 45917 | CG27: Indemnity | CH27: Occurrence
A28: 21 | B28: CB-Nakama Re Pte. Ltd. Series 2024-1 Class 1 Reset 2025 | D28: 2024-1 | E28: Class 1 | F28: 2025 | H28: LOD | I28: 62984JAC2 | J28: 0 | L28: 0.0081 | M28: 0.0077 | N28: 1 | O28: 0 | Q28: 45749 | R28: 47210 | S28: 985 | U28: Cat Bond | V28: Mezz | W28: 1 | AB28: 0 | AC28: 0 | AD28: 9226080 | AE28: 250000.5 | AF28: 250000.5 | AG28: 250000 | AI28: 0 | AL28: 101 | AM28: 0.0615072 | AN28: Buy | AO28: 45749 | AP28: 0 | AR28: 0.00166667 | AS28: 0 | AT28: 0 | AU28: 0.05611469 | AV28: 0 | AW28: 15376.831 | AX28: 0 | AY28: 252500.51 | AZ28: 1971.5093 | BA28: 22005.248 | BB28: 0 | BC28: 0 | BD28: 0 | BE28: 0 | BF28: 0 | BG28: 0 | BH28: 0 | BI28: 250000.5 | BJ28: 0.9919 | BK28: 0.010416688 | BL28: 0 | BM28: Breached | BN28: 0 | BO28: 0 | BP28: 0 | BQ28: 250000.5 | BR28: 0 | BS28: 0 | BT28: 0.12821298 | BU28: 7500.015 | BV28: 13405.321 | BW28: 1.7873726 | BX28: 0.87178702 | BY28: 0 | BZ28: 0 | CA28: 0 | CB28: 45749 | CC28: 45749 | CG28: Indemnity | CH28: Occurrence
A29: 22 | B29: CB-Logistics Re Ltd. Series 2024-1 Class A | D29: 2024-1 | E29: Class A | H29: LOD | I29: 54143LAB4 | J29: 0 | L29: 0.0296 | M29: 0.0215 | N29: 1 | O29: 0 | Q29: 45797 | R29: 47258 | S29: 1033 | U29: Cat Bond | V29: Mezz | W29: 1 | AB29: 0 | AC29: 0 | AD29: 9357500 | AE29: 250000.1 | AF29: 250000.1 | AG29: 250000 | AI29: 0 | AL29: 101.85 | AM29: 0.0985 | AN29: Buy | AO29: 45797 | AP29: 0 | AR29: 0.00263158 | AS29: 0 | AT29: 0 | AU29: 0.09311324 | AV29: 0 | AW29: 24625.01 | AX29: 0 | AY29: 254625.1 | AZ29: 6291.3599 | BA29: 38089.307 | BB29: 0 | BC29: 0 | BD29: 0 | BE29: 0 | BF29: 250000.1 | BG29: 250000.1 | BH29: 250000.1 | BI29: 250000.1 | BJ29: 0.9713 | BK29: 0.010416671 | BL29: 0 | BM29: Breached | BN29: 0 | BO29: 0 | BP29: 0 | BQ29: 250000.1 | BR29: 0 | BS29: 0 | BT29: 0.2554866 | BU29: 34881.022 | BV29: 18333.65 | BW29: 0.5256053 | BX29: 0.7445134 | BY29: 0 | BZ29: 0 | CA29: 0 | CB29: 45797 | CC29: 45797 | CG29: Indemnity | CH29: Occurrence
A30: 23 | B30: CB-Tomoni Re Pte. Ltd. Series 2022-1 Class B-1 Reset 2025 | D30: 2022-1 | E30: Class B-1 | F30: 2025 | H30: LOD | I30: 89009PAB4 | J30: 0 | L30: 0.0159 | M30: 0 | N30: 1 | O30: 0 | Q30: 45751 | R30: 47212 | S30: 987 | U30: Cat Bond | V30: Mezz | W30: 1 | AB30: 0 | AC30: 0 | AD30: 8040000 | AE30: 249999.6 | AF30: 249999.6 | AG30: 250000 | AI30: 0 | AL30: 101 | AM30: 0.067 | AN30: Buy | AO30: 45751 | AP30: 0 | AR30: 0.00208333 | AS30: 0 | AT30: 0 | AU30: 0.0596383 | AV30: 0 | AW30: 16749.973 | AX30: 0 | AY30: 252499.6 | AZ30: 3783.1095 | BA30: 30259.525 | BB30: 0 | BC30: 0 | BD30: 0 | BE30: 0 | BF30: 0 | BG30: 249999.6 | BH30: 249999.6 | BI30: 249999.6 | BJ30: 0.9843 | BK30: 0.01041665 | BL30: 0 | BM30: Breached | BN30: 0 | BO30: 0 | BP30: 0 | BQ30: 249999.6 | BR30: 0 | BS30: 0 | BT30: 0.22585764 | BU30: 2499.996 | BV30: 12966.864 | BW30: 5.1867538 | BX30: 0.77414236 | BY30: 0 | BZ30: 0 | CA30: 0 | CB30: 45751 | CC30: 45751 | CG30: Indemnity | CH30: Occurrence
A31: 24 | B31: CB-Charles River Re Ltd. Series 2024-1 Class A Reset 2025 | D31: 2024-1 | E31: Class A | F31: 2025 | H31: LOD | I31: 159873AA6 | J31: 0 | L31: 0.0397 | M31: 0 | N31: 1 | O31: 0 | Q31: 45777 | R31: 47238 | S31: 1013 | U31: Cat Bond | V31: Equity | W31: 1 | AB31: 0 | AC31: 0 | AD31: 14377500 | AE31: 250000 | AF31: 250000 | AG31: 250000 | AI31: 0 | AL31: 102 | AM31: 0.11502 | AN31: Buy | AO31: 45777 | AP31: 0 | AR31: 0.002 | AS31: 0 | AT31: 0 | AU31: 0.10692274 | AV31: 0 | AW31: 28755 | AX31: 101619.05 | AY31: 255000 | AZ31: 6876.85 | BA31: 38094.657 | BB31: 0 | BC31: 0 | BD31: 0 | BE31: 0 | BF31: 225035.29 | BG31: 250000 | BH31: 250000 | BI31: 250000 | BJ31: 0.9643 | BK31: 0.010416667 | BL31: 0 | BM31: Breached | BN31: 0 | BO31: 0 | BP31: 0 | BQ31: 250000 | BR31: 0 | BS31: 0 | BT31: 0.23915319 | BU31: 93138.4 | BV31: 21878.15 | BW31: 0.23489935 | BX31: 0.76084681 | BY31: 0 | BZ31: 0 | CA31: 0 | CB31: 45777 | CC31: 45777 | CG31: Indemnity | CH31: Occurrence
A32: 25 | B32: CB-Maschpark Re Ltd. Series 2024-1 Class A | D32: 2024-1 | E32: Class A | H32: LOD | I32: 574591AA1 | J32: 0 | L32: 0.0113 | M32: 0 | N32: 1 | O32: 0 | Q32: 45756 | R32: 47217 | S32: 992 | U32: Cat Bond | V32: Mezz | W32: 1 | AB32: 0 | AC32: 0 | AD32: 7350000 | AE32: 250000 | AF32: 250000 | AG32: 250000 | AI32: 0 | AL32: 101.6 | AM32: 0.0735 | AN32: Buy | AO32: 45756 | AP32: 0 | AR32: 0.0025 | AS32: 0 | AT32: 0 | AU32: 0.06996812 | AV32: 0 | AW32: 18375 | AX32: 0 | AY32: 254000 | AZ32: 2306.25 | BA32: 22853.282 | BB32: 0 | BC32: 0 | BD32: 0 | BE32: 0 | BF32: 0 | BG32: 0 | BH32: 62500 | BI32: 250000 | BJ32: 0.9887 | BK32: 0.010416667 | BL32: 0 | BM32: Breached | BN32: 0 | BO32: 0 | BP32: 0 | BQ32: 250000 | BR32: 0 | BS32: 0 | BT32: 0.1255102 | BU32: 2500 | BV32: 16068.75 | BW32: 6.4275 | BX32: 0.8744898 | BY32: 0 | BZ32: 0 | CA32: 0 | CB32: 45756 | CC32: 45756 | CG32: Indemnity | CH32: Occurrence
A33: 26 | B33: CB-Commonwealth Re Ltd. Series 2023-1 Class A Reset 2025 | D33: 2023-1 | E33: Class A | F33: 2025 | H33: LOD | I33: 203235AB2 | J33: 0 | L33: 0.0068 | M33: 0 | N33: 1 | O33: 0 | Q33: 45775 | R33: 47236 | S33: 1011 | U33: Cat Bond | V33: Mezz | W33: 1 | AB33: 0 | AC33: 0 | AD33: 11677500 | AE33: 250000.5 | AF33: 250000.5 | AG33: 250000 | AI33: 0 | AL33: 101.15 | AM33: 0.07785 | AN33: Buy | AO33: 45775 | AP33: 0 | AR33: 0.00166667 | AS33: 0 | AT33: 0 | AU33: 0.06993917 | AV33: 0 | AW33: 19462.539 | AX33: 75000.15 | AY33: 252875.51 | AZ33: 1609.9948 | BA33: 19799.755 | BB33: 0 | BC33: 0 | BD33: 0 | BE33: 0 | BF33: 0 | BG33: 0 | BH33: 0 | BI33: 250000.5 | BJ33: 0.9933 | BK33: 0.010416688 | BL33: 0 | BM33: Breached | BN33: 0 | BO33: 0 | BP33: 0 | BQ33: 250000.5 | BR33: 0 | BS33: 0 | BT33: 0.082722751 | BU33: 76619.15 | BV33: 17852.544 | BW33: 0.23300368 | BX33: 0.91727725 | BY33: 0 | BZ33: 0 | CA33: 0 | CB33: 45775 | CC33: 45775 | CG33: Indemnity | CH33: Occurrence
A34: 27 | B34: CB-Everglades Re II Ltd. Series 2024-1 Class A Reset 2025 | D34: 2024-1 | E34: Class A | F34: 2025 | H34: LOD | I34: 30014LAM6 | J34: 0 | L34: 0.0186 | M34: 0 | N34: 1 | O34: 0 | Q34: 45944 | R34: 47405 | S34: 1180 | U34: Cat Bond | V34: Mezz | W34: 1 | AB34: 0 | AC34: 0 | AD34: 64703043 | AE34: 499999.5 | AF34: 499999.5 | AG34: 500000 | AI34: 0 | AL34: 107.75 | AM34: 0.14378454 | AN34: Buy | AO34: 45944 | AP34: 0 | AR34: 0.00111111 | AS34: 0 | AT34: 0 | AU34: 0.09221209 | AV34: 0 | AW34: 71892.198 | AX34: 399999.6 | AY34: 538749.46 | AZ34: 8423.271 | BA34: 63203.523 | BB34: 0 | BC34: 0 | BD34: 0 | BE34: 0 | BF34: 0 | BG34: 499999.5 | BH34: 499999.5 | BI34: 499999.5 | BJ34: 0.9819 | BK34: 0.020833312 | BL34: 0 | BM34: Breached | BN34: 0 | BO34: 0 | BP34: 0 | BQ34: 499999.5 | BR34: 0 | BS34: 0 | BT34: 0.1171653 | BU34: 224999.78 | BV34: 63468.927 | BW34: 0.2820844 | BX34: 0.8828347 | BY34: 0 | BZ34: 0 | CA34: 0 | CB34: 45944 | CC34: 45944 | CG34: Indemnity | CH34: Occurrence
A35: 28 | B35: CB-Fish Pond Re Ltd. Series 2024-1 Class A Reset 2025 | D35: 2024-1 | E35: Class A | F35: 2025 | H35: LOD | I35: 33774EAA2 | J35: 0 | L35: 0.0025 | M35: 0.0008 | N35: 1 | O35: 0 | Q35: 45756 | R35: 47217 | S35: 992 | U35: Cat Bond | V35: Mezz | W35: 1 | AB35: 0 | AC35: 0 | AD35: 20094000 | AE35: 249999.45 | AF35: 249999.45 | AG35: 250000 | AI35: 0 | AL35: 102.3 | AM35: 0.0788 | AN35: Buy | AO35: 45756 | AP35: 0 | AR35: 0.00098039 | AS35: 0 | AT35: 0 | AU35: 0.06796396 | AV35: 0 | AW35: 19699.957 | AX35: 0 | AY35: 255749.44 | AZ35: 407.35961 | BA35: 9001.9859 | BB35: 0 | BC35: 0 | BD35: 0 | BE35: 0 | BF35: 0 | BG35: 0 | BH35: 0 | BI35: 97412.905 | BJ35: 0.9976 | BK35: 0.010416644 | BL35: 0 | BM35: Breached | BN35: 0 | BO35: 0 | BP35: 0 | BQ35: 249999.45 | BR35: 0 | BS35: 0 | BT35: 0.020678198 | BU35: 13351.734 | BV35: 19292.597 | BW35: 1.4449507 | BX35: 0.9793218 | BY35: 0 | BZ35: 0 | CA35: 0 | CB35: 45756 | CC35: 45756 | CG35: Indemnity | CH35: Occurrence
A36: 29 | B36: CB-Mountain Re Ltd. Series 2023-1 Class A Reset 2025 | D36: 2023-1 | E36: Class A | F36: 2025 | H36: LOD | I36: 62426LAA7 | J36: 0 | L36: 0.0261 | M36: 0 | N36: 1 | O36: 0 | Q36: 45866 | R36: 47327 | S36: 1102 | U36: Cat Bond | V36: Mezz | W36: 1 | AB36: 0 | AC36: 0 | AD36: 11660000 | AE36: 250000.3 | AF36: 250000.3 | AG36: 250000 | AI36: 0 | AL36: 103.1 | AM36: 0.106 | AN36: Buy | AO36: 45866 | AP36: 0 | AR36: 0.00227273 | AS36: 0 | AT36: 0 | AU36: 0.07152062 | AV36: 0 | AW36: 26500.032 | AX36: 151542.83 | AY36: 257750.31 | AZ36: 2418.0766 | BA36: 20263.852 | BB36: 0 | BC36: 0 | BD36: 0 | BE36: 0 | BF36: 16828.871 | BG36: 47300.586 | BH36: 91898.997 | BI36: 250000.3 | BJ36: 0.9812 | BK36: 0.010416679 | BL36: 0 | BM36: Breached | BN36: 0 | BO36: 0 | BP36: 0 | BQ36: 250000.3 | BR36: 0 | BS36: 0 | BT36: 0.091248063 | BU36: 114766.62 | BV36: 24081.955 | BW36: 0.20983415 | BX36: 0.90875194 | BY36: 0 | BZ36: 0 | CA36: 0 | CB36: 45866 | CC36: 45866 | CG36: Indemnity | CH36: Occurrence
A37: 30 | B37: CB-Palm Re Ltd. Series 2024-1 Class A Reset 2025 | D37: 2024-1 | E37: Class A | F37: 2025 | H37: LOD | I37: 69664FAA6 | J37: 0 | L37: 0.0402 | M37: 0 | N37: 1 | O37: 0 | Q37: 45791 | R37: 47252 | S37: 1027 | U37: Cat Bond | V37: Equity | W37: 1 | AB37: 0 | AC37: 0 | AD37: 20251080 | AE37: 250000.5 | AF37: 250000.5 | AG37: 250000 | AI37: 0 | AL37: 102.85 | AM37: 0.1350072 | AN37: Buy | AO37: 45791 | AP37: 0 | AR37: 0.00166667 | AS37: 0 | AT37: 0 | AU37: 0.1189812 | AV37: 0 | AW37: 33751.868 | AX37: 225000.45 | AY37: 257125.51 | AZ37: 7180.8745 | BA37: 40146.515 | BB37: 0 | BC37: 0 | BD37: 0 | BE37: 880.47174 | BF37: 250000.5 | BG37: 250000.5 | BH37: 250000.5 | BI37: 250000.5 | BJ37: 0.9674 | BK37: 0.010416688 | BL37: 0 | BM37: Breached | BN37: 0 | BO37: 0 | BP37: 0 | BQ37: 250000.5 | BR37: 0 | BS37: 0 | BT37: 0.21275488 | BU37: 116026.33 | BV37: 26570.993 | BW37: 0.2290083 | BX37: 0.78724512 | BY37: 0 | BZ37: 0 | CA37: 0 | CB37: 45791 | CC37: 45791 | CG37: Indemnity | CH37: Occurrence
A38: 31 | B38: CB-Winston Re Ltd. Series 2024-1 Class A Reset 2025 | D38: 2024-1 | E38: Class A | F38: 2025 | H38: LOD | I38: 975660AA9 | J38: 0 | L38: 0.0269 | M38: 0.0205 | N38: 1 | O38: 0 | Q38: 45939 | R38: 47400 | S38: 1175 | U38: Cat Bond | V38: Mezz | W38: 1 | AB38: 0 | AC38: 0 | AD38: 35175000 | AE38: 250000 | AF38: 250000 | AG38: 250000 | AI38: 0 | AL38: 107.85 | AM38: 0.1407 | AN38: Buy | AO38: 45939 | AP38: 0 | AR38: 0.001 | AS38: 0 | AT38: 0 | AU38: 0.08123702 | AV38: 0 | AW38: 35175 | AX38: 207327.99 | AY38: 269625 | AZ38: 5917.4409 | BA38: 37139.146 | BB38: 0 | BC38: 0 | BD38: 0 | BE38: 0 | BF38: 250000 | BG38: 250000 | BH38: 250000 | BI38: 250000 | BJ38: 0.9743 | BK38: 0.010416667 | BL38: 0 | BM38: Breached | BN38: 0 | BO38: 0 | BP38: 0 | BQ38: 250000 | BR38: 0 | BS38: 0 | BT38: 0.1682286 | BU38: 109771.3 | BV38: 29257.559 | BW38: 0.26653196 | BX38: 0.8317714 | BY38: 0 | BZ38: 0 | CA38: 0 | CB38: 45939 | CC38: 45939 | CG38: Indemnity | CH38: Occurrence
A39: 32 | B39: CB-Winston Re Ltd. Series 2024-1 Class B Reset 2025 | D39: 2024-1 | E39: Class B | F39: 2025 | H39: LOD | I39: 975660AB7 | J39: 0 | L39: 0.0326 | M39: 0.0269 | N39: 1 | O39: 0 | Q39: 45939 | R39: 47400 | S39: 1175 | U39: Cat Bond | V39: Mezz | W39: 1 | AB39: 0 | AC39: 0 | AD39: 23325000 | AE39: 250000.5 | AF39: 250000.5 | AG39: 250000 | AI39: 0 | AL39: 108.35 | AM39: 0.1555 | AN39: Buy | AO39: 45939 | AP39: 0 | AR39: 0.00166667 | AS39: 0 | AT39: 0 | AU39: 0.09178093 | AV39: 0 | AW39: 38875.078 | AX39: 225000.45 | AY39: 270875.54 | AZ39: 7315.5323 | BA39: 41391.509 | BB39: 0 | BC39: 0 | BD39: 0 | BE39: 0 | BF39: 250000.5 | BG39: 250000.5 | BH39: 250000.5 | BI39: 250000.5 | BJ39: 0.9684 | BK39: 0.010416688 | BL39: 0 | BM39: Breached | BN39: 0 | BO39: 0 | BP39: 0 | BQ39: 250000.5 | BR39: 0 | BS39: 0 | BT39: 0.18818052 | BU39: 117500.24 | BV39: 31559.545 | BW39: 0.26859134 | BX39: 0.81181948 | BY39: 0 | BZ39: 0 | CA39: 0 | CB39: 45939 | CC39: 45939 | CG39: Indemnity | CH39: Occurrence
A40: 33 | B40: CB-Winston Re Ltd. Series 2025-1 Class A | D40: 2025-1 | E40: Class A | H40: LOD | I40: 975660AC5 | J40: 0 | L40: 0.017 | M40: 0.0144 | N40: 1 | O40: 0 | Q40: 45784 | R40: 47245 | S40: 1020 | U40: Cat Bond | V40: Equity | W40: 1 | AB40: 0 | AC40: 0 | AD40: 18130000 | AE40: 249999.75 | AF40: 249999.75 | AG40: 250000 | AI40: 0 | AL40: 99.85 | AM40: 0.1036 | AN40: Buy | AO40: 45784 | AP40: 0 | AR40: 0.00142857 | AS40: 0 | AT40: 0 | AU40: 0.10708342 | AV40: 0 | AW40: 25899.974 | AX40: 182488.72 | AY40: 249624.75 | AZ40: 3909.5975 | BA40: 30579.134 | BB40: 0 | BC40: 0 | BD40: 0 | BE40: 0 | BF40: 0 | BG40: 249999.75 | BH40: 249999.75 | BI40: 249999.75 | BJ40: 0.9833 | BK40: 0.010416656 | BL40: 0 | BM40: Breached | BN40: 0 | BO40: 0 | BP40: 0 | BQ40: 249999.75 | BR40: 0 | BS40: 0 | BT40: 0.15094986 | BU40: 98183.387 | BV40: 21990.377 | BW40: 0.22397248 | BX40: 0.84905014 | BY40: 0 | BZ40: 0 | CA40: 0 | CB40: 45784 | CC40: 45784 | CG40: Indemnity | CH40: Occurrence
A41: 34 | B41: CB-Acorn Re Ltd. Series 2023-1 Class A | D41: 2023-1 | E41: Class A | H41: LOD | I41: 00485YAD1 | J41: 0 | L41: 0.0097 | M41: 0.006 | N41: 1 | O41: 0 | Q41: 45763 | R41: 47224 | S41: 999 | U41: Cat Bond | V41: Mezz | W41: 1 | AB41: 0 | AC41: 0 | AD41: 12276488 | AE41: 250000.5 | AF41: 250000.5 | AG41: 250000 | AI41: 0 | AL41: 102.4 | AM41: 0.08184325 | AN41: Buy | AO41: 45763 | AP41: 0 | AR41: 0.00166667 | AS41: 0 | AT41: 0 | AU41: 0.06899432 | AV41: 0 | AW41: 20460.853 | AX41: 0 | AY41: 256000.51 | AZ41: 1946.8789 | BA41: 20829.125 | BB41: 0 | BC41: 0 | BD41: 0 | BE41: 0 | BF41: 0 | BG41: 0 | BH41: 0 | BI41: 250000.5 | BJ41: 0.9903 | BK41: 0.010416688 | BL41: 0 | BM41: Breached | BN41: 0 | BO41: 0 | BP41: 0 | BQ41: 250000.5 | BR41: 0 | BS41: 0 | BT41: 0.095151402 | BU41: 21562.543 | BV41: 18513.975 | BW41: 0.85861739 | BX41: 0.9048486 | BY41: 0 | BZ41: 0 | CA41: 0 | CB41: 45763 | CC41: 45763 | CG41: Indemnity | CH41: Occurrence
A42: 35 | B42: CB-Ursa Re Ltd. Series 2023-3 Class AA Reset 2024 | D42: 2023-3 | E42: Class AA | F42: 2024 | H42: LOD | I42: 90323WAP5 | J42: 0 | L42: 0.0085 | M42: 0.0077 | N42: 1 | O42: 0 | Q42: 45751 | R42: 47212 | S42: 987 | U42: Cat Bond | V42: Mezz | W42: 1 | AB42: 0 | AC42: 0 | AD42: 28080000 | AE42: 249999 | AF42: 249999 | AG42: 250000 | AI42: 0 | AL42: 103.95 | AM42: 0.0936 | AN42: Buy | AO42: 45751 | AP42: 0 | AR42: 0.00083333 | AS42: 0 | AT42: 0 | AU42: 0.0712207 | AV42: 0 | AW42: 23399.906 | AX42: 0 | AY42: 259873.96 | AZ42: 2019.6865 | BA42: 22128.2 | BB42: 0 | BC42: 0 | BD42: 0 | BE42: 0 | BF42: 0 | BG42: 0 | BH42: 0 | BI42: 249999 | BJ42: 0.9915 | BK42: 0.010416625 | BL42: 0 | BM42: Breached | BN42: 0 | BO42: 0 | BP42: 0 | BQ42: 249999 | BR42: 0 | BS42: 0 | BT42: 0.086311733 | BU42: 27499.89 | BV42: 21380.22 | BW42: 0.77746565 | BX42: 0.91368827 | BY42: 0 | BZ42: 0 | CA42: 0 | CB42: 45751 | CC42: 45751 | CG42: Indemnity | CH42: Occurrence
A43: 36 | B43: CB-Foundation Re IV Ltd. Series 2023-1 Class A Reset 2025 | D43: 2023-1 | E43: Class A | F43: 2025 | H43: LOD | I43: 349939AA6 | J43: 0 | L43: 0.0176 | M43: 0 | N43: 1 | O43: 0 | Q43: 45770 | R43: 47231 | S43: 1006 | U43: Cat Bond | V43: Mezz | W43: 1 | AB43: 0 | AC43: 0 | AD43: 20260000 | AE43: 250000 | AF43: 250000 | AG43: 250000 | AI43: 0 | AL43: 103.1 | AM43: 0.1013 | AN43: Buy | AO43: 45770 | AP43: 0 | AR43: 0.00125 | AS43: 0 | AT43: 0 | AU43: 0.08468446 | AV43: 0 | AW43: 25325 | AX43: 224201.9 | AY43: 257750 | AZ43: 3592.3577 | BA43: 28646.096 | BB43: 0 | BC43: 0 | BD43: 0 | BE43: 0 | BF43: 0 | BG43: 175034.95 | BH43: 250000 | BI43: 250000 | BJ43: 0.9829 | BK43: 0.010416667 | BL43: 0 | BM43: Breached | BN43: 0 | BO43: 0 | BP43: 0 | BQ43: 250000 | BR43: 0 | BS43: 0 | BT43: 0.14185025 | BU43: 172184.51 | BV43: 21732.642 | BW43: 0.12621718 | BX43: 0.85814975 | BY43: 0 | BZ43: 0 | CA43: 0 | CB43: 45770 | CC43: 45770 | CG43: Indemnity | CH43: Occurrence
A44: 37 | B44: CB-Foundation Re IV Ltd. Series 2023-1 Class A Reset 2025 | D44: 2023-1 | E44: Class A | F44: 2025 | H44: LOD | I44: 349939AA6 | J44: 0 | L44: 0.0176 | M44: 0 | N44: 1 | O44: 0 | Q44: 45889 | R44: 47350 | S44: 1125 | U44: Cat Bond | V44: Mezz | W44: 1 | AB44: 0 | AC44: 0 | AD44: 20260000 | AE44: 250000 | AF44: 250000 | AG44: 250000 | AI44: 0 | AL44: 103.6 | AM44: 0.1013 | AN44: Buy | AO44: 45889 | AP44: 0 | AR44: 0.00125 | AS44: 0 | AT44: 0 | AU44: 0.07647726 | AV44: 0 | AW44: 25325 | AX44: 224201.9 | AY44: 259000 | AZ44: 3592.3577 | BA44: 28646.096 | BB44: 0 | BC44: 0 | BD44: 0 | BE44: 0 | BF44: 0 | BG44: 175034.95 | BH44: 250000 | BI44: 250000 | BJ44: 0.9829 | BK44: 0.010416667 | BL44: 0 | BM44: Breached | BN44: 0 | BO44: 0 | BP44: 0 | BQ44: 250000 | BR44: 0 | BS44: 0 | BT44: 0.14185025 | BU44: 172184.51 | BV44: 21732.642 | BW44: 0.12621718 | BX44: 0.85814975 | BY44: 0 | BZ44: 0 | CA44: 0 | CB44: 45889 | CC44: 45889 | CG44: Indemnity | CH44: Occurrence
A45: 38 | B45: CB-Wrigley Re Ltd. Series 2023-1 Class A Reset 2025 | D45: 2023-1 | E45: Class A | F45: 2025 | H45: LOD | I45: 982533AB7 | J45: 0 | L45: 0.007 | M45: 0 | N45: 1 | O45: 0 | Q45: 45777 | R45: 47238 | S45: 1013 | U45: Cat Bond | V45: Mezz | W45: 1 | AB45: 0 | AC45: 0 | AD45: 10080000 | AE45: 250000 | AF45: 250000 | AG45: 250000 | AI45: 0 | AL45: 101.95 | AM45: 0.1008 | AN45: Buy | AO45: 45777 | AP45: 0 | AR45: 0.0025 | AS45: 0 | AT45: 0 | AU45: 0.08695043 | AV45: 0 | AW45: 25200 | AX45: 54489.477 | AY45: 254875 | AZ45: 962.1995 | BA45: 13617.281 | BB45: 0 | BC45: 0 | BD45: 0 | BE45: 0 | BF45: 0 | BG45: 0 | BH45: 0 | BI45: 233793.04 | BJ45: 0.9938 | BK45: 0.010416667 | BL45: 0 | BM45: Breached | BN45: 0 | BO45: 0 | BP45: 0 | BQ45: 250000 | BR45: 0 | BS45: 0 | BT45: 0.03818252 | BU45: 17383.361 | BV45: 24237.8 | BW45: 1.3943104 | BX45: 0.96181748 | BY45: 0 | BZ45: 0 | CA45: 0 | CB45: 45777 | CC45: 45777 | CG45: Indemnity | CH45: Occurrence
A46: 39 | B46: CB-Fuchsia 2 Series 2024-1 Class A Reset 2025 | D46: 2024-1 | E46: Class A | F46: 2025 | H46: LOD | I46: 541917AA8 | J46: 0 | L46: 0.015 | M46: 0.0092 | N46: 1 | O46: 0 | Q46: 45755 | R46: 47216 | S46: 991 | U46: Cat Bond | V46: Mezz | W46: 1 | AB46: 0 | AC46: 0 | AD46: 17980000 | AE46: 250000 | AF46: 250000 | AG46: 250000 | AI46: 0 | AL46: 100.65 | AM46: 0.0899 | AN46: Buy | AO46: 45755 | AP46: 0 | AR46: 0.00125 | AS46: 0 | AT46: 0 | AU46: 0.09042534 | AV46: 0 | AW46: 22475 | AX46: 200000 | AY46: 251625 | AZ46: 2970.2306 | BA46: 25886.926 | BB46: 0 | BC46: 0 | BD46: 0 | BE46: 0 | BF46: 0 | BG46: 75931.154 | BH46: 212102.31 | BI46: 250000 | BJ46: 0.9855 | BK46: 0.010416667 | BL46: 0 | BM46: Breached | BN46: 0 | BO46: 0 | BP46: 0 | BQ46: 250000 | BR46: 0 | BS46: 0 | BT46: 0.13215709 | BU46: 106438.55 | BV46: 19504.769 | BW46: 0.1832491 | BX46: 0.86784291 | BY46: 0 | BZ46: 0 | CA46: 0 | CB46: 45755 | CC46: 45755 | CG46: Indemnity | CH46: Occurrence
A47: 40 | B47: CB-Montoya Re Ltd. Series 2025-1 Class B Reset 2025 | D47: 2025-1 | E47: Class B | F47: 2025 | H47: LOD | I47: 613752AE4 | J47: 0 | L47: 0.0334 | M47: 0.0313 | N47: 1 | O47: 0 | Q47: 45751 | R47: 47212 | S47: 987 | U47: Cat Bond | V47: Equity | W47: 1 | AB47: 0 | AC47: 0 | AD47: 3123216 | AE47: 249999.9 | AF47: 249999.9 | AG47: 250000 | AI47: 0 | AL47: 100.2 | AM47: 0.1041072 | AN47: Buy | AO47: 45751 | AP47: 0 | AR47: 0.00833333 | AS47: 0 | AT47: 0 | AU47: 0.10300053 | AV47: 0 | AW47: 26026.79 | AX47: 99999.96 | AY47: 250499.9 | AZ47: 7224.1726 | BA47: 40913.053 | BB47: 0 | BC47: 0 | BD47: 0 | BE47: 0 | BF47: 249999.9 | BG47: 249999.9 | BH47: 249999.9 | BI47: 249999.9 | BJ47: 0.9684 | BK47: 0.010416662 | BL47: 0 | BM47: Breached | BN47: 0 | BO47: 0 | BP47: 0 | BQ47: 249999.9 | BR47: 0 | BS47: 0 | BT47: 0.27756679 | BU47: 84167.768 | BV47: 18802.617 | BW47: 0.22339451 | BX47: 0.72243321 | BY47: 0 | BZ47: 0 | CA47: 0 | CB47: 45751 | CC47: 45751 | CG47: Indemnity | CH47: Occurrence
A48: 41 | B48: CB-Alamo Re Ltd. Series 2023-1 Class A Reset 2025 | D48: 2023-1 | E48: Class A | F48: 2025 | H48: LOD | I48: 011395AJ9 | J48: 0 | L48: 0.0312 | M48: 0 | N48: 1 | O48: 0 | Q48: 45789 | R48: 47250 | S48: 1025 | U48: Cat Bond | V48: Equity | W48: 1 | AB48: 0 | AC48: 0 | AD48: 64650000 | AE48: 250000 | AF48: 250000 | AG48: 250000 | AI48: 0 | AL48: 102.5 | AM48: 0.1293 | AN48: Buy | AO48: 45789 | AP48: 0 | AR48: 0.0005 | AS48: 0 | AT48: 0 | AU48: 0.10738033 | AV48: 0 | AW48: 32325 | AX48: 50000 | AY48: 256250 | AZ48: 6860.181 | BA48: 40030.556 | BB48: 0 | BC48: 0 | BD48: 0 | BE48: 0 | BF48: 250000 | BG48: 250000 | BH48: 250000 | BI48: 250000 | BJ48: 0.9703 | BK48: 0.010416667 | BL48: 0 | BM48: Breached | BN48: 0 | BO48: 0 | BP48: 0 | BQ48: 250000 | BR48: 0 | BS48: 0 | BT48: 0.21222524 | BU48: 42500 | BV48: 25464.819 | BW48: 0.59917221 | BX48: 0.78777476 | BY48: 0 | BZ48: 0 | CA48: 0 | CB48: 45789 | CC48: 45789 | CG48: Indemnity | CH48: Occurrence
A49: 42 | B49: CB-Alamo Re Ltd. Series 2024-1 Class C Reset 2025 | D49: 2024-1 | E49: Class C | F49: 2025 | H49: LOD | I49: 011395AQ3 | J49: 0 | L49: 0.0596 | M49: 0 | N49: 1 | O49: 0 | Q49: 45929 | R49: 47390 | S49: 1165 | U49: Cat Bond | V49: Mezz | W49: 1 | AB49: 0 | AC49: 0 | AD49: 62920000 | AE49: 250000 | AF49: 250000 | AG49: 250000 | AI49: 0 | AL49: 105.2 | AM49: 0.1573 | AN49: Buy | AO49: 45929 | AP49: 0 | AR49: 0.000625 | AS49: 0 | AT49: 0 | AU49: 0.08161725 | AV49: 0 | AW49: 39325 | AX49: 58972.76 | AY49: 263000 | AZ49: 10708.708 | BA49: 47574.124 | BB49: 0 | BC49: 0 | BD49: 61876.887 | BE49: 136414.31 | BF49: 250000 | BG49: 250000 | BH49: 250000 | BI49: 250000 | BJ49: 0.9471 | BK49: 0.010416667 | BL49: 0 | BM49: Breached | BN49: 0 | BO49: 0 | BP49: 0 | BQ49: 250000 | BR49: 0 | BS49: 0 | BT49: 0.27231299 | BU49: 46318.214 | BV49: 28616.292 | BW49: 0.61781941 | BX49: 0.72768701 | BY49: 0 | BZ49: 0 | CA49: 0 | CB49: 45929 | CC49: 45929 | CG49: Indemnity | CH49: Occurrence
A50: 43 | B50: CB-Titania Re Ltd. Series 2023-1 Class A Reset 2025 | D50: 2023-1 | E50: Class A | F50: 2025 | H50: LOD | I50: 888329AC3 | J50: 0 | L50: 0.0482 | M50: 0 | N50: 1 | O50: 0 | Q50: 45793 | R50: 47254 | S50: 1029 | U50: Cat Bond | V50: Equity | W50: 1 | AB50: 0 | AC50: 0 | AD50: 12742500 | AE50: 249999.75 | AF50: 249999.75 | AG50: 250000 | AI50: 0 | AL50: 103.75 | AM50: 0.1699 | AN50: Buy | AO50: 45793 | AP50: 0 | AR50: 0.00333333 | AS50: 0 | AT50: 0 | AU50: 0.12294792 | AV50: 0 | AW50: 42474.958 | AX50: 249999.75 | AY50: 259374.74 | AZ50: 11088.686 | BA50: 50713.27 | BB50: 0 | BC50: 0 | BD50: 0 | BE50: 249999.75 | BF50: 249999.75 | BG50: 249999.75 | BH50: 249999.75 | BI50: 249999.75 | BJ50: 0.9533 | BK50: 0.010416656 | BL50: 0 | BM50: Breached | BN50: 0 | BO50: 0 | BP50: 0 | BQ50: 249999.75 | BR50: 0 | BS50: 0 | BT50: 0.26106409 | BU50: 207537.5 | BV50: 31386.271 | BW50: 0.15123181 | BX50: 0.73893591 | BY50: 0 | BZ50: 0 | CA50: 0 | CB50: 45793 | CC50: 45793 | CG50: Indemnity | CH50: Occurrence
A51: 44 | B51: CB-Res Re 2025 Ltd. Series 2025-II Class 2 | D51: 2025-II | E51: Class 2 | H51: LOD | I51: 76091JAA6 | J51: 0 | L51: 0.0979 | M51: 0.0535 | N51: 1 | O51: 0 | Q51: 45947 | R51: 47408 | S51: 1183 | U51: Cat Bond | V51: Equity | W51: 1 | AB51: 0 | AC51: 0 | AD51: 28101440 | AE51: 250000 | AF51: 250000 | AG51: 250000 | AI51: 0 | AL51: 100 | AM51: 0.1405072 | AN51: Buy | AO51: 45947 | AP51: 0 | AR51: 0.00125 | AS51: 0 | AT51: 0 | AU51: 0.1405063 | AV51: 0 | AW51: 35126.8 | AX51: 250000 | AY51: 250000 | AZ51: 18015.408 | BA51: 61118.345 | BB51: 0 | BC51: 0 | BD51: 250000 | BE51: 250000.01 | BF51: 250000.01 | BG51: 250000.01 | BH51: 250000.01 | BI51: 250000.01 | BJ51: 0.9118 | BK51: 0.010416667 | BL51: 0 | BM51: Breached | BN51: 0 | BO51: 0 | BP51: 0 | BQ51: 250000 | BR51: 0 | BS51: 0 | BT51: 0.51286791 | BU51: 232111.28 | BV51: 17111.392 | BW51: 0.073720639 | BX51: 0.48713209 | BY51: 0 | BZ51: 0 | CA51: 0 | CB51: 45947 | CC51: 45947 | CG51: Indemnity | CH51: Occurrence
A52: 45 | B52: CB-Four Lakes Re Ltd. Series 2023-1 Class B Reset 2025_V12 | D52: 2023-1 | E52: Class B | F52: 2025 | H52: LOD | I52: 35087TAF5 | J52: 0 | L52: 0.0327 | M52: 0 | N52: 1 | O52: 0 | Q52: 45805 | R52: 47266 | S52: 1041 | U52: Cat Bond | V52: Equity | W52: 1 | AB52: 0 | AC52: 0 | AD52: 6390000 | AE52: 250000 | AF52: 250000 | AG52: 250000 | AI52: 0 | AL52: 101.6 | AM52: 0.1278 | AN52: Buy | AO52: 45805 | AP52: 0 | AR52: 0.005 | AS52: 0 | AT52: 0 | AU52: 0.11989819 | AV52: 0 | AW52: 31950 | AX52: 207911.09 | AY52: 254000 | AZ52: 5328.447 | BA52: 33347.372 | BB52: 0 | BC52: 0 | BD52: 0 | BE52: 0 | BF52: 125831.56 | BG52: 249999.99 | BH52: 249999.99 | BI52: 249999.99 | BJ52: 0.9705 | BK52: 0.010416667 | BL52: 0 | BM52: Breached | BN52: 0 | BO52: 0 | BP52: 0 | BQ52: 250000 | BR52: 0 | BS52: 0 | BT52: 0.16677455 | BU52: 149397.25 | BV52: 26621.553 | BW52: 0.17819306 | BX52: 0.83322545 | BY52: 0 | BZ52: 0 | CA52: 0 | CB52: 45805 | CC52: 45805 | CG52: Indemnity | CH52: Occurrence
A53: 46 | B53: CB-FloodSmart Re Ltd. Series 2024-1 Class A Reset 2025 | C53: NFIP | D53: 2024-1 | E53: Class A | F53: 2025 | H53: LOD | I53: 33975CAP0 | J53: 0 | L53: 0.0876 | M53: 0.0678 | N53: 1 | O53: 0 | Q53: 45358 | R53: 46458 | S53: 239 | U53: Cat Bond | V53: Equity | W53: 1 | AB53: 0 | AC53: 2000000000 | AD53: 86307500 | AE53: 250002 | AF53: 250002 | AG53: 250000 | AI53: 0 | AL53: 102.8 | AM53: 0.1817 | AN53: Buy | AO53: 45834 | AP53: 0 | AR53: 0.00052632 | AS53: 0.14337499 | AT53: 0 | AU53: 0.16562575 | AV53: 0 | AW53: 45425.363 | AX53: 183276.97 | AY53: 257002.06 | AZ53: 19510.311 | BA53: 65472.041 | BB53: 0 | BC53: 0 | BD53: 250002 | BE53: 250002 | BF53: 250002 | BG53: 250002 | BH53: 250002 | BI53: 250002 | BJ53: 0.9155 | BK53: 0.099290476 | BL53: 0 | BM53: Breached | BN53: 0 | BO53: 0 | BP53: 0 | BQ53: 250002 | BR53: 0 | BS53: 0 | BT53: 0.42950259 | BU53: 153672.34 | BV53: 25915.052 | BW53: 0.16863837 | BX53: 0.57049741 | BY53: 0 | BZ53: 0 | CA53: 0 | CB53: 45834 | CC53: 45834 | CG53: Indemnity | CH53: Occurrence
A54: 47 | B54: CB-Foundation Re IV Ltd. Series 2023-1 Class A Reset 2025 | C54: Hartford | D54: 2023-1 | E54: Class A | F54: 2025 | H54: LOD | I54: 349939AA6 | J54: 0 | L54: 0.0176 | M54: 0 | N54: 1 | O54: 0 | Q54: 45287 | R54: 46395 | S54: 176 | U54: Cat Bond | V54: Mezz | W54: 1 | AB54: 0 | AC54: 301000000 | AD54: 20180000 | AE54: 250000 | AF54: 250000 | AG54: 250000 | AI54: 0 | AL54: 103.1 | AM54: 0.1009 | AN54: Buy | AO54: 45770 | AP54: 0 | AR54: 0.00125 | AS54: 0.06234414 | AT54: 0 | AU54: 0.08468147 | AV54: 0 | AW54: 25225 | AX54: 206719.34 | AY54: 257750 | AZ54: 3592.3577 | BA54: 28646.096 | BB54: 0 | BC54: 0 | BD54: 0 | BE54: 0 | BF54: 0 | BG54: 175034.95 | BH54: 250000 | BI54: 250000 | BJ54: 0.9829 | BK54: 0.099289682 | BL54: 0 | BM54: Breached | BN54: 0 | BO54: 0 | BP54: 0 | BQ54: 250000 | BR54: 0 | BS54: 0 | BT54: 0.14241259 | BU54: 105601.1 | BV54: 21632.642 | BW54: 0.20485243 | BX54: 0.85758741 | BY54: 0 | BZ54: 0 | CA54: 0 | CB54: 45770 | CC54: 45770 | CG54: Indemnity | CH54: Occurrence
A55: 48 | B55: CB-Foundation Re IV Ltd. Series 2023-1 Class A Reset 2025 | C55: Hartford | D55: 2023-1 | E55: Class A | F55: 2025 | H55: LOD | I55: 349939AA6 | J55: 0 | L55: 0.0176 | M55: 0 | N55: 1 | O55: 0 | Q55: 45287 | R55: 46395 | S55: 176 | U55: Cat Bond | V55: Mezz | W55: 1 | AB55: 0 | AC55: 301000000 | AD55: 20180000 | AE55: 250000 | AF55: 250000 | AG55: 250000 | AI55: 0 | AL55: 103.6 | AM55: 0.1009 | AN55: Buy | AO55: 45889 | AP55: 0 | AR55: 0.00125 | AS55: 0.06234414 | AT55: 0 | AU55: 0.07647726 | AV55: 0 | AW55: 25225 | AX55: 206719.34 | AY55: 259000 | AZ55: 3592.3577 | BA55: 28646.096 | BB55: 0 | BC55: 0 | BD55: 0 | BE55: 0 | BF55: 0 | BG55: 175034.95 | BH55: 250000 | BI55: 250000 | BJ55: 0.9829 | BK55: 0.099289682 | BL55: 0 | BM55: Breached | BN55: 0 | BO55: 0 | BP55: 0 | BQ55: 250000 | BR55: 0 | BS55: 0 | BT55: 0.14241259 | BU55: 105601.1 | BV55: 21632.642 | BW55: 0.20485243 | BX55: 0.85758741 | BY55: 0 | BZ55: 0 | CA55: 0 | CB55: 45889 | CC55: 45889 | CG55: Indemnity | CH55: Occurrence
